Workbook

Sheet MASTER
A1: DASHBOARD CONSOLIDADO - GRUPO DELGA 2026
A2: Atualizado: | B2: 13/01/2026 | D2: Semana:
A4: VISÃO GERAL - BIG NUMBERS
A5: META ANUAL | C5: REALIZADO YTD | E5: % ATINGIMENTO | G5: GAP | I5: PROJETOS ATIVOS | K5: KAIZENS
A6: R$ 50,32 Mi | C6: R$ 0 | E6: 0% | G6: R$ 50,32 Mi | I6: 0 | K6: 0
A8: SAVING POR FONTE
A9: FONTE | B9: META | C9: REALIZADO | D9: % ATING. | E9: GAP | F9: STATUS
A10: Diadema | B10: 6947000 | C10: 0 | D10: =IF(B10=0,0,C10/B10) -> 0 | E10: =B10-C10 -> 6947000
A11: Ferraz | B11: 13367000 | C11: 0 | D11: =IF(B11=0,0,C11/B11) -> 0 | E11: =B11-C11 -> 13367000
A12: São Leopoldo | B12: 2100000 | C12: 0 | D12: =IF(B12=0,0,C12/B12) -> 0 | E12: =B12-C12 -> 2100000
A13: Jarinu | B13: 5356000 | C13: 0 | D13: =IF(B13=0,0,C13/B13) -> 0 | E13: =B13-C13 -> 5356000
A14: Anchieta | B14: 3841000 | C14: 0 | D14: =IF(B14=0,0,C14/B14) -> 0 | E14: =B14-C14 -> 3841000
A15: Compras | B15: 7000000 | C15: 0 | D15: =IF(B15=0,0,C15/B15) -> 0 | E15: =B15-C15 -> 7000000
A16: Vendas | B16: 10000000 | C16: 0 | D16: =IF(B16=0,0,C16/B16) -> 0 | E16: =B16-C16 -> 10000000
A17: Corporativo | B17: 1709000
A18: TOTAL | B18: =SUM(B10:B16) -> 48611000 | C18: =SUM(C10:C16) -> 0 | D18: =IF(B18=0,0,C18/B18) -> 0 | E18: =B18-C18 -> 48611000
A20: KPIs OPERACIONAIS - COMPARATIVO UNIDADES
A21: KPI | B21: META | C21: DIADEMA | D21: FERRAZ | E21: SÃO LEOPOLDO | F21: JARINU | G21: ANCHIETA | H21: MÉDIA | I21: STATUS
H22: =AVERAGE(C22:G22) -> #DIV/0!
H23: =AVERAGE(C23:G23) -> #DIV/0!
H24: =AVERAGE(C24:G24) -> #DIV/0!
H25: =AVERAGE(C25:G25) -> #DIV/0!
H26: =AVERAGE(C26:G26) -> #DIV/0!
H27: =AVERAGE(C27:G27) -> #DIV/0!
H28: =AVERAGE(C28:G28) -> #DIV/0!
H29: =AVERAGE(C29:G29) -> #DIV/0!
H30: =AVERAGE(C30:G30) -> #DIV/0!
H31: =AVERAGE(C31:G31) -> #DIV/0!
H32: =AVERAGE(C32:G32) -> #DIV/0!
H33: =AVERAGE(C33:G33) -> #DIV/0!
... H37: =AVERAGE(C37:G37) -> #DIV/0!
A40: DESTAQUES DA SEMANA | H40: RISCOS E AÇÕES
A41: 1. | H41: 1.
A42: 2. | H42: 2.
A43: 3. | H43: 3.
A44: 4. | H44: 4.
A45: 5. | H45: 5.

Sheet 5 Unidades  +
D3: DASHBOARD EXECUTIVO - GRUPO DELGA
D4: Gestão Estratégica de Projetos e Redução de Custos | Grupo Delga | 2026
D6: META DO GRUPO | F6: RETORNO PREVISTO | G6: PREVISTO 2026 | H6: 💰 RETORNO VALIDADO | J6: 💰 RETORNO REAL | L6: % ATINGIMENTO DA META | N6: INICIATIVAS | P6: Top 03 Projetos (Maior Retorno REAL até o momento)
D7: =Diadema!A5+Ferraz!A5+'São Leopoldo'!A5+Jarinu!A5+Anchieta!A5+Corporativo!A5+'Compras '!A5+Vendas!A5+'Diretoria Financeira'!A5+'Head Qualidade&Dir. Industrial'!A5 -> 50320000 | F7: =SUM(E23:L23) -> 48275349 | G7: =Diadema!D5+Ferraz!D5+Anchieta!D5+'São Leopoldo'!C26+'São Leopoldo'!D5+Jarinu!C5+'Compras '!E5+Vendas!E5 -> 21759477 | H7: =Diadema!E5+Ferraz!E5+'São Leopoldo'!E5+Jarinu!E5+Anchieta!E5+Corporativo!E5+'Compras '!G5+Vendas!G5+'Diretoria Financeira'!E5+'Head Qualidade&Dir. Industrial'!E5 -> 16843792 | J7: =Diadema!G5+Ferraz!G5+Jarinu!G5+Anchieta!G5+'São Leopoldo'!G5+Vendas!I5+'Compras '!I5+Corporativo!G5 -> 4978229.6 | L7: =J7/D7 -> 0.09893143 | N7: =SUM(J13:J15) -> 204 | P7: ='Top Ganhos '!B2 -> 699813 | Q7: ='Top Ganhos '!C2 -> 08 - Reestruturação | S7: ='Top Ganhos '!D2 -> São leopoldo
P8: ='Top Ganhos '!B3 -> 570440.18 | Q8: ='Top Ganhos '!C3 -> Negociação de preços materiais carcaça Dana | S8: ='Top Ganhos '!D3 -> Compras
P9: ='Top Ganhos '!B4 -> 421900.92 | Q9: ='Top Ganhos '!C4 -> 03 - Consumo de desmoldante | S9: ='Top Ganhos '!D4 -> Ferraz
D11: 📊 SAVING ESPECULADO POR PILAR | I11: 📋 STATUS DAS INICIATIVAS | L11: 🏭 INDICADORES OPERACIONAIS | P11: MATRIZ SPD 5 unidades
D12: Pilar | E12: Qtd. | F12: Saving (R$) | G12: Saving Validado 2026 | H12: % Total | I12: Status | J12: Qtd. | K12: R$ Previsto | L12: Aderência SPD: Unidade | M12: Aderência SPD: Auditado | N12: Análise de Margem | P12: Tipo | Q12: Unidade | R12: Auditado | S12: Meta
D13: Kaizen | E13: =SUM(Diadema!B9,Ferraz!B9,'São Leopoldo'!B9,Jarinu!B9,Anchieta!B9,Corporativo!B9,'Compras '!B9,Vendas!B11,'Diretoria Financeira'!B9,'Head Qualidade&Dir. Industrial'!B9) -> 34 | F13: =SUM(Diadema!C9,Ferraz!C9,'São Leopoldo'!C9,Jarinu!C9,Anchieta!C9,Corporativo!C9,'Compras '!C9,Vendas!C11,'Diretoria Financeira'!C9,'Head Qualidade&Dir. Industrial'!C9) -> 4453440.9 | G13: =Diadema!D9+Anchieta!D9+Jarinu!D9+'São Leopoldo'!D9+Ferraz!D9+'Compras '!D9+Vendas!D11 -> 3647094.9 | H13: =G13/$G$18 -> 0.21652458 | I13: ✓ Concluído | J13: =SUM(Diadema!I9,Ferraz!I9,'São Leopoldo'!I9,Jarinu!I9,Anchieta!I9,Corporativo!H9,'Compras '!H9,Vendas!M11,'Diretoria Financeira'!H9,'Head Qualidade&Dir. Industrial'!H9) -> 67 | K13: =SUM(Diadema!J9,Ferraz!J9,'São Leopoldo'!J9,Jarinu!J9,Anchieta!J9,Corporativo!I9,'Compras '!I9,Vendas!N11,'Diretoria Financeira'!I9,'Head Qualidade&Dir. Industrial'!I9) -> 12917194 | P13: Produtividade e Controle | Q13: =SUM(Diadema!L219,Anchieta!L132,Ferraz!L144,Jarinu!L158,'São Leopoldo'!L152)/5 -> 0.9 | R13: =SUM(Diadema!M219,Anchieta!M132,Ferraz!M144,Jarinu!M158,'São Leopoldo'!M152)/5 -> 0.4 | S13: 1
D14: Redução de Custo | E14: =SUM(Diadema!B10,Ferraz!B10,'São Leopoldo'!B10,Jarinu!B10,Anchieta!B10,Corporativo!B10,'Compras '!B10,Vendas!B12,'Diretoria Financeira'!B10,'Head Qualidade&Dir. Industrial'!B10) -> 114 | F14: =SUM(Diadema!C10,Ferraz!C10,'São Leopoldo'!C10,Jarinu!C10,Anchieta!C10,Corporativo!C10,'Compras '!C10,Vendas!C12,'Diretoria Financeira'!C10,'Head Qualidade&Dir. Industrial'!C10) -> 26091797 | G14: =Diadema!D10+Anchieta!D10+Jarinu!D10+'São Leopoldo'!D10+Ferraz!D10+'Compras '!D10+Vendas!D12 -> 7567605.5 | H14: =G14/$G$18 -> 0.44928158 | I14: ⏳ Em Execução | J14: =SUM(Diadema!I10,Ferraz!I10,'São Leopoldo'!I10,Jarinu!I10,Anchieta!I10,Corporativo!H10,'Compras '!H10,Vendas!M12,'Diretoria Financeira'!H10,'Head Qualidade&Dir. Industrial'!H10) -> 125 | K14: =SUM(Diadema!J10,Ferraz!J10,'São Leopoldo'!J10,Jarinu!J10,Anchieta!J10,Corporativo!I10,'Compras '!I10,Vendas!N12,'Diretoria Financeira'!I10,'Head Qualidade&Dir. Industrial'!I10) -> 23870856 | L14: =AVERAGE(Diadema!K10,Ferraz!K10,'São Leopoldo'!K10:K11,Jarinu!K10,Anchieta!K10) -> 0.72142857 | M14: =AVERAGE(Diadema!L10,Ferraz!L10,'São Leopoldo'!L10:L11,Jarinu!L10,Anchieta!L10) -> 0.32142857 | N14: =AVERAGE(Diadema!M10,Ferraz!M10,'São Leopoldo'!M10,Jarinu!M10,Anchieta!M10) -> 0.25809246 | P14: Documentos e Registro | Q14: =SUM(Diadema!L220,Anchieta!L133,Ferraz!L145,Jarinu!L159,'São Leopoldo'!L153)/5 -> 0.8 | R14: =SUM(Diadema!M220,Anchieta!M133,Ferraz!M145,Jarinu!M159,'São Leopoldo'!M153)/5 -> 0.38333333 | S14: 1
D15: Você Resolve | E15: =SUM(Diadema!B11,Ferraz!B11,'São Leopoldo'!B11,Jarinu!B11,Anchieta!B11,Corporativo!B11,'Compras '!B11,Vendas!B13,'Diretoria Financeira'!B11,'Head Qualidade&Dir. Industrial'!B11) -> 2 | F15: =SUM(Diadema!C11,Ferraz!C11,'São Leopoldo'!C11,Jarinu!C11,Anchieta!C11,Corporativo!C11,'Compras '!C11,Vendas!C13,'Diretoria Financeira'!C11,'Head Qualidade&Dir. Industrial'!C11) -> 690000 | G15: =Diadema!D11+Anchieta!D11+Jarinu!D11+'São Leopoldo'!D11+Ferraz!D11+'Compras '!D11+Vendas!D13 -> 0 | H15: =G15/$G$18 -> 0 | I15: 📝 Não iniciado | J15: =SUM(Diadema!I11,Ferraz!I11,'São Leopoldo'!I11,Jarinu!I11,Anchieta!I11,Corporativo!H11,'Compras '!H11,Vendas!M13,'Diretoria Financeira'!H11,'Head Qualidade&Dir. Industrial'!H11) -> 12 | K15: =SUM(Diadema!J11,Ferraz!J11,'São Leopoldo'!J11,Jarinu!J11,Anchieta!J11,Corporativo!I11,'Compras '!I11,Vendas!N13,'Diretoria Financeira'!I11,'Head Qualidade&Dir. Industrial'!I11) -> 843525.14 | P15: Manutenção do Processo | Q15: =SUM(Diadema!L221,Anchieta!L134,Ferraz!L146,Jarinu!L160,'São Leopoldo'!L154)/5 -> 0.54545455 | R15: =SUM(Diadema!M221,Anchieta!M134,Ferraz!M146,Jarinu!M160,'São Leopoldo'!M154)/5 -> 0.23636364 | S15: 1
D16: BSW | E16: =SUM(Diadema!B12,Ferraz!B12,'São Leopoldo'!B12,Jarinu!B12,Anchieta!B12,Corporativo!B12,'Compras '!B12,Vendas!B14,'Diretoria Financeira'!B12,'Head Qualidade&Dir. Industrial'!B12) -> 56 | F16: =SUM(Diadema!C12,Ferraz!C12,'São Leopoldo'!C12,Jarinu!C12,Anchieta!C12,Corporativo!C12,'Compras '!C12,Vendas!C14,'Diretoria Financeira'!C12,'Head Qualidade&Dir. Industrial'!C12) -> 7044111.2 | G16: =Diadema!D12+Anchieta!D12+Jarinu!D12+'São Leopoldo'!D12+Ferraz!D12+'Compras '!D12+Vendas!D14 -> 4229091.5 | H16: =G16/$G$18 -> 0.25107717 | P16: Análise dos Dados | Q16: =SUM(Diadema!L222,Anchieta!L135,Ferraz!L147,Jarinu!L161,'São Leopoldo'!L155)/5 -> 1 | R16: =SUM(Diadema!M222,Anchieta!M135,Ferraz!M147,Jarinu!M161,'São Leopoldo'!M155)/5 -> 0.2 | S16: 1
D17: Estratégia Comercial | E17: ='Compras '!B13+Vendas!B15 -> 2 | F17: =Vendas!C15+'Compras '!C13 -> 9996000 | G17: ='Compras '!D13+Vendas!D15 -> 1400000 | H17: =G17/$G$18 -> 0.083116676
D18: TOTAL | E18: =SUM(E13:E16) -> 206 | F18: =SUM(F13:F17) -> 48275349 | G18: =SUM(G13:G17) -> 16843792 | H18: =SUM(H13:H17) -> 1
D21: - | E21: Diadema | F21: Ferraz | G21: São Leopoldo | H21: Jarinu | I21: Anchieta | J21: Corporativo | K21: Compras | L21: Vendas
D22: META DA UNIDADE | E22: =Diadema!A5 -> 6947000 | F22: =Ferraz!A5 -> 13367000 | G22: ='São Leopoldo'!A5 -> 2100000 | H22: =Jarinu!A5 -> 5356000 | I22: =Anchieta!A5 -> 3841000 | J22: =Corporativo!A5 -> 1709000 | K22: ='Compras '!A5 -> 7000000 | L22: =Vendas!A5 -> 10000000 | M22: VA | N22: =Diadema!G15+Jarinu!G15+Ferraz!G15+'São Leopoldo'!G15+Anchieta!G15+'Compras '!P17 -> 8411705.6
D23: RETORNO PREVISTO | E23: =Diadema!C5 -> 4622086.3 | F23: =Ferraz!C5 -> 7884000 | G23: ='São Leopoldo'!C5 -> 1676299.2 | H23: =Jarinu!B5 -> 3919443 | I23: =Anchieta!C5 -> 1275000 | J23: =Corporativo!C5 -> 0 | K23: ='Compras '!C5 -> 18356957 | L23: =Vendas!C5 -> 10541563 | M23: GGF | N23: =Diadema!G16+Jarinu!G16+Ferraz!G16+'São Leopoldo'!G16+Anchieta!G16+'Compras '!P18 -> 4168697.5
D24: PREVISTO (Concluido) | E24: =Diadema!J9 -> 3163136.8 | F24: =Ferraz!J9 -> 681600 | G24: ='São Leopoldo'!J9 -> 733701.5 | H24: =Jarinu!J9 -> 414120 | I24: =Anchieta!J9 -> 0 | J24: =Corporativo!I9 -> 0 | K24: ='Compras '!I9 -> 7924636 | L24: =Vendas!N11 -> 0 | M24: MA | N24: =Diadema!G17+Jarinu!G17+Ferraz!G17+'São Leopoldo'!G17+Anchieta!G17+'Compras '!P19 -> 1877825.8
D25: 💰 RETORNO VALIDADO | E25: =Diadema!E5 -> 2465004.8 | F25: =Ferraz!E5 -> 2199075.8 | G25: ='São Leopoldo'!E5 -> 2337750.5 | H25: =Jarinu!E5 -> 2819031.8 | I25: =Anchieta!E5 -> 512316.71 | J25: =Corporativo!E5 -> 0 | K25: ='Compras '!G5 -> 4565049.3 | L25: =Vendas!E5 -> 1945563 | M25: Outros | N25: =Diadema!G18+Jarinu!G18+Ferraz!G18+'São Leopoldo'!G18+Anchieta!G18+'Compras '!P20 -> 440000
D26: 💰 RETORNO REAL | E26: =Diadema!G5 -> 415214.84 | F26: =Ferraz!G5 -> 1194100.1 | G26: ='São Leopoldo'!G5 -> 821641.95 | H26: =Jarinu!G5 -> 393297.17 | I26: =Anchieta!G5 -> 141116.67 | J26: =Corporativo!G5 -> 0 | K26: ='Compras '!I5 -> 597103.47 | L26: =Vendas!G5 -> 1945563
D27: % ATINGIMENTO DA META | E27: =Diadema!J5 -> 0.059768942 | F27: =Ferraz!J5 -> 0.089331945 | G27: ='São Leopoldo'!J5 -> 0.39125807 | H27: =Jarinu!J5 -> 0.073431137 | I27: =Anchieta!J5 -> 0.036739566 | J27: =Corporativo!J5 -> 0 | K27: ='Compras '!L5 -> 0.085300496 | L27: =Vendas!J5 -> 0
D28: INICIATIVAS | E28: =Diadema!L5 -> 56 | F28: =Ferraz!L5 -> 22 | G28: ='São Leopoldo'!L5 -> 26 | H28: =Jarinu!L5 -> 34 | I28: =Anchieta!L5 -> 13 | J28: =Corporativo!M5 -> 0 | K28: ='Compras '!O5 -> 51 | L28: =Vendas!M5 -> 0
D29: Status SPD: Unidade | E29: =Diadema!K10 -> 0.64285714 | F29: =Ferraz!K10 -> 0.82142857 | G29: ='São Leopoldo'!K10 -> 0.75 | H29: =Jarinu!K10 -> 0.71428571 | I29: =Anchieta!K10 -> 0.67857143
D30: Status SPD: Auditado | E30: =Diadema!L10 -> 0.39285714 | F30: =Ferraz!L10 -> 0 | G30: ='São Leopoldo'!L10 -> 0.35714286 | H30: =Jarinu!L10 -> 0.42857143 | I30: =Anchieta!L10 -> 0.42857143
D31: Análise de Margem | E31: =N14 -> 0.25809246 | F31: =Ferraz!M10 -> 0.20833333 | G31: ='São Leopoldo'!M10 -> 0.15384615 | H31: =Jarinu!M10 -> 0.43333333 | I31: =Anchieta!M10 -> 0.33333333
F52: ,
D53: Posição | E53: Unidade / Departamento | F53: Nome do projeto /Inicio do Saving | H53: Status | I53: Status de Custos | J53: Previsto em 2026 | K53: Valor Previsto até o Momento | L53: Valor Real até o Momento | M53: Delta
D54: 1 | E54: =_xlfn.XLOOKUP(F54,Pareto!S:S,Pareto!T:T) -> Compras | F54: =_xlfn.XLOOKUP(K54,Pareto!V:V,Pareto!S:S) -> Negociação de preços materiais carcaça Dana | H54: =_xlfn.XLOOKUP(F54,Pareto!S:S,Pareto!X:X) -> ✓ Concluído | I54: =_xlfn.XLOOKUP('5 Unidades +'!F54,Pareto!S:S,Pareto!Z:Z) -> OK | J54: =_xlfn.XLOOKUP(F54,Pareto!S:S,Pareto!U:U) -> 2430268.8 | K54: =IFERROR(LARGE(Pareto!V:V,'5 Unidades +'!D54),"0") -> 1104667.6 | L54: =_xlfn.XLOOKUP(F54,Pareto!S:S,Pareto!W:W) -> 570440.18 | M54: =IF(L54="",-K54,L54-K54) -> -534227.45
D55: 2 | E55: =_xlfn.XLOOKUP(F55,Pareto!S:S,Pareto!T:T) -> São leopoldo | F55: =_xlfn.XLOOKUP(K55,Pareto!V:V,Pareto!S:S) -> 08 - Reestruturação | H55: =_xlfn.XLOOKUP(F55,Pareto!S:S,Pareto!X:X) -> ✓ Concluído | I55: =_xlfn.XLOOKUP('5 Unidades +'!F55,Pareto!S:S,Pareto!Z:Z) -> OK | J55: =_xlfn.XLOOKUP(F55,Pareto!S:S,Pareto!U:U) -> 520985.23 | K55: =IFERROR(LARGE(Pareto!V:V,D55)," ") -> 520985.23 | L55: =_xlfn.XLOOKUP(F55,Pareto!S:S,Pareto!W:W) -> 699813 | M55: =IF(L55="",-K55,L55-K55) -> 178827.77
D56: 3 | E56: =_xlfn.XLOOKUP(F56,Pareto!S:S,Pareto!T:T) -> Jarinu | F56: =_xlfn.XLOOKUP(K56,Pareto!V:V,Pareto!S:S) -> 36 - Venda Robos | H56: =_xlfn.XLOOKUP(F56,Pareto!S:S,Pareto!X:X) -> ✓ Concluído | I56: =_xlfn.XLOOKUP('5 Unidades +'!F56,Pareto!S:S,Pareto!Z:Z) -> OK | J56: =_xlfn.XLOOKUP(F56,Pareto!S:S,Pareto!U:U) -> 0 | K56: =IFERROR(LARGE(Pareto!V:V,D56)," ") -> 390000 | L56: =_xlfn.XLOOKUP(F56,Pareto!S:S,Pareto!W:W) -> 390000 | M56: =IF(L56="",-K56,L56-K56) -> -0.003
D57: 4 | E57: =_xlfn.XLOOKUP(F57,Pareto!S:S,Pareto!T:T) -> Ferraz | F57: =_xlfn.XLOOKUP(K57,Pareto!V:V,Pareto!S:S) -> 06 - Reaproveitamento de lixas | H57: =_xlfn.XLOOKUP(F57,Pareto!S:S,Pareto!X:X) -> ✓ Concluído | I57: =_xlfn.XLOOKUP('5 Unidades +'!F57,Pareto!S:S,Pareto!Z:Z) -> OK | J57: =_xlfn.XLOOKUP(F57,Pareto!S:S,Pareto!U:U) -> 151815.13 | K57: =IFERROR(LARGE(Pareto!V:V,D57)," ") -> 253025.22 | L57: =_xlfn.XLOOKUP(F57,Pareto!S:S,Pareto!W:W) -> 276395.48 | M57: =IF(L57="",-K57,L57-K57) -> 23370.263
D58: 5 | E58: =_xlfn.XLOOKUP(F58,Pareto!S:S,Pareto!T:T) -> Ferraz | F58: =_xlfn.XLOOKUP(K58,Pareto!V:V,Pareto!S:S) -> 03 - Consumo de desmoldante | H58: =_xlfn.XLOOKUP(F58,Pareto!S:S,Pareto!X:X) -> ⏳ Em Execução | I58: =_xlfn.XLOOKUP('5 Unidades +'!F58,Pareto!S:S,Pareto!Z:Z) -> OK | J58: =_xlfn.XLOOKUP(F58,Pareto!S:S,Pareto!U:U) -> 126310.64 | K58: =IFERROR(LARGE(Pareto!V:V,D58)," ") -> 210517.73 | L58: =_xlfn.XLOOKUP(F58,Pareto!S:S,Pareto!W:W) -> 421900.92 | M58: =IF(L58="",-K58,L58-K58) -> 211383.19
D59: 6 | E59: =_xlfn.XLOOKUP(F59,Pareto!S:S,Pareto!T:T) -> Ferraz | F59: =_xlfn.XLOOKUP(K59,Pareto!V:V,Pareto!S:S) -> 07 - Consumo de gás | H59: =_xlfn.XLOOKUP(F59,Pareto!S:S,Pareto!X:X) -> ⏳ Em Execução | I59: =_xlfn.XLOOKUP('5 Unidades +'!F59,Pareto!S:S,Pareto!Z:Z) -> OK | J59: =_xlfn.XLOOKUP(F59,Pareto!S:S,Pareto!U:U) -> 101344.25 | K59: =IFERROR(LARGE(Pareto!V:V,D59)," ") -> 168907.08 | L59: =_xlfn.XLOOKUP(F59,Pareto!S:S,Pareto!W:W) -> 413825.57 | M59: =IF(L59="",-K59,L59-K59) -> 244918.49 | P59: ,
D60: 7 | E60: =_xlfn.XLOOKUP(F60,Pareto!S:S,Pareto!T:T) -> Diadema | F60: =_xlfn.XLOOKUP(K60,Pareto!V:V,Pareto!S:S) -> 29 - DA000489Z_DA000490Z - STC Scania M_ | H60: =_xlfn.XLOOKUP(F60,Pareto!S:S,Pareto!X:X) -> ✓ Concluído | I60: =_xlfn.XLOOKUP('5 Unidades +'!F60,Pareto!S:S,Pareto!Z:Z) -> OK | J60: =_xlfn.XLOOKUP(F60,Pareto!S:S,Pareto!U:U) -> 446423.79 | K60: =IFERROR(LARGE(Pareto!V:V,D60)," ") -> 133927.14 | L60: =_xlfn.XLOOKUP(F60,Pareto!S:S,Pareto!W:W) -> 182981.18 | M60: =IF(L60="",-K60,L60-K60) -> 49054.041
D61: 8 | E61: =_xlfn.XLOOKUP(F61,Pareto!S:S,Pareto!T:T) -> Ferraz | F61: =_xlfn.XLOOKUP(K61,Pareto!V:V,Pareto!S:S) -> Consumo de água | H61: =_xlfn.XLOOKUP(F61,Pareto!S:S,Pareto!X:X) -> ⏳ Em Execução | I61: =_xlfn.XLOOKUP('5 Unidades +'!F61,Pareto!S:S,Pareto!Z:Z) -> OK | J61: =_xlfn.XLOOKUP(F61,Pareto!S:S,Pareto!U:U) -> 76753.75 | K61: =IFERROR(LARGE(Pareto!V:V,D61)," ") -> 127922.92 | L61: =_xlfn.XLOOKUP(F61,Pareto!S:S,Pareto!W:W) -> 45098 | M61: =IF(L61="",-K61,L61-K61) -> -82824.917
D62: 9 | E62: =_xlfn.XLOOKUP(F62,Pareto!S:S,Pareto!T:T) -> São leopoldo | F62: =_xlfn.XLOOKUP(K62,Pareto!V:V,Pareto!S:S) -> 01 - Redução de Refugo | H62: =_xlfn.XLOOKUP(F62,Pareto!S:S,Pareto!X:X) -> ⏳ Em Execução | I62: =_xlfn.XLOOKUP('5 Unidades +'!F62,Pareto!S:S,Pareto!Z:Z) -> OK | J62: =_xlfn.XLOOKUP(F62,Pareto!S:S,Pareto!U:U) -> 59652.758 | K62: =IFERROR(LARGE(Pareto!V:V,D62)," ") -> 79537.011 | L62: =_xlfn.XLOOKUP(F62,Pareto!S:S,Pareto!W:W) -> 98159.34 | M62: =IF(L62="",-K62,L62-K62) -> 18622.329
D63: 10 | E63: =_xlfn.XLOOKUP(F63,Pareto!S:S,Pareto!T:T) -> Compras | F63: =_xlfn.XLOOKUP(K63,Pareto!V:V,Pareto!S:S) -> Viabilizar itens Usiminas via Gonvarri-Full Service | H63: =_xlfn.XLOOKUP(F63,Pareto!S:S,Pareto!X:X) -> ✓ Concluído | I63: =_xlfn.XLOOKUP('5 Unidades +'!F63,Pareto!S:S,Pareto!Z:Z) | J63: =_xlfn.XLOOKUP(F63,Pareto!S:S,Pareto!U:U) -> 264492.5 | K63: =IFERROR(LARGE(Pareto!V:V,D63)," ") -> 79347.75 | L63: =_xlfn.XLOOKUP(F63,Pareto!S:S,Pareto!W:W) | M63: =IF(L63="",-K63,L63-K63) -> -79347.75
D64: 11 | E64: =_xlfn.XLOOKUP(F64,Pareto!S:S,Pareto!T:T) -> Ferraz | F64: =_xlfn.XLOOKUP(K64,Pareto!V:V,Pareto!S:S) -> 10 - Consumo de energia elétrica: vazamentos de ar | H64: =_xlfn.XLOOKUP(F64,Pareto!S:S,Pareto!X:X) -> ⏳ Em Execução | I64: =_xlfn.XLOOKUP('5 Unidades +'!F64,Pareto!S:S,Pareto!Z:Z) -> OK | J64: =_xlfn.XLOOKUP(F64,Pareto!S:S,Pareto!U:U) -> 57455.182 | K64: =IFERROR(LARGE(Pareto!V:V,D64)," ") -> 76606.909 | L64: =_xlfn.XLOOKUP(F64,Pareto!S:S,Pareto!W:W) | M64: =IF(L64="",-K64,L64-K64) -> -76606.909
D65: 12 | E65: =_xlfn.XLOOKUP(F65,Pareto!S:S,Pareto!T:T) -> Anchieta | F65: =_xlfn.XLOOKUP(K65,Pareto!V:V,Pareto!S:S) -> 04 - GÁS | H65: =_xlfn.XLOOKUP(F65,Pareto!S:S,Pareto!X:X) -> ⏳ Em Execução | I65: =_xlfn.XLOOKUP('5 Unidades +'!F65,Pareto!S:S,Pareto!Z:Z) -> OK | J65: =_xlfn.XLOOKUP(F65,Pareto!S:S,Pareto!U:U) -> 84366.097 | K65: =IFERROR(LARGE(Pareto!V:V,D65)," ") -> 56244.064 | L65: =_xlfn.XLOOKUP(F65,Pareto!S:S,Pareto!W:W) -> -2790.25 | M65: =IF(L65="",-K65,L65-K65) -> -59034.314
D66: 13 | E66: =_xlfn.XLOOKUP(F66,Pareto!S:S,Pareto!T:T) -> Compras | F66: =_xlfn.XLOOKUP(K66,Pareto!V:V,Pareto!S:S) -> Resourcing Maletas Man (Mercante para Cartec) | H66: =_xlfn.XLOOKUP(F66,Pareto!S:S,Pareto!X:X) -> ✓ Concluído | I66: =_xlfn.XLOOKUP('5 Unidades +'!F66,Pareto!S:S,Pareto!Z:Z) -> Não Ok | J66: =_xlfn.XLOOKUP(F66,Pareto!S:S,Pareto!U:U) -> 183134.17 | K66: =IFERROR(LARGE(Pareto!V:V,D66)," ") -> 54940.25 | L66: =_xlfn.XLOOKUP(F66,Pareto!S:S,Pareto!W:W) | M66: =IF(L66="",-K66,L66-K66) -> -54940.25
D67: 14 | E67: =_xlfn.XLOOKUP(F67,Pareto!S:S,Pareto!T:T) -> Compras | F67: =_xlfn.XLOOKUP(K67,Pareto!V:V,Pareto!S:S) -> Redução de custo Abrasivos Curva A Ferraz | H67: =_xlfn.XLOOKUP(F67,Pareto!S:S,Pareto!X:X) -> ✓ Concluído | I67: =_xlfn.XLOOKUP('5 Unidades +'!F67,Pareto!S:S,Pareto!Z:Z) -> Não Ok | J67: =_xlfn.XLOOKUP(F67,Pareto!S:S,Pareto!U:U) -> 145740.83 | K67: =IFERROR(LARGE(Pareto!V:V,D67)," ") -> 52996.667 | L67: =_xlfn.XLOOKUP(F67,Pareto!S:S,Pareto!W:W) | M67: =IF(L67="",-K67,L67-K67) -> -52996.667
D68: 15 | E68: =_xlfn.XLOOKUP(F68,Pareto!S:S,Pareto!T:T) -> Compras | F68: =_xlfn.XLOOKUP(K68,Pareto!V:V,Pareto!S:S) -> Resourcing Hasmman para Metalac | H68: =_xlfn.XLOOKUP(F68,Pareto!S:S,Pareto!X:X) -> ✓ Concluído | I68: =_xlfn.XLOOKUP('5 Unidades +'!F68,Pareto!S:S,Pareto!Z:Z) -> OK | J68: =_xlfn.XLOOKUP(F68,Pareto!S:S,Pareto!U:U) -> 142025.58 | K68: =IFERROR(LARGE(Pareto!V:V,D68)," ") -> 51645.667 | L68: =_xlfn.XLOOKUP(F68,Pareto!S:S,Pareto!W:W) | M68: =IF(L68="",-K68,L68-K68) -> -51645.667
D69: 16 | E69: =_xlfn.XLOOKUP(F69,Pareto!S:S,Pareto!T:T) -> Ferraz | F69: =_xlfn.XLOOKUP(K69,Pareto!V:V,Pareto!S:S) -> 14 - Consumo de EPI's | H69: =_xlfn.XLOOKUP(F69,Pareto!S:S,Pareto!X:X) -> ⏳ Em Execução | I69: =_xlfn.XLOOKUP('5 Unidades +'!F69,Pareto!S:S,Pareto!Z:Z) -> OK | J69: =_xlfn.XLOOKUP(F69,Pareto!S:S,Pareto!U:U) -> 30921.5 | K69: =IFERROR(LARGE(Pareto!V:V,D69)," ") -> 51535.833 | L69: =_xlfn.XLOOKUP(F69,Pareto!S:S,Pareto!W:W) -> 36880.14 | M69: =IF(L69="",-K69,L69-K69) -> -14655.693
D70: 17 | E70: =_xlfn.XLOOKUP(F70,Pareto!S:S,Pareto!T:T) -> Jarinu | F70: =_xlfn.XLOOKUP(K70,Pareto!V:V,Pareto!S:S) -> 30 - Redução de Refugo | H70: =_xlfn.XLOOKUP(F70,Pareto!S:S,Pareto!X:X) -> ⏳ Em Execução | I70: =_xlfn.XLOOKUP('5 Unidades +'!F70,Pareto!S:S,Pareto!Z:Z) -> OK | J70: =_xlfn.XLOOKUP(F70,Pareto!S:S,Pareto!U:U) -> 76500 | K70: =IFERROR(LARGE(Pareto!V:V,D70)," ") -> 51000 | L70: =_xlfn.XLOOKUP(F70,Pareto!S:S,Pareto!W:W) | M70: =IF(L70="",-K70,L70-K70) -> -51000
D71: 18 | E71: =_xlfn.XLOOKUP(F71,Pareto!S:S,Pareto!T:T) -> Anchieta | F71: =_xlfn.XLOOKUP(K71,Pareto!V:V,Pareto!S:S) -> 01 - VENDA DE ATIVOS | H71: =_xlfn.XLOOKUP(F71,Pareto!S:S,Pareto!X:X) -> ⏳ Em Execução | I71: =_xlfn.XLOOKUP('5 Unidades +'!F71,Pareto!S:S,Pareto!Z:Z) -> OK | J71: =_xlfn.XLOOKUP(F71,Pareto!S:S,Pareto!U:U) -> 0 | K71: =IFERROR(LARGE(Pareto!V:V,D71)," ") -> 50000 | L71: =_xlfn.XLOOKUP(F71,Pareto!S:S,Pareto!W:W) -> 50000 | M71: =IF(L71="",-K71,L71-K71) -> 0
... D257: 204 | E257: =_xlfn.XLOOKUP(F257,Pareto!S:S,Pareto!T:T) -> #N/A | F257: =_xlfn.XLOOKUP(K257,Pareto!V:V,Pareto!S:S) -> #N/A | H257: =_xlfn.XLOOKUP(F257,Pareto!S:S,Pareto!X:X) -> #N/A | I257: =_xlfn.XLOOKUP('5 Unidades +'!F257,Pareto!S:S,Pareto!Z:Z) -> #N/A | J257: =_xlfn.XLOOKUP(F257,Pareto!S:S,Pareto!U:U) -> #N/A | K257: =IFERROR(LARGE(Pareto!V:V,D257)," ") | L257: =_xlfn.XLOOKUP(F257,Pareto!S:S,Pareto!W:W) -> #N/A | M257: =IF(L257="",-K257,L257-K257) -> #N/A
J258: =SUBTOTAL(9,J53:J153) -> 7286158.8 | K258: =SUM(K54:K153) -> 4219129.6 | L258: {=SUM(IFERROR(L54:L153,0))} -> 3554549.2 | M258: =L258-K258 -> -664580.37
D264: Unidade | E264: Previsto | F264: Real
D265: Compras | E265: =SUMIF($E$54:$E$246,D265,$K$54:$K$246) -> 1566100.7 | F265: =SUMIF($E$54:$E$103,D265,$L$54:$L$246) -> 597103.47
D266: Ferraz | E266: =SUMIF($E$54:$E$246,D266,$K$54:$K$246) -> 890026.8 | F266: =SUMIF($E$54:$E$103,D266,$L$54:$L$246) -> 1194100.1
D267: São leopoldo | E267: =SUMIF($E$54:$E$246,D267,$K$54:$K$246) -> 670756.89 | F267: =SUMIF($E$54:$E$103,D267,$L$54:$L$246) -> 821498.26
D268: Diadema | E268: =SUMIF($E$54:$E$246,D268,$K$54:$K$246) -> 466575.82 | F268: =SUMIF($E$54:$E$103,D268,$L$54:$L$246) -> 386808.69
D269: Anchieta | E269: =SUMIF($E$54:$E$246,D269,$K$54:$K$246) -> 177113.98 | F269: =SUMIF($E$54:$E$103,D269,$L$54:$L$246) -> 144003.31
D270: Jarinu | E270: =SUMIF($E$54:$E$246,D270,$K$54:$K$246) -> 448555.4 | F270: =SUMIF($E$54:$E$103,D270,$L$54:$L$246) -> 390000

Sheet Diadema
A1: DASHBOARD EXECUTIVO - UNIDADE DIADEMA
A2: Gestão Estratégica de Projetos e Redução de Custos | Grupo Delga | 2026
A4: META DA UNIDADE | C4: RETORNO PREVISTO (Total) | D4: PREVISTO 2026 | E4: 💰 RETORNO VALIDADO | G4: 💰 RETORNO REAL | J4: % ATINGIMENTO DA META | L4: INICIATIVAS | O4: TOP 20 Raking de Projetos Valorizados | AP4: dip | AQ4: perf | AU4: 2025 | AV4: 2026
A5: =Parâmetros!E5 -> 6947000 | C5: =SUM(I55:I176) -> 4622086.3 | D5: =SUMIF(Q55:Q176,"Previsto",AI55:AI176) -> 3121824.8 | E5: =SUM(N55:N176) -> 2465004.8 | G5: =SUMIF(Q55:Q176,"Real",AI55:AI176) -> 415214.84 | J5: =G5/A5 -> 0.059768942 | L5: =SUM(I9:I11) -> 56 | O5: POS | P5: Tipo | Q5: Valor Previsto Unidade | R5: Valor Previsto Custos | S5: Retorno Previsto | T5: Retorno Real até hoje | U5: Projetos | Z5: Peso | AA5: Pareto | AB5: % Previsto | AC5: % Real | AD5: Planejado | AE5: % Responsabilidade Delga | AS5: 0.3293 | AT5: 0.9228 | AW5: p | AX5: 0.9261 | AY5: 0.95
O6: {=_xlfn.SEQUENCE(20)} -> 1 | P6: =_xlfn.XLOOKUP(U6,$C$55:$C$176,$A$55:$A$176) -> BSW | Q6: =MAX(I55:I176) -> 450000.01 | R6: =_xlfn.XLOOKUP(Q6,$I$55:$I$176,$N$55:$N$176) -> 446423.79 | S6: =_xlfn.XLOOKUP(U6,$C$55:$C$176,$J$55:$J$176) -> 46082 | T6: {=SUMPRODUCT(($C$55:$C$175=U6)*(S$54:$AG$54<=TODAY())*(ISNUMBER(S$56:$AG$176)),S$56:$AG$176)} -> 182981.18 | U6: =IFERROR(HYPERLINK(INDEX($D$55:$D$176,MATCH(Q6,$I$55:$I$176,0)),INDEX($C$55:$C$176,MATCH(Q6,$I$55:$I$176,0)) ), ) -> 29 - DA000489Z_DA000490Z - STC Scania M_ | Z6: =Q6/$C$5 -> 0.097358634 | AA6: =Z6 -> 0.097358634 | AB6: {=IFERROR(INDEX($R$55:$R$176,MATCH(1,($AN$55:$AN$176=U6)*($Q$55:$Q$176="Previsto"), 0) ), "")} -> 1 | AC6: {=IFERROR( INDEX($R$55:$R$176,MATCH(1,($AN$55:$AN$176=U6)*($Q$55:$Q$176="Real"),0)),"")} -> 1 | AD6: =IF(OR(AB6="",AC6=""),"",IF(AC6=100%,"CONCLUÍDO",IF(AC6=0,IF(AB6=0,"PROJETO NÃO INICIADO","FALTA DE ACOMPANHAMENTO"),IF(AC6>AB6,"ADIANTADO",IF(AC6=AB6,"CONFORME PLANEJADO","ATRASO"))))) -> CONCLUÍDO | AE6: {=_xlfn.XLOOKUP($U$6:$U$25,$C$55:$C$176,$P$55:$P$176)} -> 1 | AS6: 0.4166 | AT6: 0.9152 | AW6: d | AX6: 0.5017 | AY6: 0.58
A7: 📊 SAVING PREVISTO POR PILAR | H7: 📋 STATUS DAS INICIATIVAS | K7: 🏭 INDICADORES OPERACIONAIS | O7: 2 | P7: =_xlfn.XLOOKUP(U7,$C$55:$C$176,$A$55:$A$176) -> BSW | Q7: =IFERROR(LARGE($I$55:$I$176,O7)," ") -> 331600 | R7: =_xlfn.XLOOKUP(Q7,$I$55:$I$176,$N$55:$N$176) -> 160178.29 | S7: =_xlfn.XLOOKUP(U7,$C$55:$C$176,$J$55:$J$176) -> 46082 | T7: {=SUMPRODUCT(($C$55:$C$175=U7)*(S$54:$AG$54<=TODAY())*(ISNUMBER(S$56:$AG$176)),S$56:$AG$176)} -> 51688.193 | U7: =IFERROR(HYPERLINK(INDEX($D$55:$D$176,MATCH(Q7,$I$55:$I$176,0)),INDEX($C$55:$C$176,MATCH(Q7,$I$55:$I$176,0)) ), "" ) -> 01 - Redução de peso bruto DA000489A | Z7: =Q7/$C$5 -> 0.071742494 | AA7: =Z7+AA6 -> 0.16910113 | AB7: {=IFERROR(INDEX($R$55:$R$176,MATCH(1,($AN$55:$AN$176=U7)*($Q$55:$Q$176="Previsto"), 0) ), "")} -> 1 | AC7: {=IFERROR( INDEX($R$55:$R$176,MATCH(1,($AN$55:$AN$176=U7)*($Q$55:$Q$176="Real"),0)),"")} -> 1 | AD7: =IF(OR(AB7="",AC7=""),"",IF(AC7=100%,"CONCLUÍDO",IF(AC7=0,IF(AB7=0,"PROJETO NÃO INICIADO","FALTA DE ACOMPANHAMENTO"),IF(AC7>AB7,"ADIANTADO",IF(AC7=AB7,"CONFORME PLANEJADO","ATRASO"))))) -> CONCLUÍDO | AE7: 1 | AS7: 0.4666 | AT7: 0.9202 | AW7: q | AX7: 0.955 | AY7: 0.965
A8: Pilar | B8: Qtd. | C8: Saving (R$) | D8: Saving Validado 2026 | E8: % Total | F8: Barra | H8: Status | I8: Qtd. | J8: R$ Previsto | K8: Aderência SPD: Unidade | L8: Aderência SPD: Auditado | M8: Análise de Margem (Form 206) | O8: 3 | P8: =_xlfn.XLOOKUP(U8,$C$55:$C$176,$A$55:$A$176) -> Redução de custo | Q8: =IFERROR(LARGE($I$55:$I$176,O8)," ") -> 288000 | R8: =_xlfn.XLOOKUP(Q8,$I$55:$I$176,$N$55:$N$176) -> 79673.52 | S8: =_xlfn.XLOOKUP(U8,$C$55:$C$176,$J$55:$J$176) -> 46143 | T8: {=SUMPRODUCT(($C$55:$C$175=U8)*(S$54:$AG$54<=TODAY())*(ISNUMBER(S$56:$AG$176)),S$56:$AG$176)} -> -31423.7 | U8: =IFERROR(HYPERLINK(INDEX($D$55:$D$176,MATCH(Q8,$I$55:$I$176,0)),INDEX($C$55:$C$176,MATCH(Q8,$I$55:$I$176,0)) ), "" ) -> 06 - Produtividade | Z8: =Q8/$C$5 -> 0.062309525 | AA8: =Z8+AA7 -> 0.23141065 | AB8: {=IFERROR(INDEX($R$55:$R$176,MATCH(1,($AN$55:$AN$176=U8)*($Q$55:$Q$176="Previsto"), 0) ), "")} -> 0.96 | AC8: {=IFERROR( INDEX($R$55:$R$176,MATCH(1,($AN$55:$AN$176=U8)*($Q$55:$Q$176="Real"),0)),"")} -> 0.98 | AD8: =IF(OR(AB8="",AC8=""),"",IF(AC8=100%,"CONCLUÍDO",IF(AC8=0,IF(AB8=0,"PROJETO NÃO INICIADO","FALTA DE ACOMPANHAMENTO"),IF(AC8>AB8,"ADIANTADO",IF(AC8=AB8,"CONFORME PLANEJADO","ATRASO"))))) -> ADIANTADO | AE8: 1 | AT8: 0.5436 | AU8: 0.9206 | AY8: =AX7*AX6*AX5 -> 0.44371627 | AZ8: =AY7*AY6*AY5 -> 0.531715
A9: Kaizen | B9: =COUNTIF($A$55:$A$176,A9) -> 10 | C9: =SUMIF($A$55:$A$176,A9,$I$55:$I$176) -> 625866.77 | D9: =SUMIF($A$55:$A$176,A9,$N$55:$N$176) -> 168076.19 | E9: =IF($D$13=0,"",D9/$D$13) -> 0.068184935 | F9: =E9 -> 0.068184935 | H9: ✓ Concluído | I9: =COUNTIF($O$55:$O$176,H9) -> 36 | J9: =SUMIF($O$55:$O$176,H9,$I$55:$I$176) -> 3163136.8 | O9: 4 | Z9: =Q9/$C$5 -> 0 | AA9: =Z9+AA8 -> 0.23141065 | AB9: {=IFERROR(INDEX($R$55:$R$176,MATCH(1,($AN$55:$AN$176=U9)*($Q$55:$Q$176="Previsto"), 0) ), "")} | AC9: {=IFERROR( INDEX($R$55:$R$176,MATCH(1,($AN$55:$AN$176=U9)*($Q$55:$Q$176="Real"),0)),"")} -> 0 | AD9: =IF(OR(AB9="",AC9=""),"",IF(AC9=100%,"CONCLUÍDO",IF(AC9=0,IF(AB9=0,"PROJETO NÃO INICIADO","FALTA DE ACOMPANHAMENTO"),IF(AC9>AB9,"ADIANTADO",IF(AC9=AB9,"CONFORME PLANEJADO","ATRASO"))))) | AE9: 0 | AT9: 0.5123 | AU9: 0.923
A10: Redução de Custo | B10: =COUNTIF($A$55:$A$176,A10) -> 10 | C10: =SUMIF($A$55:$A$176,A10,$I$55:$I$176) -> 592471.54 | D10: =SUMIF($A$55:$A$176,A10,$N$55:$N$176) -> 208784.28 | E10: =IF($D$13=0,"",D10/$D$13) -> 0.084699341 | F10: =E10 -> 0.084699341 | H10: ⏳ Em Execução | I10: =COUNTIF($O$55:$O$176,H10) -> 19 | J10: =SUMIF($O$55:$O$176,H10,$I$55:$I$176) -> 1458948 | K10: =E207 -> 0.64285714 | L10: =F207 -> 0.39285714 | M10: =L214 -> 0.16161616 | O10: 5 | P10: =_xlfn.XLOOKUP(U10,$C$55:$C$176,$A$55:$A$176) -> BSW | Q10: =IFERROR(LARGE($I$55:$I$176,O10)," ") -> 270000 | R10: =_xlfn.XLOOKUP(Q10,$I$55:$I$176,$N$55:$N$176) -> 128107.04 | S10: =_xlfn.XLOOKUP(U10,$C$55:$C$176,$J$55:$J$176) -> 46174 | T10: {=SUMPRODUCT(($C$55:$C$175=U10)*(S$54:$AG$54<=TODAY())*(ISNUMBER(S$56:$AG$176)),S$56:$AG$176)} -> 0 | U10: =IFERROR(HYPERLINK(INDEX($D$55:$D$176,MATCH(Q10,$I$55:$I$176,0)),INDEX($C$55:$C$176,MATCH(Q10,$I$55:$I$176,0)) ), "" ) -> 23 - Redução do peso bruto VW000581Z / VW000582Z | Z10: =Q10/$C$5 -> 0.058415179 | AA10: =Z10+AA9 -> 0.28982583 | AB10: {=IFERROR(INDEX($R$55:$R$176,MATCH(1,($AN$55:$AN$176=U10)*($Q$55:$Q$176="Previsto"), 0) ), "")} -> 0.2 | AC10: {=IFERROR( INDEX($R$55:$R$176,MATCH(1,($AN$55:$AN$176=U10)*($Q$55:$Q$176="Real"),0)),"")} -> 0.25 | AD10: =IF(OR(AB10="",AC10=""),"",IF(AC10=100%,"CONCLUÍDO",IF(AC10=0,IF(AB10=0,"PROJETO NÃO INICIADO","FALTA DE ACOMPANHAMENTO"),IF(AC10>AB10,"ADIANTADO",IF(AC10=AB10,"CONFORME PLANEJADO","ATRASO"))))) -> ADIANTADO | AE10: 0.8 | AT10: 0.5216 | AU10: 0.9165
A11: Você Resolve | B11: =COUNTIF($A$55:$A$176,A11) -> 0 | C11: =SUMIF($A$55:$A$176,A11,$I$55:$I$176) -> 0 | D11: =SUMIF($A$55:$A$176,A11,$N$55:$N$176) -> 0 | E11: =IF($D$13=0,"",D11/$D$13) -> 0 | F11: =E11 -> 0 | H11: 📝 Não iniciado | I11: =COUNTIF($O$55:$O$176,H11) -> 1 | J11: =SUMIF($O$55:$O$176,H11,$I$55:$I$176) -> 1.5355 | O11: 6 | P11: =_xlfn.XLOOKUP(U11,$C$55:$C$176,$A$55:$A$176) -> BSW | Q11: =IFERROR(LARGE($I$55:$I$176,O11)," ") -> 236000 | R11: =_xlfn.XLOOKUP(Q11,$I$55:$I$176,$N$55:$N$176) -> 138092.84 | S11: =_xlfn.XLOOKUP(U11,$C$55:$C$176,$J$55:$J$176) -> 46174 | T11: {=SUMPRODUCT(($C$55:$C$175=U11)*(S$54:$AG$54<=TODAY())*(ISNUMBER(S$56:$AG$176)),S$56:$AG$176)} -> 0 | U11: =IFERROR(HYPERLINK(INDEX($D$55:$D$176,MATCH(Q11,$I$55:$I$176,0)),INDEX($C$55:$C$176,MATCH(Q11,$I$55:$I$176,0)) ), "" ) -> 52 - Redução de MP - GM000458Z / GM000459Z | Z11: =Q11/$C$5 -> 0.051059194 | AA11: =Z11+AA10 -> 0.34088503 | AB11: {=IFERROR(INDEX($R$55:$R$176,MATCH(1,($AN$55:$AN$176=U11)*($Q$55:$Q$176="Previsto"), 0) ), "")} -> 1 | AC11: {=IFERROR( INDEX($R$55:$R$176,MATCH(1,($AN$55:$AN$176=U11)*($Q$55:$Q$176="Real"),0)),"")} -> 1 | AD11: =IF(OR(AB11="",AC11=""),"",IF(AC11=100%,"CONCLUÍDO",IF(AC11=0,IF(AB11=0,"PROJETO NÃO INICIADO","FALTA DE ACOMPANHAMENTO"),IF(AC11>AB11,"ADIANTADO",IF(AC11=AB11,"CONFORME PLANEJADO","ATRASO"))))) -> CONCLUÍDO | AE11: 1 | AT11: 0.5217 | AU11: 0.9237
A12: BSW | B12: =COUNTIF($A$55:$A$176,A12) -> 37 | C12: =SUMIF($A$55:$A$176,A12,$I$55:$I$176) -> 3403748 | D12: =SUMIF($A$55:$A$176,A12,$N$55:$N$176) -> 2088144.3 | E12: =IF($D$13=0,"",D12/$D$13) -> 0.84711572 | F12: =E12 -> 0.84711572 | O12: 7 | P12: =_xlfn.XLOOKUP(U12,$C$55:$C$176,$A$55:$A$176) -> BSW | Q12: =IFERROR(LARGE($I$55:$I$176,O12)," ") -> 230000 | R12: =_xlfn.XLOOKUP(Q12,$I$55:$I$176,$N$55:$N$176) -> 115000 | S12: =_xlfn.XLOOKUP(U12,$C$55:$C$176,$J$55:$J$176) -> 46204 | T12: {=SUMPRODUCT(($C$55:$C$175=U12)*(S$54:$AG$54<=TODAY())*(ISNUMBER(S$56:$AG$176)),S$56:$AG$176)} -> 0 | U12: =IFERROR(HYPERLINK(INDEX($D$55:$D$176,MATCH(Q12,$I$55:$I$176,0)),INDEX($C$55:$C$176,MATCH(Q12,$I$55:$I$176,0)) ), "" ) -> 44 - Mudança de fonte Usiminas para Arcelor | Z12: =Q12/$C$5 -> 0.049761078 | AA12: =Z12+AA11 -> 0.3906461 | AB12: {=IFERROR(INDEX($R$55:$R$176,MATCH(1,($AN$55:$AN$176=U12)*($Q$55:$Q$176="Previsto"), 0) ), "")} -> 0.29 | AC12: {=IFERROR( INDEX($R$55:$R$176,MATCH(1,($AN$55:$AN$176=U12)*($Q$55:$Q$176="Real"),0)),"")} -> 0.36 | AD12: =IF(OR(AB12="",AC12=""),"",IF(AC12=100%,"CONCLUÍDO",IF(AC12=0,IF(AB12=0,"PROJETO NÃO INICIADO","FALTA DE ACOMPANHAMENTO"),IF(AC12>AB12,"ADIANTADO",IF(AC12=AB12,"CONFORME PLANEJADO","ATRASO"))))) -> ADIANTADO | AE12: 0.2 | AT12: 0.5746 | AU12: 0.936
A13: TOTAL | B13: =SUM(B9:B12) -> 57 | C13: =SUM(C9:C12) -> 4622086.3 | D13: =SUM(D9:D12) -> 2465004.8 | E13: =SUM(E9:E12) -> 1 | O13: 8 | P13: =_xlfn.XLOOKUP(U13,$C$55:$C$176,$A$55:$A$176) -> Kaizen | Q13: =IFERROR(LARGE($I$55:$I$176,O13)," ") -> 228000 | R13: =_xlfn.XLOOKUP(Q13,$I$55:$I$176,$N$55:$N$176) -> 124710.19 | S13: =_xlfn.XLOOKUP(U13,$C$55:$C$176,$J$55:$J$176) -> 46082 | T13: {=SUMPRODUCT(($C$55:$C$175=U13)*(S$54:$AG$54<=TODAY())*(ISNUMBER(S$56:$AG$176)),S$56:$AG$176)} -> 12885.19 | U13: =IFERROR(HYPERLINK(INDEX($D$55:$D$176,MATCH(Q13,$I$55:$I$176,0)),INDEX($C$55:$C$176,MATCH(Q13,$I$55:$I$176,0)) ), "" ) -> 16 - Eficiência de MO na linha de Solda e Montagem | Z13: =Q13/$C$5 -> 0.049328373 | AA13: =Z13+AA12 -> 0.43997448 | AB13: {=IFERROR(INDEX($R$55:$R$176,MATCH(1,($AN$55:$AN$176=U13)*($Q$55:$Q$176="Previsto"), 0) ), "")} -> 1 | AC13: {=IFERROR( INDEX($R$55:$R$176,MATCH(1,($AN$55:$AN$176=U13)*($Q$55:$Q$176="Real"),0)),"")} -> 1 | AD13: =IF(OR(AB13="",AC13=""),"",IF(AC13=100%,"CONCLUÍDO",IF(AC13=0,IF(AB13=0,"PROJETO NÃO INICIADO","FALTA DE ACOMPANHAMENTO"),IF(AC13>AB13,"ADIANTADO",IF(AC13=AB13,"CONFORME PLANEJADO","ATRASO"))))) -> CONCLUÍDO | AE13: 1 | AT13: 0.5423 | AU13: 0.936
O14: 9 | P14: =_xlfn.XLOOKUP(U14,$C$55:$C$176,$A$55:$A$176) -> BSW | Q14: =IFERROR(LARGE($I$55:$I$176,O14)," ") -> 223200 | R14: =_xlfn.XLOOKUP(Q14,$I$55:$I$176,$N$55:$N$176) -> 0 | S14: =_xlfn.XLOOKUP(U14,$C$55:$C$176,$J$55:$J$176) -> 46174 | T14: {=SUMPRODUCT(($C$55:$C$175=U14)*(S$54:$AG$54<=TODAY())*(ISNUMBER(S$56:$AG$176)),S$56:$AG$176)} -> 0 | U14: =IFERROR(HYPERLINK(INDEX($D$55:$D$176,MATCH(Q14,$I$55:$I$176,0)),INDEX($C$55:$C$176,MATCH(Q14,$I$55:$I$176,0)) ), "" ) -> 57 - AlmaCAM_Redução de Peso | Z14: =Q14/$C$5 -> 0.048289881 | AA14: =Z14+AA13 -> 0.48826436 | AB14: {=IFERROR(INDEX($R$55:$R$176,MATCH(1,($AN$55:$AN$176=U14)*($Q$55:$Q$176="Previsto"), 0) ), "")} -> 1 | AC14: {=IFERROR( INDEX($R$55:$R$176,MATCH(1,($AN$55:$AN$176=U14)*($Q$55:$Q$176="Real"),0)),"")} -> 1 | AD14: =IF(OR(AB14="",AC14=""),"",IF(AC14=100%,"CONCLUÍDO",IF(AC14=0,IF(AB14=0,"PROJETO NÃO INICIADO","FALTA DE ACOMPANHAMENTO"),IF(AC14>AB14,"ADIANTADO",IF(AC14=AB14,"CONFORME PLANEJADO","ATRASO"))))) -> CONCLUÍDO | AE14: 1 | AS14: 0.5472 | AT14: 0.9115
F15: VA | G15: =SUMIF($B$55:$B$176,F15,$N$55:$N$176) -> 2088144.3 | O15: 10 | P15: =_xlfn.XLOOKUP(U15,$C$55:$C$176,$A$55:$A$176) -> BSW | Q15: =IFERROR(LARGE($I$55:$I$176,O15)," ") -> 189200 | R15: =_xlfn.XLOOKUP(Q15,$I$55:$I$176,$N$55:$N$176) -> 70963.59 | S15: =_xlfn.XLOOKUP(U15,$C$55:$C$176,$J$55:$J$176) -> 46235 | T15: {=SUMPRODUCT(($C$55:$C$175=U15)*(S$54:$AG$54<=TODAY())*(ISNUMBER(S$56:$AG$176)),S$56:$AG$176)} -> 0 | U15: =IFERROR(HYPERLINK(INDEX($D$55:$D$176,MATCH(Q15,$I$55:$I$176,0)),INDEX($C$55:$C$176,MATCH(Q15,$I$55:$I$176,0)) ), "" ) -> 47 - REDUÇÃO DE MP DJ000079Z – 80Z | Z15: =Q15/$C$5 -> 0.040933896 | AA15: =Z15+AA14 -> 0.52919825 | AB15: {=IFERROR(INDEX($R$55:$R$176,MATCH(1,($AN$55:$AN$176=U15)*($Q$55:$Q$176="Previsto"), 0) ), "")} -> 0.24 | AC15: {=IFERROR( INDEX($R$55:$R$176,MATCH(1,($AN$55:$AN$176=U15)*($Q$55:$Q$176="Real"),0)),"")} -> 0.38 | AD15: =IF(OR(AB15="",AC15=""),"",IF(AC15=100%,"CONCLUÍDO",IF(AC15=0,IF(AB15=0,"PROJETO NÃO INICIADO","FALTA DE ACOMPANHAMENTO"),IF(AC15>AB15,"ADIANTADO",IF(AC15=AB15,"CONFORME PLANEJADO","ATRASO"))))) -> ADIANTADO | AE15: 0.5 | AS15: 0.5483 | AT15: 0.9229
F16: GGF | G16: =SUMIF($B$55:$B$176,F16,$N$55:$N$176) -> 376860.47 | O16: 11 | P16: =_xlfn.XLOOKUP(U16,$C$55:$C$176,$A$55:$A$176) -> Redução de custo | Q16: =IFERROR(LARGE($I$55:$I$176,O16)," ") -> 160000 | R16: =_xlfn.XLOOKUP(Q16,$I$55:$I$176,$N$55:$N$176) -> 72500 | S16: =_xlfn.XLOOKUP(U16,$C$55:$C$176,$J$55:$J$176) -> 46174 | T16: {=SUMPRODUCT(($C$55:$C$175=U16)*(S$54:$AG$54<=TODAY())*(ISNUMBER(S$56:$AG$176)),S$56:$AG$176)} -> 0 | U16: =IFERROR(HYPERLINK(INDEX($D$55:$D$176,MATCH(Q16,$I$55:$I$176,0)),INDEX($C$55:$C$176,MATCH(Q16,$I$55:$I$176,0)) ), "" ) -> 42 - Aluguel de Compressor | Z16: =Q16/$C$5 -> 0.034616402 | AA16: =Z16+AA15 -> 0.56381466 | AB16: {=IFERROR(INDEX($R$55:$R$176,MATCH(1,($AN$55:$AN$176=U16)*($Q$55:$Q$176="Previsto"), 0) ), "")} -> 0.43 | AC16: {=IFERROR( INDEX($R$55:$R$176,MATCH(1,($AN$55:$AN$176=U16)*($Q$55:$Q$176="Real"),0)),"")} -> 1 | AD16: =IF(OR(AB16="",AC16=""),"",IF(AC16=100%,"CONCLUÍDO",IF(AC16=0,IF(AB16=0,"PROJETO NÃO INICIADO","FALTA DE ACOMPANHAMENTO"),IF(AC16>AB16,"ADIANTADO",IF(AC16=AB16,"CONFORME PLANEJADO","ATRASO"))))) -> CONCLUÍDO | AE16: 1 | AS16: 0.4958 | AT16: 0.9642
F17: MA | G17: =SUMIF($B$55:$B$176,F17,$N$55:$N$176) -> 0 | O17: 12 | P17: =_xlfn.XLOOKUP(U17,$C$55:$C$176,$A$55:$A$176) -> Kaizen | Q17: =IFERROR(LARGE($I$55:$I$176,O17)," ") -> 135186 | R17: =_xlfn.XLOOKUP(Q17,$I$55:$I$176,$N$55:$N$176) -> 0 | S17: =_xlfn.XLOOKUP(U17,$C$55:$C$176,$J$55:$J$176) -> 0 | T17: {=SUMPRODUCT(($C$55:$C$175=U17)*(S$54:$AG$54<=TODAY())*(ISNUMBER(S$56:$AG$176)),S$56:$AG$176)} -> 0 | U17: =IFERROR(HYPERLINK(INDEX($D$55:$D$176,MATCH(Q17,$I$55:$I$176,0)),INDEX($C$55:$C$176,MATCH(Q17,$I$55:$I$176,0)) ), "" ) -> 02 - Redução na quantidade de lâmpadas acessa, na produção | Z17: =Q17/$C$5 -> 0.029247831 | AA17: =Z17+AA16 -> 0.59306249 | AB17: {=IFERROR(INDEX($R$55:$R$176,MATCH(1,($AN$55:$AN$176=U17)*($Q$55:$Q$176="Previsto"), 0) ), "")} -> 1 | AC17: {=IFERROR( INDEX($R$55:$R$176,MATCH(1,($AN$55:$AN$176=U17)*($Q$55:$Q$176="Real"),0)),"")} -> 1 | AD17: =IF(OR(AB17="",AC17=""),"",IF(AC17=100%,"CONCLUÍDO",IF(AC17=0,IF(AB17=0,"PROJETO NÃO INICIADO","FALTA DE ACOMPANHAMENTO"),IF(AC17>AB17,"ADIANTADO",IF(AC17=AB17,"CONFORME PLANEJADO","ATRASO"))))) -> CONCLUÍDO | AE17: 1 | AS17: =AVERAGE(AS5:AS16) -> 0.4673 | AT17: =AVERAGE(AT5:AT16) -> 0.731075 | AU17: =AT17*AS17 -> 0.34163135
F18: Outros | G18: =SUMIF($B$55:$B$176,F18,$N$55:$N$176) -> 0 | O18: 13 | P18: =_xlfn.XLOOKUP(U18,$C$55:$C$176,$A$55:$A$176) -> BSW | Q18: =IFERROR(LARGE($I$55:$I$176,O18)," ") -> 115000 | R18: =_xlfn.XLOOKUP(Q18,$I$55:$I$176,$N$55:$N$176) -> 39111.77 | S18: =_xlfn.XLOOKUP(U18,$C$55:$C$176,$J$55:$J$176) -> 46174 | T18: {=SUMPRODUCT(($C$55:$C$175=U18)*(S$54:$AG$54<=TODAY())*(ISNUMBER(S$56:$AG$176)),S$56:$AG$176)} -> 0 | U18: =IFERROR(HYPERLINK(INDEX($D$55:$D$176,MATCH(Q18,$I$55:$I$176,0)),INDEX($C$55:$C$176,MATCH(Q18,$I$55:$I$176,0)) ), "" ) -> 30 - DA000491Z_DE000492Z - STC Scania G_ | Z18: =Q18/$C$5 -> 0.024880539 | AA18: =Z18+AA17 -> 0.61794303 | AB18: {=IFERROR(INDEX($R$55:$R$176,MATCH(1,($AN$55:$AN$176=U18)*($Q$55:$Q$176="Previsto"), 0) ), "")} -> 1 | AC18: {=IFERROR( INDEX($R$55:$R$176,MATCH(1,($AN$55:$AN$176=U18)*($Q$55:$Q$176="Real"),0)),"")} -> 0.95 | AD18: =IF(OR(AB18="",AC18=""),"",IF(AC18=100%,"CONCLUÍDO",IF(AC18=0,IF(AB18=0,"PROJETO NÃO INICIADO","FALTA DE ACOMPANHAMENTO"),IF(AC18>AB18,"ADIANTADO",IF(AC18=AB18,"CONFORME PLANEJADO","ATRASO"))))) -> ATRASO | AE18: 1
O19: 14 | P19: =_xlfn.XLOOKUP(U19,$C$55:$C$176,$A$55:$A$176) -> BSW | Q19: =IFERROR(LARGE($I$55:$I$176,O19)," ") -> 106000 | R19: =_xlfn.XLOOKUP(Q19,$I$55:$I$176,$N$55:$N$176) -> 99381.26 | S19: =_xlfn.XLOOKUP(U19,$C$55:$C$176,$J$55:$J$176) -> 46136 | T19: {=SUMPRODUCT(($C$55:$C$175=U19)*(S$54:$AG$54<=TODAY())*(ISNUMBER(S$56:$AG$176)),S$56:$AG$176)} -> 34660.772 | U19: =IFERROR(HYPERLINK(INDEX($D$55:$D$176,MATCH(Q19,$I$55:$I$176,0)),INDEX($C$55:$C$176,MATCH(Q19,$I$55:$I$176,0)) ), "" ) -> 45 - Redução de MP GM000409Z | Z19: =Q19/$C$5 -> 0.022933367 | AA19: =Z19+AA18 -> 0.64087639 | AB19: {=IFERROR(INDEX($R$55:$R$176,MATCH(1,($AN$55:$AN$176=U19)*($Q$55:$Q$176="Previsto"), 0) ), "")} -> 0.88 | AC19: {=IFERROR( INDEX($R$55:$R$176,MATCH(1,($AN$55:$AN$176=U19)*($Q$55:$Q$176="Real"),0)),"")} -> 0.97 | AD19: =IF(OR(AB19="",AC19=""),"",IF(AC19=100%,"CONCLUÍDO",IF(AC19=0,IF(AB19=0,"PROJETO NÃO INICIADO","FALTA DE ACOMPANHAMENTO"),IF(AC19>AB19,"ADIANTADO",IF(AC19=AB19,"CONFORME PLANEJADO","ATRASO"))))) -> ADIANTADO | AE19: 1
O20: 15 | P20: =_xlfn.XLOOKUP(U20,$C$55:$C$176,$A$55:$A$176) -> Kaizen | Q20: =IFERROR(LARGE($I$55:$I$176,O20)," ") -> 96000 | R20: =_xlfn.XLOOKUP(Q20,$I$55:$I$176,$N$55:$N$176) -> 0 | S20: =_xlfn.XLOOKUP(U20,$C$55:$C$176,$J$55:$J$176) -> 46204 | T20: {=SUMPRODUCT(($C$55:$C$175=U20)*(S$54:$AG$54<=TODAY())*(ISNUMBER(S$56:$AG$176)),S$56:$AG$176)} -> 0 | U20: =IFERROR(HYPERLINK(INDEX($D$55:$D$176,MATCH(Q20,$I$55:$I$176,0)),INDEX($C$55:$C$176,MATCH(Q20,$I$55:$I$176,0)) ), "" ) -> 43 - Automação Boomerang | Z20: =Q20/$C$5 -> 0.020769841 | AA20: =Z20+AA19 -> 0.66164623 | AB20: {=IFERROR(INDEX($R$55:$R$176,MATCH(1,($AN$55:$AN$176=U20)*($Q$55:$Q$176="Previsto"), 0) ), "")} -> 0.3 | AC20: {=IFERROR( INDEX($R$55:$R$176,MATCH(1,($AN$55:$AN$176=U20)*($Q$55:$Q$176="Real"),0)),"")} -> 0.32 | AD20: =IF(OR(AB20="",AC20=""),"",IF(AC20=100%,"CONCLUÍDO",IF(AC20=0,IF(AB20=0,"PROJETO NÃO INICIADO","FALTA DE ACOMPANHAMENTO"),IF(AC20>AB20,"ADIANTADO",IF(AC20=AB20,"CONFORME PLANEJADO","ATRASO"))))) -> ADIANTADO | AE20: 1
O21: 16 | P21: =_xlfn.XLOOKUP(U21,$C$55:$C$176,$A$55:$A$176) -> BSW | Q21: =IFERROR(LARGE($I$55:$I$176,O21)," ") -> 92500 | R21: =_xlfn.XLOOKUP(Q21,$I$55:$I$176,$N$55:$N$176) -> 153302.58 | S21: =_xlfn.XLOOKUP(U21,$C$55:$C$176,$J$55:$J$176) -> 46174 | T21: {=SUMPRODUCT(($C$55:$C$175=U21)*(S$54:$AG$54<=TODAY())*(ISNUMBER(S$56:$AG$176)),S$56:$AG$176)} -> 0 | U21: =IFERROR(HYPERLINK(INDEX($D$55:$D$176,MATCH(Q21,$I$55:$I$176,0)),INDEX($C$55:$C$176,MATCH(Q21,$I$55:$I$176,0)) ), "" ) -> 50 - Suporte da lanterna MB003681 | Z21: =Q21/$C$5 -> 0.020012608 | AA21: =Z21+AA20 -> 0.68165884 | AB21: {=IFERROR(INDEX($R$55:$R$176,MATCH(1,($AN$55:$AN$176=U21)*($Q$55:$Q$176="Previsto"), 0) ), "")} -> 0.86 | AC21: {=IFERROR( INDEX($R$55:$R$176,MATCH(1,($AN$55:$AN$176=U21)*($Q$55:$Q$176="Real"),0)),"")} -> 0.86 | AD21: =IF(OR(AB21="",AC21=""),"",IF(AC21=100%,"CONCLUÍDO",IF(AC21=0,IF(AB21=0,"PROJETO NÃO INICIADO","FALTA DE ACOMPANHAMENTO"),IF(AC21>AB21,"ADIANTADO",IF(AC21=AB21,"CONFORME PLANEJADO","ATRASO"))))) -> CONFORME PLANEJADO | AE21: 1
O22: 17 | P22: =_xlfn.XLOOKUP(U22,$C$55:$C$176,$A$55:$A$176) -> BSW | Q22: =IFERROR(LARGE($I$55:$I$176,O22)," ") -> 91200 | R22: =_xlfn.XLOOKUP(Q22,$I$55:$I$176,$N$55:$N$176) -> 28666.41 | S22: =_xlfn.XLOOKUP(U22,$C$55:$C$176,$J$55:$J$176) -> 46204 | T22: {=SUMPRODUCT(($C$55:$C$175=U22)*(S$54:$AG$54<=TODAY())*(ISNUMBER(S$56:$AG$176)),S$56:$AG$176)} -> 0 | U22: =IFERROR(HYPERLINK(INDEX($D$55:$D$176,MATCH(Q22,$I$55:$I$176,0)),INDEX($C$55:$C$176,MATCH(Q22,$I$55:$I$176,0)) ), "" ) -> 56 -Redução de Peso Bruto do item SV001141LA / SV001142LA | Z22: =Q22/$C$5 -> 0.019731349 | AA22: =Z22+AA21 -> 0.70139019 | AB22: {=IFERROR(INDEX($R$55:$R$176,MATCH(1,($AN$55:$AN$176=U22)*($Q$55:$Q$176="Previsto"), 0) ), "")} -> 0.86792453 | AC22: {=IFERROR( INDEX($R$55:$R$176,MATCH(1,($AN$55:$AN$176=U22)*($Q$55:$Q$176="Real"),0)),"")} -> 0.75 | AD22: =IF(OR(AB22="",AC22=""),"",IF(AC22=100%,"CONCLUÍDO",IF(AC22=0,IF(AB22=0,"PROJETO NÃO INICIADO","FALTA DE ACOMPANHAMENTO"),IF(AC22>AB22,"ADIANTADO",IF(AC22=AB22,"CONFORME PLANEJADO","ATRASO"))))) -> ATRASO | AE22: 1
O23: 18 | P23: =_xlfn.XLOOKUP(U23,$C$55:$C$176,$A$55:$A$176) -> BSW | Q23: =IFERROR(LARGE($I$55:$I$176,O23)," ") -> 90000 | R23: =_xlfn.XLOOKUP(Q23,$I$55:$I$176,$N$55:$N$176) -> 41632.63 | S23: =_xlfn.XLOOKUP(U23,$C$55:$C$176,$J$55:$J$176) -> 46174 | T23: {=SUMPRODUCT(($C$55:$C$175=U23)*(S$54:$AG$54<=TODAY())*(ISNUMBER(S$56:$AG$176)),S$56:$AG$176)} -> 0 | U23: =IFERROR(HYPERLINK(INDEX($D$55:$D$176,MATCH(Q23,$I$55:$I$176,0)),INDEX($C$55:$C$176,MATCH(Q23,$I$55:$I$176,0)) ), "" ) -> 27 - DA000459AA - STC Volvo_ | Z23: =Q23/$C$5 -> 0.019471726 | AA23: =Z23+AA22 -> 0.72086192 | AB23: {=IFERROR(INDEX($R$55:$R$176,MATCH(1,($AN$55:$AN$176=U23)*($Q$55:$Q$176="Previsto"), 0) ), "")} -> 1 | AC23: {=IFERROR( INDEX($R$55:$R$176,MATCH(1,($AN$55:$AN$176=U23)*($Q$55:$Q$176="Real"),0)),"")} -> 1 | AD23: =IF(OR(AB23="",AC23=""),"",IF(AC23=100%,"CONCLUÍDO",IF(AC23=0,IF(AB23=0,"PROJETO NÃO INICIADO","FALTA DE ACOMPANHAMENTO"),IF(AC23>AB23,"ADIANTADO",IF(AC23=AB23,"CONFORME PLANEJADO","ATRASO"))))) -> CONCLUÍDO | AE23: 1
O24: 19 | P24: =_xlfn.XLOOKUP(U24,$C$55:$C$176,$A$55:$A$176) -> Redução de custo | Q24: =IFERROR(LARGE($I$55:$I$176,O24)," ") -> 68000 | R24: =_xlfn.XLOOKUP(Q24,$I$55:$I$176,$N$55:$N$176) -> 56610.76 | S24: =_xlfn.XLOOKUP(U24,$C$55:$C$176,$J$55:$J$176) -> 46082 | T24: {=SUMPRODUCT(($C$55:$C$175=U24)*(S$54:$AG$54<=TODAY())*(ISNUMBER(S$56:$AG$176)),S$56:$AG$176)} -> 15439.298 | U24: =IFERROR(HYPERLINK(INDEX($D$55:$D$176,MATCH(Q24,$I$55:$I$176,0)),INDEX($C$55:$C$176,MATCH(Q24,$I$55:$I$176,0)) ), "" ) -> 05 - Empilhadeira - Diadema | Z24: =Q24/$C$5 -> 0.014711971 | AA24: =Z24+AA23 -> 0.73557389 | AB24: {=IFERROR(INDEX($R$55:$R$176,MATCH(1,($AN$55:$AN$176=U24)*($Q$55:$Q$176="Previsto"), 0) ), "")} -> 1 | AC24: {=IFERROR( INDEX($R$55:$R$176,MATCH(1,($AN$55:$AN$176=U24)*($Q$55:$Q$176="Real"),0)),"")} -> 1 | AD24: =IF(OR(AB24="",AC24=""),"",IF(AC24=100%,"CONCLUÍDO",IF(AC24=0,IF(AB24=0,"PROJETO NÃO INICIADO","FALTA DE ACOMPANHAMENTO"),IF(AC24>AB24,"ADIANTADO",IF(AC24=AB24,"CONFORME PLANEJADO","ATRASO"))))) -> CONCLUÍDO | AE24: 1
O25: 20 | P25: =_xlfn.XLOOKUP(U25,$C$55:$C$176,$A$55:$A$176) -> BSW | Q25: =IFERROR(LARGE($I$55:$I$176,O25)," ") -> 63600 | R25: =_xlfn.XLOOKUP(Q25,$I$55:$I$176,$N$55:$N$176) -> 0 | S25: =_xlfn.XLOOKUP(U25,$C$55:$C$176,$J$55:$J$176) -> 46204 | T25: {=SUMPRODUCT(($C$55:$C$175=U25)*(S$54:$AG$54<=TODAY())*(ISNUMBER(S$56:$AG$176)),S$56:$AG$176)} -> 0 | U25: =IFERROR( HYPERLINK( INDEX(Diadema!$D$55:$D$176, MATCH(Q25,Diadema!$I$55:$I$176,0) ), INDEX(Diadema!$C$55:$C$176, MATCH(Q25,Diadema!$I$55:$I$176,0) ) ), "" ) -> 49 - REDUÇÃO DE MP GM000408Z / GM000409Z | Z25: =Q25/$C$5 -> 0.01376002 | AA25: =Z25+AA24 -> 0.74933391 | AB25: {=IFERROR(INDEX($R$55:$R$176,MATCH(1,($AN$55:$AN$176=U25)*($Q$55:$Q$176="Previsto"), 0) ), "")} -> 0.28 | AC25: {=IFERROR( INDEX($R$55:$R$176,MATCH(1,($AN$55:$AN$176=U25)*($Q$55:$Q$176="Real"),0)),"")} -> 1 | AD25: =IF(OR(AB25="",AC25=""),"",IF(AC25=100%,"CONCLUÍDO",IF(AC25=0,IF(AB25=0,"PROJETO NÃO INICIADO","FALTA DE ACOMPANHAMENTO"),IF(AC25>AB25,"ADIANTADO",IF(AC25=AB25,"CONFORME PLANEJADO","ATRASO"))))) -> CONCLUÍDO | AE25: 0.5
O26: Total | Q26: =SUM(Q6:Q25) -> 3463486 | R26: =SUM(R6:R25) -> 1754354.7
A27: 1. KPIs ESTRATÉGICOS
A28: CATEGORIA | B28: KPI | C28: UN | D28: Frequência | E28: TIPO | F28: BASELINE 2025 | G28: META 2026 | H28: Jan | I28: P. Ofensor1 | J28: Fev | K28: P. Ofensor2 | L28: Mar | M28: P. Ofensor3 | N28: Abr | O28: P. Ofensor4 | P28: Mai | Q28: P. Ofensor5 | R28: Jun | S28: P. Ofensor6 | T28: Jul | U28: P. Ofensor7 | V28: Ago | W28: P. Ofensor8 | X28: Set | Y28: P. Ofensor9 | Z28: Out | AA28: P. Ofensor10 | AB28: Nov | AC28: P. Ofensor11 | AD28: Dez | AE28: P. Ofensor12
A29: Financeiro | B29: Margem VA | C29: % | D29: Mensal | E29: Maior Melhor ↑ | F29: 0.346 | G29: 0.361 | H29: 0.321 | I29: Matéria Prima | J29: 0.33 | K29: Matéria Prima | L29: 0.326 | M29: Matéria Prima | N29: 0.358 | O29: Matéria Prima | P29: 0.358 | Q29: Matéria Prima
A30: Financeiro | B30: Custo de Scrap (Refugo) | C30: % | D30: Mensal | E30: Menor Melhor ↓ | F30: 0.003 | G30: 0.002 | H30: 0.00201 | I30: Rachadura | J30: 0.0065 | K30: Rachadura | L30: 0.0042 | M30: Rachadura | N30: 0.0043 | O30: Rachadura | P30: 0.0028 | Q30: Rachadura
A31: Operacional | B31: OEE Prensas Grandes (24) | C31: % | D31: Semanal | E31: Maior Melhor ↑ | F31: 0.501 | G31: 0.56 | H31: 0.4843 | I31: Falta de energia | J31: =J33*J34*J35 -> 0.51104832 | K31: Manutenção | L31: =L33*L34*L35 -> 0.66519873 | M31: Manutenção | N31: 0.7202 | O31: Manutenção | P31: 0.6949 | Q31: Manutenção
A32: Operacional | B32: Eficiência de MO Planta | C32: % | D32: Mensal | E32: Maior Melhor ↑ | F32: 0.562 | G32: 0.64 | H32: 0.551 | I32: Falta de energia | J32: 0.561 | K32: Falta de energia | L32: 0.53 | M32: Falta de OP | N32: 0.508 | O32: Falta de OP | P32: 0.523 | Q32: Falta de OP
A33: Operacional | B33: Performance Prensas Grandes (24) | C33: % | D33: Semanal | E33: Maior Melhor ↑ | F33: 0.9261 | G33: 0.95 | H33: 0.8992 | I33: Falta de energia | J33: 0.8879 | K33: Manutenção | L33: 0.9508 | M33: Manutenção | N33: 0.9717 | O33: Manutenção | P33: 0.9461 | Q33: Manutenção
A34: Operacional | B34: Qualidade Prensas Grandes (24) | C34: % | D34: Semanal | E34: Maior Melhor ↑ | F34: 0.955 | G34: 0.965 | H34: 0.9995 | I34: Ferramentaria | J34: 0.9996 | K34: Ferramentaria | L34: 0.9996 | M34: Manutenção | N34: 0.9997 | O34: Manutenção | P34: 0.9997 | Q34: Manutenção
A35: Operacional | B35: Disponibilidade Prensas Grandes (24) | C35: % | D35: Semanal | E35: Maior Melhor ↑ | F35: 0.959 | G35: 0.97 | H35: 0.5389 | I35: Ferramentaria | J35: 0.5758 | K35: Ferramentaria | L35: 0.6999 | M35: Manutenção | N35: 0.7414 | O35: Manutenção | P35: 0.7347 | Q35: Manutenção
A36: Operacional | B36: MTBF (Manutenção) | C36: h | D36: Mensal | E36: Maior Melhor ↑ | F36: 13:00 | G36: 15:00 | H36: 0.625 | I36: Quebra mecânica | J36: 0.54166667 | K36: Quebra mecânica | L36: 0.875 | M36: Quebra mecânica | N36: 1.5 | O36: Quebra mecânica | P36: 1.5 | Q36: Quebra mecânica
A37: Operacional | B37: MTTR (Manutenção) | C37: h | D37: Mensal | E37: Menor Melhor ↓ | F37: 0:33 | G37: 0:30 | H37: 00:15 | I37: Problema com CLP | J37: 0.048611111 | K37: Quebra mecânica | L37: 0.052083333 | M37: Quebra mecânica | N37: 0.031944444 | O37: Quebra mecânica | P37: 0.038888889 | Q37: Quebra mecânica
A38: Operacional | B38: Horas Extras | C38: Valor | D38: Mensal | E38: Menor Melhor ↓ | F38: 91000 | G38: 73000 | H38: 108458.31 | I38: Manutenção | J38: 81579 | K38: Manutenção | L38: =5000+87000 -> 92000 | M38: Manutenção | N38: 97860 | O38: Manutenção | P38: 96507 | Q38: Manutenção
A39: Operacional | B39: Acuracidade Estoque | C39: Valor | D39: Semanal | E39: Menor Melhor ↓ | F39: 458000 | G39: 358737 | H39: 29000 | I39: Apontamento incorreto | J39: 30000 | K39: Apontamento incorreto | L39: 6176 | M39: Apontamento incorreto | N39: 5680 | O39: Mat. sem saldo | P39: 213.12 | Q39: Mat. sem saldo
A40: Qualidade | B40: PPM Interno | C40: ppm | D40: Mensal | E40: Menor Melhor ↓ | F40: - | G40: 900 | H40: 60593 | I40: Rebarba | J40: 57795 | K40: Rebarba | L40: 19052 | M40: Rebarba | N40: 59710 | O40: Rebarba | P40: 60162 | Q40: Rebarba
A41: Qualidade | B41: PPM Externo | C41: ppm | D41: Mensal | E41: Menor Melhor ↓ | F41: 3347 | G41: 3000 | H41: 1 | I41: Solda irregular | J41: 476 | K41: Falta de rosca | L41: 80 | M41: Quebra de FIFO | N41: 30 | O41: Falta de componente | P41: 1 | Q41: Dimensional
A42: Qualidade | B42: CONC | C42: % | D42: Mensal | E42: Menor Melhor ↓ | F42: 0.026 | G42: 0.016 | H42: 0.0098 | I42: Horas extras | J42: 0.0142 | K42: Refugo | L42: 0.0106 | M42: Horas extras | N42: 0.0162 | O42: Refugo | P42: 0.0142 | Q42: Frete estra
A43: Qualidade | B43: Reclamações de Clientes | C43: qtd | D43: Diário | E43: Menor Melhor ↓ | F43: 49 | G43: 45 | H43: 1 | I43: Solda irregular | J43: 2 | K43: Rosca obstruída | L43: 2 | M43: Quebra de FIFO | N43: 2 | O43: Falta de componente | P43: 3 | Q43: Dimensional
A44: Segurança | B44: Taxa de Frequência de Acidente | C44: taxa | D44: Mensal | E44: Menor Melhor ↓ | F44: 28 | G44: 26 | H44: 32 | I44: Lesão dedos | J44: 30 | K44: Lesão dedos | L44: 13 | M44: Lesão dedos | N44: 0 | O44: Lesão dedos | P44: 0 | Q44: Lesão dedos
A45: Validação Processo | B45: % Conformidade vs POC | C45: % | D45: P/ Prioridade | E45: Maior Melhor ↑ | F45: - | G45: 1 | H45: 0 | I45: Engenharia | J45: 0.1 | K45: Custos | L45: 0.13 | M45: Custos | N45: 0.13 | O45: Custos | P45: 0.16 | Q45: Engenharia | AG45: Departamento Suporte
A46: Sistema de Produção Delga (SPD) | B46: % Aderência às Ferramentas SPD | C46: % | D46: Semanal | E46: Maior Melhor ↑ | F46: - | G46: 1 | H46: 0.32 | I46: Logística | J46: 0.87 | K46: Logística | L46: 0.47 | M46: Produção | N46: 0.61 | O46: Produção | P46: 0.64 | Q46: Produção | AG46: Departamentos | AH46: Valor de Impacto
A47: Operacional | B47: MTBF (Ferramentaria) | C47: h | D47: Mensal | E47: Maior Melhor ↑ | F47: 80:00 | G47: 60:00 | H47: 54:25 | I47: Qualidade/dimensional | J47: 57:08 | K47: Qualidade/dimensional | L47: 74:31 | M47: Qualidade/dimensional | N47: 3.4520833 | O47: Linhas de corte/ajustes | P47: 4.7284722 | Q47: Rebarbas | AG47: Compras | AH47: =SUMIF($AK$55:$AK$106,AG47,$AM$55:$AM$106) -> 0
A48: Operacional | B48: MTTR (Ferramentaria) | C48: h | D48: Mensal | E48: Menor Melhor ↓ | F48: 2:00 | G48: 1:45 | H48: 0.088194444 | I48: Qualidade/dimensional | J48: 0.058333333 | K48: Rebarbas | L48: 0.061805556 | M48: Rebarbas | N48: 0.10277778 | O48: Qualidade/dimensional | P48: 0.070833333 | Q48: Qualidade/dimensional | AG48: Vendas | AH48: =SUMIF($AK$55:$AK$106,AG48,$AM$55:$AM$106) -> 0
A49: Gerente de Planta | B49: Performance de GESTÂO | C49: R$ | D49: Mensal | E49: Maior Melhor ↑ | H49: 170000 | J49: 110000 | L49: 487000 | AG49: Orçamento | AH49: =SUMIF($AK$55:$AK$106,AG49,$AM$55:$AM$106) -> 0
AG50: Simulação | AH50: =SUMIF($AK$55:$AK$106,AG50,$AM$55:$AM$106) -> 0
AG51: Eng. Corporativa | AH51: =SUMIF($AK$55:$AK$106,AG51,$AM$55:$AM$106) -> 0
A53: 2. IDEIAS DE KAIZENS E PROJETOS DE REDUÇÃO DE CUSTOS | U53: 1° Tri | X53: 2° Tri | AB53: 3° Tri | AF53: 4° Tri
A54: TIPO Redução de custos Kaizen / Você resolve | B54: VA / GGF / Material Auxiliar | C54: Nome do Projeto | D54: Caminho da Evidência | E54: DESCRIÇÃO | F54: RESPONSÁVEL | G54: Inicio Mês/Ano | H54: Termino Mês/Ano | I54: Previsto (R$) | J54: Mês do 1º RETORNO | K54: Quantidade de meses com retorno | L54: Processo de entrega do projeto a custos | M54: VALIDADOR OK / NOK CUSTOS | N54: SAVING VALIDADO (R$ Valor) | O54: Status | P54: % Responsabilidade Delga | Q54: Previsto /Real | R54: Avanço | S54: 46023 | T54: 46054 | U54: 46082 | V54: Total 1° Tri | W54: 46113 | X54: 46143 | Y54: 46174 | Z54: Total 2° Tri | AA54: 46204 | AB54: 46235 | AC54: 46266 | AD54: Total 3° Tri | AE54: 46296 | AF54: 46327 | AG54: 46357 | AH54: Total 4° Tri | AI54: Total Ano | AJ54: OBS | AK54: Departamento Suporte | AL54: % de Impacto | AM54: Impacto Financeiro | AN54: proj ref. | AP54: Retorno até hoje
A55: BSW | B55: VA | C55: 01 - Redução de peso bruto DA000489A | D55: \\192.168.0.20\DEPARTAMENTOS\\Engenharia\0. Kaizen Diadema\6. 2026\01 Janeiro\01 - DA000489AB -Bruno Manachini_Engenharia\01 - KAIZEN - DA000489AB_Rev00_Bruno Manachini.xlsx | E55: Peso bruto: de 4,27 Kg / peça para 4,18kg / peça | F55: B. Manachini | G55: 46027 | H55: 46087 | I55: 331600 | J55: 46082 | K55: =IF(J55="", "", 12 - MONTH(J55) + 1) -> 10 | M55: OK | N55: 160178.29 | O55: ✓ Concluído | P55: 1 | Q55: Previsto | R55: 1 | S55: =IFERROR(IF(AND(S$54>=EOMONTH($J55,-1)+1,S$54<=EOMONTH(EOMONTH($J55,-1)+1,$K55-1)),IF(NOT(ISBLANK($N55)),$N55/$K55,$I55/$K55),0),0) -> 0 | T55: =IFERROR(IF(AND(T$54>=EOMONTH($J55,-1)+1,T$54<=EOMONTH(EOMONTH($J55,-1)+1,$K55-1)),IF(NOT(ISBLANK($N55)),$N55/$K55,$I55/$K55),0),0) -> 0 | U55: =IFERROR(IF(AND(U$54>=EOMONTH($J55,-1)+1,U$54<=EOMONTH(EOMONTH($J55,-1)+1,$K55-1)),IF(NOT(ISBLANK($N55)),$N55/$K55,$I55/$K55),0),0) -> 16017.829 | V55: =SUM(S55:U55) -> 16017.829 | W55: =IFERROR(IF(AND(W$54>=EOMONTH($J55,-1)+1,W$54<=EOMONTH(EOMONTH($J55,-1)+1,$K55-1)),IF(NOT(ISBLANK($N55)),$N55/$K55,$I55/$K55),0),0) -> 16017.829 | X55: =IFERROR(IF(AND(X$54>=EOMONTH($J55,-1)+1,X$54<=EOMONTH(EOMONTH($J55,-1)+1,$K55-1)),IF(NOT(ISBLANK($N55)),$N55/$K55,$I55/$K55),0),0) -> 16017.829 | Y55: =IFERROR(IF(AND(Y$54>=EOMONTH($J55,-1)+1,Y$54<=EOMONTH(EOMONTH($J55,-1)+1,$K55-1)),IF(NOT(ISBLANK($N55)),$N55/$K55,$I55/$K55),0),0) -> 16017.829 | Z55: =SUM(W55:Y55) -> 48053.487 | AA55: =IFERROR(IF(AND(AA$54>=EOMONTH($J55,-1)+1,AA$54<=EOMONTH(EOMONTH($J55,-1)+1,$K55-1)),IF(NOT(ISBLANK($N55)),$N55/$K55,$I55/$K55),0),0) -> 16017.829 | AB55: =IFERROR(IF(AND(AB$54>=EOMONTH($J55,-1)+1,AB$54<=EOMONTH(EOMONTH($J55,-1)+1,$K55-1)),IF(NOT(ISBLANK($N55)),$N55/$K55,$I55/$K55),0),0) -> 16017.829 | AC55: =IFERROR(IF(AND(AC$54>=EOMONTH($J55,-1)+1,AC$54<=EOMONTH(EOMONTH($J55,-1)+1,$K55-1)),IF(NOT(ISBLANK($N55)),$N55/$K55,$I55/$K55),0),0) -> 16017.829 | AD55: =SUM(AA55:AC55) -> 48053.487 | AE55: =IFERROR(IF(AND(AE$54>=EOMONTH($J55,-1)+1,AE$54<=EOMONTH(EOMONTH($J55,-1)+1,$K55-1)),IF(NOT(ISBLANK($N55)),$N55/$K55,$I55/$K55),0),0) -> 16017.829 | AF55: =IFERROR(IF(AND(AF$54>=EOMONTH($J55,-1)+1,AF$54<=EOMONTH(EOMONTH($J55,-1)+1,$K55-1)),IF(NOT(ISBLANK($N55)),$N55/$K55,$I55/$K55),0),0) -> 16017.829 | AG55: =IFERROR(IF(AND(AG$54>=EOMONTH($J55,-1)+1,AG$54<=EOMONTH(EOMONTH($J55,-1)+1,$K55-1)),IF(NOT(ISBLANK($N55)),$N55/$K55,$I55/$K55),0),0) -> 16017.829 | AH55: =SUM(AE55:AG55) -> 48053.487 | AI55: =SUM(V55,Z55,AD55,AH55) -> 160178.29 | AJ55: Validado pela Carolina Reis Machado em 18/12/2025 (e-mail 11:55) - Redução de Peso Bruto do item DA000489AB (Reforço Sup. Tanque) - Revisão em 09/02 - baseado no volume Budget dos itens faturados (Mar a Dez) - considerado apenas a variação do custo peça, pois os processos embora mudem, no efeito resultado continuamos pagando a mão de obra de 2 operadores. | AM55: =N55*AL55 -> 0 | AN55: =C55 -> 01 - Redução de peso bruto DA000489A | AO55: P | AP55: {=IF(OR(AN55="",AN55=0),"",IF(SUMPRODUCT(($C$55:$C$175=AN55)*(S$54:$AG$54<EOMONTH(TODAY(),-1)+1)*(ISNUMBER(S$55:$AG$175)),S$55:$AG$175)=0,"",SUMPRODUCT(($C$55:$C$175=AN55)*(S$54:$AG$54<EOMONTH(TODAY(),-1)+1)*(ISNUMBER(S$55:$AG$175)),S$55:$AG$175)))} -> 48053.487
Q56: Real | R56: 1 | S56: 0 | U56: 12674.077 | V56: =SUM(S56:U56) -> 12674.077 | W56: 17853.917 | X56: 21160.198 | Z56: =SUM(W56:Y56) -> 39014.116 | AD56: =SUM(AA56:AC56) -> 0 | AH56: =SUM(AE56:AG56) -> 0 | AI56: =SUM(V56,Z56,AD56,AH56) -> 51688.193 | AJ56: Projeto de kaizen número 01 de 2026. E-mail de revalidação enviado em 10/02/2026 16h12 - Carolina Rodrigues. | AN56: =C55 -> 01 - Redução de peso bruto DA000489A | AO56: R | AP56: {=IF(OR(AN56="",AN56=0),"",IF(SUMPRODUCT(($C$55:$C$175=AN56)*($S$54:AG$54<=TODAY())*(ISNUMBER($S$56:AG$176)),$S$56:AG$176)=0,"",SUMPRODUCT(($C$55:$C$175=AN56)*($S$54:AG$54<=TODAY())*(ISNUMBER($S$56:AG$176)),$S$56:AG$176)))} -> 51688.193
A57: Kaizen | B57: GGF | C57: 02 - Redução na quantidade de lâmpadas acessa, na produção | D57: \\192.168.0.20\DEPARTAMENTOS\Engenharia\0. Kaizen Diadema\6. 2026\02 Fevereiro\09 - Redução de lampadas acessas na fábrica_Eduardo Fajardo_Concluído\9 - Kaizen Redução de lampadas acessas na fábrica_Eduardo Fajardo.xlsx | E57: Redução no consumo de energia elétrica, por meio do desligamento de lâmpadas e redistribuição, sem afetar iluminamento | F57: E. Fajardo | G57: 46032 | H57: 46081 | I57: 135186 | O57: ✓ Concluído | P57: 1 | Q57: Previsto | R57: 1 | S57: =IFERROR(IF(AND(S$54>=EOMONTH($J57,-1)+1,S$54<=EOMONTH(EOMONTH($J57,-1)+1,$K57-1)),IF(NOT(ISBLANK($N57)),$N57/$K57,$I57/$K57),0),0) -> 0 | T57: =IFERROR(IF(AND(T$54>=EOMONTH($J57,-1)+1,T$54<=EOMONTH(EOMONTH($J57,-1)+1,$K57-1)),IF(NOT(ISBLANK($N57)),$N57/$K57,$I57/$K57),0),0) -> 0 | U57: =IFERROR(IF(AND(U$54>=EOMONTH($J57,-1)+1,U$54<=EOMONTH(EOMONTH($J57,-1)+1,$K57-1)),IF(NOT(ISBLANK($N57)),$N57/$K57,$I57/$K57),0),0) -> 0 | V57: =SUM(S57:U57) -> 0 | W57: =IFERROR(IF(AND(W$54>=EOMONTH($J57,-1)+1,W$54<=EOMONTH(EOMONTH($J57,-1)+1,$K57-1)),IF(NOT(ISBLANK($N57)),$N57/$K57,$I57/$K57),0),0) -> 0 | X57: =IFERROR(IF(AND(X$54>=EOMONTH($J57,-1)+1,X$54<=EOMONTH(EOMONTH($J57,-1)+1,$K57-1)),IF(NOT(ISBLANK($N57)),$N57/$K57,$I57/$K57),0),0) -> 0 | Y57: =IFERROR(IF(AND(Y$54>=EOMONTH($J57,-1)+1,Y$54<=EOMONTH(EOMONTH($J57,-1)+1,$K57-1)),IF(NOT(ISBLANK($N57)),$N57/$K57,$I57/$K57),0),0) -> 0 | Z57: =SUM(W57:Y57) -> 0 | AA57: =IFERROR(IF(AND(AA$54>=EOMONTH($J57,-1)+1,AA$54<=EOMONTH(EOMONTH($J57,-1)+1,$K57-1)),IF(NOT(ISBLANK($N57)),$N57/$K57,$I57/$K57),0),0) -> 0 | AB57: =IFERROR(IF(AND(AB$54>=EOMONTH($J57,-1)+1,AB$54<=EOMONTH(EOMONTH($J57,-1)+1,$K57-1)),IF(NOT(ISBLANK($N57)),$N57/$K57,$I57/$K57),0),0) -> 0 | AC57: =IFERROR(IF(AND(AC$54>=EOMONTH($J57,-1)+1,AC$54<=EOMONTH(EOMONTH($J57,-1)+1,$K57-1)),IF(NOT(ISBLANK($N57)),$N57/$K57,$I57/$K57),0),0) -> 0 | AD57: =SUM(AA57:AC57) -> 0 | AE57: =IFERROR(IF(AND(AE$54>=EOMONTH($J57,-1)+1,AE$54<=EOMONTH(EOMONTH($J57,-1)+1,$K57-1)),IF(NOT(ISBLANK($N57)),$N57/$K57,$I57/$K57),0),0) -> 0 | AF57: =IFERROR(IF(AND(AF$54>=EOMONTH($J57,-1)+1,AF$54<=EOMONTH(EOMONTH($J57,-1)+1,$K57-1)),IF(NOT(ISBLANK($N57)),$N57/$K57,$I57/$K57),0),0) -> 0 | AG57: =IFERROR(IF(AND(AG$54>=EOMONTH($J57,-1)+1,AG$54<=EOMONTH(EOMONTH($J57,-1)+1,$K57-1)),IF(NOT(ISBLANK($N57)),$N57/$K57,$I57/$K57),0),0) -> 0 | AH57: =SUM(AE57:AG57) -> 0 | AI57: =SUM(V57,Z57,AD57,AH57) -> 0 | AJ57: 100 luminárias x 180W = 18KWh. 18KWh x 24h x 6dias = 2.592 x 4,2 semanas = 10.886KWh x R$1,00 = R$ 10.886,00 por mês | AM57: =N57*AL57 -> 0 | AN57: =C57 -> 02 - Redução na quantidade de lâmpadas acessa, na produção | AO57: P | AP57: {=IF(OR(AN57="",AN57=0),"",IF(SUMPRODUCT(($C$55:$C$175=AN57)*(S$54:$AG$54<EOMONTH(TODAY(),-1)+1)*(ISNUMBER(S$55:$AG$175)),S$55:$AG$175)=0,"",SUMPRODUCT(($C$55:$C$175=AN57)*(S$54:$AG$54<EOMONTH(TODAY(),-1)+1)*(ISNUMBER(S$55:$AG$175)),S$55:$AG$175)))}
Q58: Real | R58: 1 | V58: =SUM(S58:U58) -> 0 | Z58: =SUM(W58:Y58) -> 0 | AD58: =SUM(AA58:AC58) -> 0 | AH58: =SUM(AE58:AG58) -> 0 | AI58: =SUM(V58,Z58,AD58,AH58) -> 0 | AJ58: O baseline 401,7KWh para cada 1.000 peças vendidas. Projeto de kaizen número 09 de 2026 | AN58: =C57 -> 02 - Redução na quantidade de lâmpadas acessa, na produção | AO58: R | AP58: {=IF(OR(AN58="",AN58=0),"",IF(SUMPRODUCT(($C$55:$C$175=AN58)*($S$54:AG$54<=TODAY())*(ISNUMBER($S$56:AG$176)),$S$56:AG$176)=0,"",SUMPRODUCT(($C$55:$C$175=AN58)*($S$54:AG$54<=TODAY())*(ISNUMBER($S$56:AG$176)),$S$56:AG$176)))}
A59: Kaizen | B59: GGF | C59: 03 - Otimização de processo - Cavalo Marinho | D59: \\192.168.0.20\DEPARTAMENTOS\\Engenharia\0. Kaizen Diadema\6. 2026\01 Janeiro\03 - GM000463Z_GM000359AA_Robson Luz_Engenharia\3 - Eficiência_Operacional - GM000359AA_GM000463Z_REV01.xlsx | E59: Atualmente usa-se 8 MO e 4 prensas. A proposta é usar 2 prensas e 6MO | F59: R. Luz | G59: 46023 | H59: 46112 | I59: 24000.001 | J59: 46082 | K59: =IF(J59="", "", 12 - MONTH(J59) + 1) -> 10 | O59: ✓ Concluído | P59: 1 | Q59: Previsto | R59: 1 | S59: =IFERROR(IF(AND(S$54>=EOMONTH($J59,-1)+1,S$54<=EOMONTH(EOMONTH($J59,-1)+1,$K59-1)),IF(NOT(ISBLANK($N59)),$N59/$K59,$I59/$K59),0),0) -> 0 | T59: =IFERROR(IF(AND(T$54>=EOMONTH($J59,-1)+1,T$54<=EOMONTH(EOMONTH($J59,-1)+1,$K59-1)),IF(NOT(ISBLANK($N59)),$N59/$K59,$I59/$K59),0),0) -> 0 | U59: =IFERROR(IF(AND(U$54>=EOMONTH($J59,-1)+1,U$54<=EOMONTH(EOMONTH($J59,-1)+1,$K59-1)),IF(NOT(ISBLANK($N59)),$N59/$K59,$I59/$K59),0),0) -> 2400.0001 | V59: =SUM(S59:U59) -> 2400.0001 | W59: =IFERROR(IF(AND(W$54>=EOMONTH($J59,-1)+1,W$54<=EOMONTH(EOMONTH($J59,-1)+1,$K59-1)),IF(NOT(ISBLANK($N59)),$N59/$K59,$I59/$K59),0),0) -> 2400.0001 | X59: =IFERROR(IF(AND(X$54>=EOMONTH($J59,-1)+1,X$54<=EOMONTH(EOMONTH($J59,-1)+1,$K59-1)),IF(NOT(ISBLANK($N59)),$N59/$K59,$I59/$K59),0),0) -> 2400.0001 | Y59: =IFERROR(IF(AND(Y$54>=EOMONTH($J59,-1)+1,Y$54<=EOMONTH(EOMONTH($J59,-1)+1,$K59-1)),IF(NOT(ISBLANK($N59)),$N59/$K59,$I59/$K59),0),0) -> 2400.0001 | Z59: =SUM(W59:Y59) -> 7200.0003 | AA59: =IFERROR(IF(AND(AA$54>=EOMONTH($J59,-1)+1,AA$54<=EOMONTH(EOMONTH($J59,-1)+1,$K59-1)),IF(NOT(ISBLANK($N59)),$N59/$K59,$I59/$K59),0),0) -> 2400.0001 | AB59: =IFERROR(IF(AND(AB$54>=EOMONTH($J59,-1)+1,AB$54<=EOMONTH(EOMONTH($J59,-1)+1,$K59-1)),IF(NOT(ISBLANK($N59)),$N59/$K59,$I59/$K59),0),0) -> 2400.0001 | AC59: =IFERROR(IF(AND(AC$54>=EOMONTH($J59,-1)+1,AC$54<=EOMONTH(EOMONTH($J59,-1)+1,$K59-1)),IF(NOT(ISBLANK($N59)),$N59/$K59,$I59/$K59),0),0) -> 2400.0001 | AD59: =SUM(AA59:AC59) -> 7200.0003 | AE59: =IFERROR(IF(AND(AE$54>=EOMONTH($J59,-1)+1,AE$54<=EOMONTH(EOMONTH($J59,-1)+1,$K59-1)),IF(NOT(ISBLANK($N59)),$N59/$K59,$I59/$K59),0),0) -> 2400.0001 | AF59: =IFERROR(IF(AND(AF$54>=EOMONTH($J59,-1)+1,AF$54<=EOMONTH(EOMONTH($J59,-1)+1,$K59-1)),IF(NOT(ISBLANK($N59)),$N59/$K59,$I59/$K59),0),0) -> 2400.0001 | AG59: =IFERROR(IF(AND(AG$54>=EOMONTH($J59,-1)+1,AG$54<=EOMONTH(EOMONTH($J59,-1)+1,$K59-1)),IF(NOT(ISBLANK($N59)),$N59/$K59,$I59/$K59),0),0) -> 2400.0001 | AH59: =SUM(AE59:AG59) -> 7200.0003 | AI59: =SUM(V59,Z59,AD59,AH59) -> 24000.001 | AJ59: Spin 3k pçs/mês, 2 corridas mensais, 180pçs/hora. 1500/180 = 8,33h x 2 = 16,66 x 8 MO = 133,3h. 16,6h x 6MO = 100h. Logo, save de 33,3h / 166 = 0,2MO. Projeto kaizen 03 2026 | AM59: =N59*AL59 -> 0 | AN59: =C59 -> 03 - Otimização de processo - Cavalo Marinho | AO59: P | AP59: {=IF(OR(AN59="",AN59=0),"",IF(SUMPRODUCT(($C$55:$C$175=AN59)*(S$54:$AG$54<EOMONTH(TODAY(),-1)+1)*(ISNUMBER(S$55:$AG$175)),S$55:$AG$175)=0,"",SUMPRODUCT(($C$55:$C$175=AN59)*(S$54:$AG$54<EOMONTH(TODAY(),-1)+1)*(ISNUMBER(S$55:$AG$175)),S$55:$AG$175)))} -> 7200.0003
Q60: Real | R60: 1 | V60: =SUM(S60:U60) -> 0 | Z60: =SUM(W60:Y60) -> 0 | AD60: =SUM(AA60:AC60) -> 0 | AH60: =SUM(AE60:AG60) -> 0 | AI60: =SUM(V60,Z60,AD60,AH60) -> 0 | AJ60: Projeto concluído, tendo redução de 1MO somando este projeto com o projeto 4 (Pulmão) e projeto 19 (Facão). Projeto de kaizen 03 de 2026 | AN60: =C59 -> 03 - Otimização de processo - Cavalo Marinho | AO60: R | AP60: {=IF(OR(AN60="",AN60=0),"",IF(SUMPRODUCT(($C$55:$C$175=AN60)*($S$54:AG$54<=TODAY())*(ISNUMBER($S$56:AG$176)),$S$56:AG$176)=0,"",SUMPRODUCT(($C$55:$C$175=AN60)*($S$54:AG$54<=TODAY())*(ISNUMBER($S$56:AG$176)),$S$56:AG$176)))}
A61: Kaizen | B61: GGF | C61: 04 - Otimização de processo - Pulmão | D61: \\192.168.0.20\DEPARTAMENTOS\Engenharia\0. Kaizen Diadema\5. 2025\11 Novembro - 5\52 - Kaizen Pulmão.pptx | E61: Atualmente usa-se 20 MO. A proposta é usar 18MO. | F61: J. Oliveira | G61: 46023 | H61: 46054 | I61: 42000 | J61: 46082 | K61: =IF(J61="", "", 12 - MONTH(J61) + 1) -> 10 | O61: ✓ Concluído | P61: 1 | Q61: Previsto | R61: 1 | S61: =IFERROR(IF(AND(S$54>=EOMONTH($J61,-1)+1,S$54<=EOMONTH(EOMONTH($J61,-1)+1,$K61-1)),IF(NOT(ISBLANK($N61)),$N61/$K61,$I61/$K61),0),0) -> 0 | T61: =IFERROR(IF(AND(T$54>=EOMONTH($J61,-1)+1,T$54<=EOMONTH(EOMONTH($J61,-1)+1,$K61-1)),IF(NOT(ISBLANK($N61)),$N61/$K61,$I61/$K61),0),0) -> 0 | U61: =IFERROR(IF(AND(U$54>=EOMONTH($J61,-1)+1,U$54<=EOMONTH(EOMONTH($J61,-1)+1,$K61-1)),IF(NOT(ISBLANK($N61)),$N61/$K61,$I61/$K61),0),0) -> 4200 | V61: =SUM(S61:U61) -> 4200 | W61: =IFERROR(IF(AND(W$54>=EOMONTH($J61,-1)+1,W$54<=EOMONTH(EOMONTH($J61,-1)+1,$K61-1)),IF(NOT(ISBLANK($N61)),$N61/$K61,$I61/$K61),0),0) -> 4200 | X61: =IFERROR(IF(AND(X$54>=EOMONTH($J61,-1)+1,X$54<=EOMONTH(EOMONTH($J61,-1)+1,$K61-1)),IF(NOT(ISBLANK($N61)),$N61/$K61,$I61/$K61),0),0) -> 4200 | Y61: =IFERROR(IF(AND(Y$54>=EOMONTH($J61,-1)+1,Y$54<=EOMONTH(EOMONTH($J61,-1)+1,$K61-1)),IF(NOT(ISBLANK($N61)),$N61/$K61,$I61/$K61),0),0) -> 4200 | Z61: =SUM(W61:Y61) -> 12600 | AA61: =IFERROR(IF(AND(AA$54>=EOMONTH($J61,-1)+1,AA$54<=EOMONTH(EOMONTH($J61,-1)+1,$K61-1)),IF(NOT(ISBLANK($N61)),$N61/$K61,$I61/$K61),0),0) -> 4200 | AB61: =IFERROR(IF(AND(AB$54>=EOMONTH($J61,-1)+1,AB$54<=EOMONTH(EOMONTH($J61,-1)+1,$K61-1)),IF(NOT(ISBLANK($N61)),$N61/$K61,$I61/$K61),0),0) -> 4200 | AC61: =IFERROR(IF(AND(AC$54>=EOMONTH($J61,-1)+1,AC$54<=EOMONTH(EOMONTH($J61,-1)+1,$K61-1)),IF(NOT(ISBLANK($N61)),$N61/$K61,$I61/$K61),0),0) -> 4200 | AD61: =SUM(AA61:AC61) -> 12600 | AE61: =IFERROR(IF(AND(AE$54>=EOMONTH($J61,-1)+1,AE$54<=EOMONTH(EOMONTH($J61,-1)+1,$K61-1)),IF(NOT(ISBLANK($N61)),$N61/$K61,$I61/$K61),0),0) -> 4200 | AF61: =IFERROR(IF(AND(AF$54>=EOMONTH($J61,-1)+1,AF$54<=EOMONTH(EOMONTH($J61,-1)+1,$K61-1)),IF(NOT(ISBLANK($N61)),$N61/$K61,$I61/$K61),0),0) -> 4200 | AG61: =IFERROR(IF(AND(AG$54>=EOMONTH($J61,-1)+1,AG$54<=EOMONTH(EOMONTH($J61,-1)+1,$K61-1)),IF(NOT(ISBLANK($N61)),$N61/$K61,$I61/$K61),0),0) -> 4200 | AH61: =SUM(AE61:AG61) -> 12600 | AI61: =SUM(V61,Z61,AD61,AH61) -> 42000 | AJ61: 6k pçs/mês, 4 corridas mensais, 206pçs/hora. 6000/206 = 29,12h x 20MO = 582,5h. 29,12h x 18MO = 524h. Logo, save de 58,34h / 166 = 0,35MO | AM61: =N61*AL61 -> 0 | AN61: =C61 -> 04 - Otimização de processo - Pulmão | AO61: P | AP61: {=IF(OR(AN61="",AN61=0),"",IF(SUMPRODUCT(($C$55:$C$175=AN61)*(S$54:$AG$54<EOMONTH(TODAY(),-1)+1)*(ISNUMBER(S$55:$AG$175)),S$55:$AG$175)=0,"",SUMPRODUCT(($C$55:$C$175=AN61)*(S$54:$AG$54<EOMONTH(TODAY(),-1)+1)*(ISNUMBER(S$55:$AG$175)),S$55:$AG$175)))} -> 12600
Q62: Real | R62: 1 | V62: =SUM(S62:U62) -> 0 | Z62: =SUM(W62:Y62) -> 0 | AD62: =SUM(AA62:AC62) -> 0 | AH62: =SUM(AE62:AG62) -> 0 | AI62: =SUM(V62,Z62,AD62,AH62) -> 0 | AJ62: Projeto concluído, tendo redução de 1MO somando este projeto com o projeto 3 (Cavalo Marinho) e projeto 19 (Facão). Projeto de kaizen 52 de 2025 | AN62: =C61 -> 04 - Otimização de processo - Pulmão | AO62: R | AP62: {=IF(OR(AN62="",AN62=0),"",IF(SUMPRODUCT(($C$55:$C$175=AN62)*($S$54:AG$54<=TODAY())*(ISNUMBER($S$56:AG$176)),$S$56:AG$176)=0,"",SUMPRODUCT(($C$55:$C$175=AN62)*($S$54:AG$54<=TODAY())*(ISNUMBER($S$56:AG$176)),$S$56:AG$176)))}
A63: Redução de custo | B63: GGF | C63: 05 - Empilhadeira - Diadema | D63: \\192.168.0.20\DEPARTAMENTOS\\Engenharia\0. Kaizen Diadema\6. 2026\02 Fevereiro\17 - Redução do contrato de empilhadeiras_Eduardo Fajardo\17 - Redução de do contrato de empilhadeiras_Eduardo Fajardo.xlsx | E63: Redução de 1 empilhadeira. Eram 8 em operação, e serão 7 | F63: E. Fajardo | G63: 46027 | H63: 46078 | I63: 68000 | J63: 46082 | K63: =IF(J63="", "", 12 - MONTH(J63) + 1) -> 10 | M63: OK | N63: 56610.76 | O63: ✓ Concluído | P63: 1 | Q63: Previsto | R63: 1 | S63: =IFERROR(IF(AND(S$54>=EOMONTH($J63,-1)+1,S$54<=EOMONTH(EOMONTH($J63,-1)+1,$K63-1)),IF(NOT(ISBLANK($N63)),$N63/$K63,$I63/$K63),0),0) -> 0 | T63: =IFERROR(IF(AND(T$54>=EOMONTH($J63,-1)+1,T$54<=EOMONTH(EOMONTH($J63,-1)+1,$K63-1)),IF(NOT(ISBLANK($N63)),$N63/$K63,$I63/$K63),0),0) -> 0 | U63: =IFERROR(IF(AND(U$54>=EOMONTH($J63,-1)+1,U$54<=EOMONTH(EOMONTH($J63,-1)+1,$K63-1)),IF(NOT(ISBLANK($N63)),$N63/$K63,$I63/$K63),0),0) -> 5661.076 | V63: =SUM(S63:U63) -> 5661.076 | W63: =IFERROR(IF(AND(W$54>=EOMONTH($J63,-1)+1,W$54<=EOMONTH(EOMONTH($J63,-1)+1,$K63-1)),IF(NOT(ISBLANK($N63)),$N63/$K63,$I63/$K63),0),0) -> 5661.076 | X63: =IFERROR(IF(AND(X$54>=EOMONTH($J63,-1)+1,X$54<=EOMONTH(EOMONTH($J63,-1)+1,$K63-1)),IF(NOT(ISBLANK($N63)),$N63/$K63,$I63/$K63),0),0) -> 5661.076 | Y63: =IFERROR(IF(AND(Y$54>=EOMONTH($J63,-1)+1,Y$54<=EOMONTH(EOMONTH($J63,-1)+1,$K63-1)),IF(NOT(ISBLANK($N63)),$N63/$K63,$I63/$K63),0),0) -> 5661.076 | Z63: =SUM(W63:Y63) -> 16983.228 | AA63: =IFERROR(IF(AND(AA$54>=EOMONTH($J63,-1)+1,AA$54<=EOMONTH(EOMONTH($J63,-1)+1,$K63-1)),IF(NOT(ISBLANK($N63)),$N63/$K63,$I63/$K63),0),0) -> 5661.076 | AB63: =IFERROR(IF(AND(AB$54>=EOMONTH($J63,-1)+1,AB$54<=EOMONTH(EOMONTH($J63,-1)+1,$K63-1)),IF(NOT(ISBLANK($N63)),$N63/$K63,$I63/$K63),0),0) -> 5661.076 | AC63: =IFERROR(IF(AND(AC$54>=EOMONTH($J63,-1)+1,AC$54<=EOMONTH(EOMONTH($J63,-1)+1,$K63-1)),IF(NOT(ISBLANK($N63)),$N63/$K63,$I63/$K63),0),0) -> 5661.076 | AD63: =SUM(AA63:AC63) -> 16983.228 | AE63: =IFERROR(IF(AND(AE$54>=EOMONTH($J63,-1)+1,AE$54<=EOMONTH(EOMONTH($J63,-1)+1,$K63-1)),IF(NOT(ISBLANK($N63)),$N63/$K63,$I63/$K63),0),0) -> 5661.076 | AF63: =IFERROR(IF(AND(AF$54>=EOMONTH($J63,-1)+1,AF$54<=EOMONTH(EOMONTH($J63,-1)+1,$K63-1)),IF(NOT(ISBLANK($N63)),$N63/$K63,$I63/$K63),0),0) -> 5661.076 | AG63: =IFERROR(IF(AND(AG$54>=EOMONTH($J63,-1)+1,AG$54<=EOMONTH(EOMONTH($J63,-1)+1,$K63-1)),IF(NOT(ISBLANK($N63)),$N63/$K63,$I63/$K63),0),0) -> 5661.076 | AH63: =SUM(AE63:AG63) -> 16983.228 | AI63: =SUM(V63,Z63,AD63,AH63) -> 56610.76 | AJ63: 13/02/2026: Projeto de kaizen número 17 de 2026. E empilhaderia já foi devolvida. | AM63: =N63*AL63 -> 0 | AN63: =C63 -> 05 - Empilhadeira - Diadema | AO63: P | AP63: {=IF(OR(AN63="",AN63=0),"",IF(SUMPRODUCT(($C$55:$C$175=AN63)*(S$54:$AG$54<EOMONTH(TODAY(),-1)+1)*(ISNUMBER(S$55:$AG$175)),S$55:$AG$175)=0,"",SUMPRODUCT(($C$55:$C$175=AN63)*(S$54:$AG$54<EOMONTH(TODAY(),-1)+1)*(ISNUMBER(S$55:$AG$175)),S$55:$AG$175)))} -> 16983.228
Q64: Real | R64: 1 | T64: 0 | U64: 5146.4325 | V64: =SUM(S64:U64) -> 5146.4325 | W64: 5146.4325 | X64: 5146.4325 | Z64: =SUM(W64:Y64) -> 10292.865 | AD64: =SUM(AA64:AC64) -> 0 | AH64: =SUM(AE64:AG64) -> 0 | AI64: =SUM(V64,Z64,AD64,AH64) -> 15439.298 | AJ64: 13/02/2026: Falta validação do time de Controladoria -> Considerados valores líquidos para o resultado -> Resultado de Fevereiro ainda contemplou o valor de 8 empilhadeiras. | AN64: =C63 -> 05 - Empilhadeira - Diadema | AO64: R | AP64: {=IF(OR(AN64="",AN64=0),"",IF(SUMPRODUCT(($C$55:$C$175=AN64)*($S$54:AG$54<=TODAY())*(ISNUMBER($S$56:AG$176)),$S$56:AG$176)=0,"",SUMPRODUCT(($C$55:$C$175=AN64)*($S$54:AG$54<=TODAY())*(ISNUMBER($S$56:AG$176)),$S$56:AG$176)))} -> 15439.298
A65: Redução de custo | B65: GGF | C65: 06 - Produtividade | D65: \\192.168.0.20\DEPARTAMENTOS\Engenharia\0. Kaizen Diadema\6. 2026\02 Fevereiro\18 - Produtividade_Aumento da eficiência para 73%_Rua 2-3-4-8_Eduardo Fajardo\18 - Produtividade_Aumento da eficiência para 73%_Rua 2-3-4-8.xlsx | E65: Aumento da eficiência da rua 2, 3 e 4 \para 73,4%. | F65: E. Fajardo | G65: 46070 | H65: 46142 | I65: 288000 | J65: 46143 | K65: =IF(J65="", "", 12 - MONTH(J65) + 1) -> 8 | M65: OK | N65: 79673.52 | O65: ✓ Concluído | P65: 1 | Q65: Previsto | R65: 0.96 | S65: =IFERROR(IF(AND(S$54>=EOMONTH($J65,-1)+1,S$54<=EOMONTH(EOMONTH($J65,-1)+1,$K65-1)),IF(NOT(ISBLANK($N65)),$N65/$K65,$I65/$K65),0),0) -> 0 | T65: =IFERROR(IF(AND(T$54>=EOMONTH($J65,-1)+1,T$54<=EOMONTH(EOMONTH($J65,-1)+1,$K65-1)),IF(NOT(ISBLANK($N65)),$N65/$K65,$I65/$K65),0),0) -> 0 | U65: =IFERROR(IF(AND(U$54>=EOMONTH($J65,-1)+1,U$54<=EOMONTH(EOMONTH($J65,-1)+1,$K65-1)),IF(NOT(ISBLANK($N65)),$N65/$K65,$I65/$K65),0),0) -> 0 | V65: =SUM(S65:U65) -> 0 | W65: =IFERROR(IF(AND(W$54>=EOMONTH($J65,-1)+1,W$54<=EOMONTH(EOMONTH($J65,-1)+1,$K65-1)),IF(NOT(ISBLANK($N65)),$N65/$K65,$I65/$K65),0),0) -> 0 | X65: =IFERROR(IF(AND(X$54>=EOMONTH($J65,-1)+1,X$54<=EOMONTH(EOMONTH($J65,-1)+1,$K65-1)),IF(NOT(ISBLANK($N65)),$N65/$K65,$I65/$K65),0),0) -> 9959.19 | Y65: =IFERROR(IF(AND(Y$54>=EOMONTH($J65,-1)+1,Y$54<=EOMONTH(EOMONTH($J65,-1)+1,$K65-1)),IF(NOT(ISBLANK($N65)),$N65/$K65,$I65/$K65),0),0) -> 9959.19 | Z65: =SUM(W65:Y65) -> 19918.38 | AA65: =IFERROR(IF(AND(AA$54>=EOMONTH($J65,-1)+1,AA$54<=EOMONTH(EOMONTH($J65,-1)+1,$K65-1)),IF(NOT(ISBLANK($N65)),$N65/$K65,$I65/$K65),0),0) -> 9959.19 | AB65: =IFERROR(IF(AND(AB$54>=EOMONTH($J65,-1)+1,AB$54<=EOMONTH(EOMONTH($J65,-1)+1,$K65-1)),IF(NOT(ISBLANK($N65)),$N65/$K65,$I65/$K65),0),0) -> 9959.19 | AC65: =IFERROR(IF(AND(AC$54>=EOMONTH($J65,-1)+1,AC$54<=EOMONTH(EOMONTH($J65,-1)+1,$K65-1)),IF(NOT(ISBLANK($N65)),$N65/$K65,$I65/$K65),0),0) -> 9959.19 | AD65: =SUM(AA65:AC65) -> 29877.57 | AE65: =IFERROR(IF(AND(AE$54>=EOMONTH($J65,-1)+1,AE$54<=EOMONTH(EOMONTH($J65,-1)+1,$K65-1)),IF(NOT(ISBLANK($N65)),$N65/$K65,$I65/$K65),0),0) -> 9959.19 | AF65: =IFERROR(IF(AND(AF$54>=EOMONTH($J65,-1)+1,AF$54<=EOMONTH(EOMONTH($J65,-1)+1,$K65-1)),IF(NOT(ISBLANK($N65)),$N65/$K65,$I65/$K65),0),0) -> 9959.19 | AG65: =IFERROR(IF(AND(AG$54>=EOMONTH($J65,-1)+1,AG$54<=EOMONTH(EOMONTH($J65,-1)+1,$K65-1)),IF(NOT(ISBLANK($N65)),$N65/$K65,$I65/$K65),0),0) -> 9959.19 | AH65: =SUM(AE65:AG65) -> 29877.57 | AI65: =SUM(V65,Z65,AD65,AH65) -> 79673.52 | AJ65: 16/02/206: Projeto de kaizen número 18 de 2026. Enviado para validação da controladoria em 02/03/2026. | AM65: =N65*AL65 -> 0 | AN65: =C65 -> 06 - Produtividade | AO65: P | AP65: {=IF(OR(AN65="",AN65=0),"",IF(SUMPRODUCT(($C$55:$C$175=AN65)*(S$54:$AG$54<EOMONTH(TODAY(),-1)+1)*(ISNUMBER(S$55:$AG$175)),S$55:$AG$175)=0,"",SUMPRODUCT(($C$55:$C$175=AN65)*(S$54:$AG$54<EOMONTH(TODAY(),-1)+1)*(ISNUMBER(S$55:$AG$175)),S$55:$AG$175)))} -> 9959.19
Q66: Real | R66: 0.98 | V66: =SUM(S66:U66) -> 0 | X66: -31423.7 | Z66: =SUM(W66:Y66) -> -31423.7 | AD66: =SUM(AA66:AC66) -> 0 | AH66: =SUM(AE66:AG66) -> 0 | AI66: =SUM(V66,Z66,AD66,AH66) -> -31423.7 | AN66: =C65 -> 06 - Produtividade | AO66: R | AP66: {=IF(OR(AN66="",AN66=0),"",IF(SUMPRODUCT(($C$55:$C$175=AN66)*($S$54:AG$54<=TODAY())*(ISNUMBER($S$56:AG$176)),$S$56:AG$176)=0,"",SUMPRODUCT(($C$55:$C$175=AN66)*($S$54:AG$54<=TODAY())*(ISNUMBER($S$56:AG$176)),$S$56:AG$176)))} -> -31423.7
A67: Redução de custo | B67: GGF | C67: 07 - Consumo de água | D67: \\192.168.0.20\DEPARTAMENTOS\Engenharia\0. Kaizen Diadema\6. 2026\03 Março\42 - Redução do Consumo de Água_Eduardo Fajardo\42 - Redução do Consumo de Água_Eduardo Fajardo_REV00.xlsx | E67: Instalar válvula corta ar, redução de vazão e pressão nas torneira, caça vazamentos e instalação de hidromêtro na torre Alpina. | F67: E. Fajardo | G67: 46037 | H67: 46127 | I67: 16500 | K67: =IF(J67="", "", 12 - MONTH(J67) + 1) | O67: ⏳ Em Execução | P67: 1 | Q67: Previsto | R67: 1 | S67: =IFERROR(IF(AND(S$54>=EOMONTH($J67,-1)+1,S$54<=EOMONTH(EOMONTH($J67,-1)+1,$K67-1)),IF(NOT(ISBLANK($N67)),$N67/$K67,$I67/$K67),0),0) -> 0 | T67: =IFERROR(IF(AND(T$54>=EOMONTH($J67,-1)+1,T$54<=EOMONTH(EOMONTH($J67,-1)+1,$K67-1)),IF(NOT(ISBLANK($N67)),$N67/$K67,$I67/$K67),0),0) -> 0 | U67: =IFERROR(IF(AND(U$54>=EOMONTH($J67,-1)+1,U$54<=EOMONTH(EOMONTH($J67,-1)+1,$K67-1)),IF(NOT(ISBLANK($N67)),$N67/$K67,$I67/$K67),0),0) -> 0 | V67: =SUM(S67:U67) -> 0 | W67: =IFERROR(IF(AND(W$54>=EOMONTH($J67,-1)+1,W$54<=EOMONTH(EOMONTH($J67,-1)+1,$K67-1)),IF(NOT(ISBLANK($N67)),$N67/$K67,$I67/$K67),0),0) -> 0 | X67: =IFERROR(IF(AND(X$54>=EOMONTH($J67,-1)+1,X$54<=EOMONTH(EOMONTH($J67,-1)+1,$K67-1)),IF(NOT(ISBLANK($N67)),$N67/$K67,$I67/$K67),0),0) -> 0 | Y67: =IFERROR(IF(AND(Y$54>=EOMONTH($J67,-1)+1,Y$54<=EOMONTH(EOMONTH($J67,-1)+1,$K67-1)),IF(NOT(ISBLANK($N67)),$N67/$K67,$I67/$K67),0),0) -> 0 | Z67: =SUM(W67:Y67) -> 0 | AA67: =IFERROR(IF(AND(AA$54>=EOMONTH($J67,-1)+1,AA$54<=EOMONTH(EOMONTH($J67,-1)+1,$K67-1)),IF(NOT(ISBLANK($N67)),$N67/$K67,$I67/$K67),0),0) -> 0 | AB67: =IFERROR(IF(AND(AB$54>=EOMONTH($J67,-1)+1,AB$54<=EOMONTH(EOMONTH($J67,-1)+1,$K67-1)),IF(NOT(ISBLANK($N67)),$N67/$K67,$I67/$K67),0),0) -> 0 | AC67: =IFERROR(IF(AND(AC$54>=EOMONTH($J67,-1)+1,AC$54<=EOMONTH(EOMONTH($J67,-1)+1,$K67-1)),IF(NOT(ISBLANK($N67)),$N67/$K67,$I67/$K67),0),0) -> 0 | AD67: =SUM(AA67:AC67) -> 0 | AE67: =IFERROR(IF(AND(AE$54>=EOMONTH($J67,-1)+1,AE$54<=EOMONTH(EOMONTH($J67,-1)+1,$K67-1)),IF(NOT(ISBLANK($N67)),$N67/$K67,$I67/$K67),0),0) -> 0 | AF67: =IFERROR(IF(AND(AF$54>=EOMONTH($J67,-1)+1,AF$54<=EOMONTH(EOMONTH($J67,-1)+1,$K67-1)),IF(NOT(ISBLANK($N67)),$N67/$K67,$I67/$K67),0),0) -> 0 | AG67: =IFERROR(IF(AND(AG$54>=EOMONTH($J67,-1)+1,AG$54<=EOMONTH(EOMONTH($J67,-1)+1,$K67-1)),IF(NOT(ISBLANK($N67)),$N67/$K67,$I67/$K67),0),0) -> 0 | AH67: =SUM(AE67:AG67) -> 0 | AI67: =SUM(V67,Z67,AD67,AH67) -> 0 | AJ67: O baseline 570l para cada 1.000 peças vendidas. Kaizen número 42 de 2026. Enviado para validação da controladoria em 02/04/2026 | AM67: =N67*AL67 -> 0 | AN67: =C67 -> 07 - Consumo de água | AO67: P | AP67: {=IF(OR(AN67="",AN67=0),"",IF(SUMPRODUCT(($C$55:$C$175=AN67)*(S$54:$AG$54<EOMONTH(TODAY(),-1)+1)*(ISNUMBER(S$55:$AG$175)),S$55:$AG$175)=0,"",SUMPRODUCT(($C$55:$C$175=AN67)*(S$54:$AG$54<EOMONTH(TODAY(),-1)+1)*(ISNUMBER(S$55:$AG$175)),S$55:$AG$175)))}
Q68: Real | R68: 0.95 | V68: =SUM(S68:U68) -> 0 | Z68: =SUM(W68:Y68) -> 0 | AD68: =SUM(AA68:AC68) -> 0 | AH68: =SUM(AE68:AG68) -> 0 | AI68: =SUM(V68,Z68,AD68,AH68) -> 0 | AN68: =C67 -> 07 - Consumo de água | AO68: R | AP68: {=IF(OR(AN68="",AN68=0),"",IF(SUMPRODUCT(($C$55:$C$175=AN68)*($S$54:AG$54<=TODAY())*(ISNUMBER($S$56:AG$176)),$S$56:AG$176)=0,"",SUMPRODUCT(($C$55:$C$175=AN68)*($S$54:AG$54<=TODAY())*(ISNUMBER($S$56:AG$176)),$S$56:AG$176)))}
A69: BSW | B69: VA | C69: 08 - Redução de peso bruto MB002446LA / MB003670LA / MB003671LA | D69: \\192.168.0.20\DEPARTAMENTOS\\Engenharia\0. Kaizen Diadema\6. 2026\01 Janeiro\02 - MB2446LA_MB3670LA_MB3671LA_Engenharia_Bruno Manachini_Validado Pela Controladoria\02 - KAIZEN - MB2446LA_MB3670LA_MB3671LA_Rev00_Bruno Manachini.xlsx | E69: Reduzir a largura da chapa de 1150mm para 1000, resultando em maior aproveitamento. | F69: B. Manachini | G69: 46036 | H69: 46142 | I69: 44400 | J69: 46143 | K69: =IF(J69="", "", 12 - MONTH(J69) + 1) -> 8 | M69: OK | N69: 13137.64 | O69: ⏳ Em Execução | P69: 0.5 | Q69: Previsto | R69: 0.97 | S69: =IFERROR(IF(AND(S$54>=EOMONTH($J69,-1)+1,S$54<=EOMONTH(EOMONTH($J69,-1)+1,$K69-1)),IF(NOT(ISBLANK($N69)),$N69/$K69,$I69/$K69),0),0) -> 0 | T69: =IFERROR(IF(AND(T$54>=EOMONTH($J69,-1)+1,T$54<=EOMONTH(EOMONTH($J69,-1)+1,$K69-1)),IF(NOT(ISBLANK($N69)),$N69/$K69,$I69/$K69),0),0) -> 0 | U69: =IFERROR(IF(AND(U$54>=EOMONTH($J69,-1)+1,U$54<=EOMONTH(EOMONTH($J69,-1)+1,$K69-1)),IF(NOT(ISBLANK($N69)),$N69/$K69,$I69/$K69),0),0) -> 0 | V69: =SUM(S69:U69) -> 0 | W69: =IFERROR(IF(AND(W$54>=EOMONTH($J69,-1)+1,W$54<=EOMONTH(EOMONTH($J69,-1)+1,$K69-1)),IF(NOT(ISBLANK($N69)),$N69/$K69,$I69/$K69),0),0) -> 0 | X69: =IFERROR(IF(AND(X$54>=EOMONTH($J69,-1)+1,X$54<=EOMONTH(EOMONTH($J69,-1)+1,$K69-1)),IF(NOT(ISBLANK($N69)),$N69/$K69,$I69/$K69),0),0) -> 1642.205 | Y69: =IFERROR(IF(AND(Y$54>=EOMONTH($J69,-1)+1,Y$54<=EOMONTH(EOMONTH($J69,-1)+1,$K69-1)),IF(NOT(ISBLANK($N69)),$N69/$K69,$I69/$K69),0),0) -> 1642.205 | Z69: =SUM(W69:Y69) -> 3284.41 | AA69: =IFERROR(IF(AND(AA$54>=EOMONTH($J69,-1)+1,AA$54<=EOMONTH(EOMONTH($J69,-1)+1,$K69-1)),IF(NOT(ISBLANK($N69)),$N69/$K69,$I69/$K69),0),0) -> 1642.205 | AB69: =IFERROR(IF(AND(AB$54>=EOMONTH($J69,-1)+1,AB$54<=EOMONTH(EOMONTH($J69,-1)+1,$K69-1)),IF(NOT(ISBLANK($N69)),$N69/$K69,$I69/$K69),0),0) -> 1642.205 | AC69: =IFERROR(IF(AND(AC$54>=EOMONTH($J69,-1)+1,AC$54<=EOMONTH(EOMONTH($J69,-1)+1,$K69-1)),IF(NOT(ISBLANK($N69)),$N69/$K69,$I69/$K69),0),0) -> 1642.205 | AD69: =SUM(AA69:AC69) -> 4926.615 | AE69: =IFERROR(IF(AND(AE$54>=EOMONTH($J69,-1)+1,AE$54<=EOMONTH(EOMONTH($J69,-1)+1,$K69-1)),IF(NOT(ISBLANK($N69)),$N69/$K69,$I69/$K69),0),0) -> 1642.205 | AF69: =IFERROR(IF(AND(AF$54>=EOMONTH($J69,-1)+1,AF$54<=EOMONTH(EOMONTH($J69,-1)+1,$K69-1)),IF(NOT(ISBLANK($N69)),$N69/$K69,$I69/$K69),0),0) -> 1642.205 | AG69: =IFERROR(IF(AND(AG$54>=EOMONTH($J69,-1)+1,AG$54<=EOMONTH(EOMONTH($J69,-1)+1,$K69-1)),IF(NOT(ISBLANK($N69)),$N69/$K69,$I69/$K69),0),0) -> 1642.205 | AH69: =SUM(AE69:AG69) -> 4926.615 | AI69: =SUM(V69,Z69,AD69,AH69) -> 13137.64 | AJ69: 05/02/2026: Com base no volume médio, e redução de peso bruto para cada PN, estima-se redução de 674kg/mês. Ao preço de R$5,5/kg, a redução especulada é de R$3700/mês | AM69: =N69*AL69 -> 0 | AN69: =C69 -> 08 - Redução de peso bruto MB002446LA / MB003670LA / MB003671LA | AO69: P | AP69: {=IF(OR(AN69="",AN69=0),"",IF(SUMPRODUCT(($C$55:$C$175=AN69)*(S$54:$AG$54<EOMONTH(TODAY(),-1)+1)*(ISNUMBER(S$55:$AG$175)),S$55:$AG$175)=0,"",SUMPRODUCT(($C$55:$C$175=AN69)*(S$54:$AG$54<EOMONTH(TODAY(),-1)+1)*(ISNUMBER(S$55:$AG$175)),S$55:$AG$175)))} -> 1642.205
Q70: Real | R70: 0.8 | V70: =SUM(S70:U70) -> 0 | X70: 3901.66 | Z70: =SUM(W70:Y70) -> 3901.66 | AD70: =SUM(AA70:AC70) -> 0 | AH70: =SUM(AE70:AG70) -> 0 | AI70: =SUM(V70,Z70,AD70,AH70) -> 3901.66 | AJ70: Projeto de kaizen número 02 de 2026 - CUSTOS >> Validação em andamento, LT incorreta.. Não se compra Bobina desde 08/2025 e o preço calculado em Budget é menor do que o efetuado por Compras em Dez/26, gerando um penalti no Kaizen (será agendado um alinhamento entre as areas para definição das premissas, nesses casos) | AN70: =C69 -> 08 - Redução de peso bruto MB002446LA / MB003670LA / MB003671LA | AO70: R | AP70: {=IF(OR(AN70="",AN70=0),"",IF(SUMPRODUCT(($C$55:$C$175=AN70)*($S$54:AG$54<=TODAY())*(ISNUMBER($S$56:AG$176)),$S$56:AG$176)=0,"",SUMPRODUCT(($C$55:$C$175=AN70)*($S$54:AG$54<=TODAY())*(ISNUMBER($S$56:AG$176)),$S$56:AG$176)))} -> 3901.66
A71: Redução de custo | B71: GGF | C71: 09 - Taxa de Esgoto | D71: \\192.168.0.20\departamentos\Engenharia\0. Kaizen Diadema\6. 2026\04 Abril\51 - Taxa de Esgoto_Eduardo Fajardo)REV00\51_Taxa de Esgoto_Eduardo Fajardo_Rev00.xlsx | E71: Redução do pagamento da conta de água/esgoto gerado na planta devido a evaporação dos processos | F71: E. Fajardo | G71: 46082 | H71: 46203 | I71: =1513*6 -> 9078 | K71: =IF(J71="", "", 12 - MONTH(J71) + 1) | O71: ⏳ Em Execução | P71: 1 | Q71: Previsto | R71: 0.48 | S71: =IFERROR(IF(AND(S$54>=EOMONTH($J71,-1)+1,S$54<=EOMONTH(EOMONTH($J71,-1)+1,$K71-1)),IF(NOT(ISBLANK($N71)),$N71/$K71,$I71/$K71),0),0) -> 0 | T71: =IFERROR(IF(AND(T$54>=EOMONTH($J71,-1)+1,T$54<=EOMONTH(EOMONTH($J71,-1)+1,$K71-1)),IF(NOT(ISBLANK($N71)),$N71/$K71,$I71/$K71),0),0) -> 0 | U71: =IFERROR(IF(AND(U$54>=EOMONTH($J71,-1)+1,U$54<=EOMONTH(EOMONTH($J71,-1)+1,$K71-1)),IF(NOT(ISBLANK($N71)),$N71/$K71,$I71/$K71),0),0) -> 0 | V71: =SUM(S71:U71) -> 0 | W71: =IFERROR(IF(AND(W$54>=EOMONTH($J71,-1)+1,W$54<=EOMONTH(EOMONTH($J71,-1)+1,$K71-1)),IF(NOT(ISBLANK($N71)),$N71/$K71,$I71/$K71),0),0) -> 0 | X71: =IFERROR(IF(AND(X$54>=EOMONTH($J71,-1)+1,X$54<=EOMONTH(EOMONTH($J71,-1)+1,$K71-1)),IF(NOT(ISBLANK($N71)),$N71/$K71,$I71/$K71),0),0) -> 0 | Y71: =IFERROR(IF(AND(Y$54>=EOMONTH($J71,-1)+1,Y$54<=EOMONTH(EOMONTH($J71,-1)+1,$K71-1)),IF(NOT(ISBLANK($N71)),$N71/$K71,$I71/$K71),0),0) -> 0 | Z71: =SUM(W71:Y71) -> 0 | AA71: =IFERROR(IF(AND(AA$54>=EOMONTH($J71,-1)+1,AA$54<=EOMONTH(EOMONTH($J71,-1)+1,$K71-1)),IF(NOT(ISBLANK($N71)),$N71/$K71,$I71/$K71),0),0) -> 0 | AB71: =IFERROR(IF(AND(AB$54>=EOMONTH($J71,-1)+1,AB$54<=EOMONTH(EOMONTH($J71,-1)+1,$K71-1)),IF(NOT(ISBLANK($N71)),$N71/$K71,$I71/$K71),0),0) -> 0 | AC71: =IFERROR(IF(AND(AC$54>=EOMONTH($J71,-1)+1,AC$54<=EOMONTH(EOMONTH($J71,-1)+1,$K71-1)),IF(NOT(ISBLANK($N71)),$N71/$K71,$I71/$K71),0),0) -> 0 | AD71: =SUM(AA71:AC71) -> 0 | AE71: =IFERROR(IF(AND(AE$54>=EOMONTH($J71,-1)+1,AE$54<=EOMONTH(EOMONTH($J71,-1)+1,$K71-1)),IF(NOT(ISBLANK($N71)),$N71/$K71,$I71/$K71),0),0) -> 0 | AF71: =IFERROR(IF(AND(AF$54>=EOMONTH($J71,-1)+1,AF$54<=EOMONTH(EOMONTH($J71,-1)+1,$K71-1)),IF(NOT(ISBLANK($N71)),$N71/$K71,$I71/$K71),0),0) -> 0 | AG71: =IFERROR(IF(AND(AG$54>=EOMONTH($J71,-1)+1,AG$54<=EOMONTH(EOMONTH($J71,-1)+1,$K71-1)),IF(NOT(ISBLANK($N71)),$N71/$K71,$I71/$K71),0),0) -> 0 | AH71: =SUM(AE71:AG71) -> 0 | AI71: =SUM(V71,Z71,AD71,AH71) -> 0 | AJ71: 29/04/2026: Projeto de kaizen númeor 51 de 2026. Enviado para validaç!ao da controladoria em 29/04/2026 | AM71: =N71*AL71 -> 0 | AN71: =C71 -> 09 - Taxa de Esgoto | AO71: P | AP71: {=IF(OR(AN71="",AN71=0),"",IF(SUMPRODUCT(($C$55:$C$175=AN71)*(S$54:$AG$54<EOMONTH(TODAY(),-1)+1)*(ISNUMBER(S$55:$AG$175)),S$55:$AG$175)=0,"",SUMPRODUCT(($C$55:$C$175=AN71)*(S$54:$AG$54<EOMONTH(TODAY(),-1)+1)*(ISNUMBER(S$55:$AG$175)),S$55:$AG$175)))}
Q72: Real | R72: 0.56 | V72: =SUM(S72:U72) -> 0 | Z72: =SUM(W72:Y72) -> 0 | AD72: =SUM(AA72:AC72) -> 0 | AH72: =SUM(AE72:AG72) -> 0 | AI72: =SUM(V72,Z72,AD72,AH72) -> 0 | AN72: =C71 -> 09 - Taxa de Esgoto | AO72: R | AP72: {=IF(OR(AN72="",AN72=0),"",IF(SUMPRODUCT(($C$55:$C$175=AN72)*($S$54:AG$54<=TODAY())*(ISNUMBER($S$56:AG$176)),$S$56:AG$176)=0,"",SUMPRODUCT(($C$55:$C$175=AN72)*($S$54:AG$54<=TODAY())*(ISNUMBER($S$56:AG$176)),$S$56:AG$176)))}
A73: Kaizen | B73: GGF | C73: 10 - Padronização de arame de solda | D73: \\192.168.0.20\DEPARTAMENTOS\\Engenharia\0. Kaizen Diadema\6. 2026\01 Janeiro\06 - Padronização de Arame de Solda_Izaias Junior_Engenharia\06_Padronização Arame de Solda. rev01_Izaias Junior.xlsx | E73: Padronizar todos os processos de solda com arame de 1,2mm | F73: I. Junior | G73: 46042 | H73: 46142 | I73: 2928 | J73: 46143 | K73: =IF(J73="", "", 12 - MONTH(J73) + 1) -> 8 | O73: ⏳ Em Execução | P73: 1 | Q73: Previsto | R73: 0.97 | S73: =IFERROR(IF(AND(S$54>=EOMONTH($J73,-1)+1,S$54<=EOMONTH(EOMONTH($J73,-1)+1,$K73-1)),IF(NOT(ISBLANK($N73)),$N73/$K73,$I73/$K73),0),0) -> 0 | T73: =IFERROR(IF(AND(T$54>=EOMONTH($J73,-1)+1,T$54<=EOMONTH(EOMONTH($J73,-1)+1,$K73-1)),IF(NOT(ISBLANK($N73)),$N73/$K73,$I73/$K73),0),0) -> 0 | U73: =IFERROR(IF(AND(U$54>=EOMONTH($J73,-1)+1,U$54<=EOMONTH(EOMONTH($J73,-1)+1,$K73-1)),IF(NOT(ISBLANK($N73)),$N73/$K73,$I73/$K73),0),0) -> 0 | V73: =SUM(S73:U73) -> 0 | W73: =IFERROR(IF(AND(W$54>=EOMONTH($J73,-1)+1,W$54<=EOMONTH(EOMONTH($J73,-1)+1,$K73-1)),IF(NOT(ISBLANK($N73)),$N73/$K73,$I73/$K73),0),0) -> 0 | X73: =IFERROR(IF(AND(X$54>=EOMONTH($J73,-1)+1,X$54<=EOMONTH(EOMONTH($J73,-1)+1,$K73-1)),IF(NOT(ISBLANK($N73)),$N73/$K73,$I73/$K73),0),0) -> 366 | Y73: =IFERROR(IF(AND(Y$54>=EOMONTH($J73,-1)+1,Y$54<=EOMONTH(EOMONTH($J73,-1)+1,$K73-1)),IF(NOT(ISBLANK($N73)),$N73/$K73,$I73/$K73),0),0) -> 366 | Z73: =SUM(W73:Y73) -> 732 | AA73: =IFERROR(IF(AND(AA$54>=EOMONTH($J73,-1)+1,AA$54<=EOMONTH(EOMONTH($J73,-1)+1,$K73-1)),IF(NOT(ISBLANK($N73)),$N73/$K73,$I73/$K73),0),0) -> 366 | AB73: =IFERROR(IF(AND(AB$54>=EOMONTH($J73,-1)+1,AB$54<=EOMONTH(EOMONTH($J73,-1)+1,$K73-1)),IF(NOT(ISBLANK($N73)),$N73/$K73,$I73/$K73),0),0) -> 366 | AC73: =IFERROR(IF(AND(AC$54>=EOMONTH($J73,-1)+1,AC$54<=EOMONTH(EOMONTH($J73,-1)+1,$K73-1)),IF(NOT(ISBLANK($N73)),$N73/$K73,$I73/$K73),0),0) -> 366 | AD73: =SUM(AA73:AC73) -> 1098 | AE73: =IFERROR(IF(AND(AE$54>=EOMONTH($J73,-1)+1,AE$54<=EOMONTH(EOMONTH($J73,-1)+1,$K73-1)),IF(NOT(ISBLANK($N73)),$N73/$K73,$I73/$K73),0),0) -> 366 | AF73: =IFERROR(IF(AND(AF$54>=EOMONTH($J73,-1)+1,AF$54<=EOMONTH(EOMONTH($J73,-1)+1,$K73-1)),IF(NOT(ISBLANK($N73)),$N73/$K73,$I73/$K73),0),0) -> 366 | AG73: =IFERROR(IF(AND(AG$54>=EOMONTH($J73,-1)+1,AG$54<=EOMONTH(EOMONTH($J73,-1)+1,$K73-1)),IF(NOT(ISBLANK($N73)),$N73/$K73,$I73/$K73),0),0) -> 366 | AH73: =SUM(AE73:AG73) -> 1098 | AI73: =SUM(V73,Z73,AD73,AH73) -> 2928 | AJ73: Projeto de kaizen número 06 de 2026 | AM73: =N73*AL73 -> 0 | AN73: =C73 -> 10 - Padronização de arame de solda | AO73: P | AP73: {=IF(OR(AN73="",AN73=0),"",IF(SUMPRODUCT(($C$55:$C$175=AN73)*(S$54:$AG$54<EOMONTH(TODAY(),-1)+1)*(ISNUMBER(S$55:$AG$175)),S$55:$AG$175)=0,"",SUMPRODUCT(($C$55:$C$175=AN73)*(S$54:$AG$54<EOMONTH(TODAY(),-1)+1)*(ISNUMBER(S$55:$AG$175)),S$55:$AG$175)))} -> 366
Q74: Real | R74: 0.95 | V74: =SUM(S74:U74) -> 0 | Z74: =SUM(W74:Y74) -> 0 | AD74: =SUM(AA74:AC74) -> 0 | AH74: =SUM(AE74:AG74) -> 0 | AI74: =SUM(V74,Z74,AD74,AH74) -> 0 | AN74: =C73 -> 10 - Padronização de arame de solda | AO74: R | AP74: {=IF(OR(AN74="",AN74=0),"",IF(SUMPRODUCT(($C$55:$C$175=AN74)*($S$54:AG$54<=TODAY())*(ISNUMBER($S$56:AG$176)),$S$56:AG$176)=0,"",SUMPRODUCT(($C$55:$C$175=AN74)*($S$54:AG$54<=TODAY())*(ISNUMBER($S$56:AG$176)),$S$56:AG$176)))}
A75: Redução de custo | B75: GGF | C75: 11 - Resourcing de DSL para DD | E75: Trazer 2 ferramentas da VW1131 | F75: E. Fajardo | G75: 46113 | H75: 46113 | I75: =3.071/2 -> 1.5355 | K75: =IF(J75="", "", 12 - MONTH(J75) + 1) | O75: 📝 Não iniciado | P75: 1 | Q75: Previsto | R75: 1 | S75: =IFERROR(IF(AND(S$54>=EOMONTH($J75,-1)+1,S$54<=EOMONTH(EOMONTH($J75,-1)+1,$K75-1)),IF(NOT(ISBLANK($N75)),$N75/$K75,$I75/$K75),0),0) -> 0 | T75: =IFERROR(IF(AND(T$54>=EOMONTH($J75,-1)+1,T$54<=EOMONTH(EOMONTH($J75,-1)+1,$K75-1)),IF(NOT(ISBLANK($N75)),$N75/$K75,$I75/$K75),0),0) -> 0 | U75: =IFERROR(IF(AND(U$54>=EOMONTH($J75,-1)+1,U$54<=EOMONTH(EOMONTH($J75,-1)+1,$K75-1)),IF(NOT(ISBLANK($N75)),$N75/$K75,$I75/$K75),0),0) -> 0 | V75: =SUM(S75:U75) -> 0 | W75: =IFERROR(IF(AND(W$54>=EOMONTH($J75,-1)+1,W$54<=EOMONTH(EOMONTH($J75,-1)+1,$K75-1)),IF(NOT(ISBLANK($N75)),$N75/$K75,$I75/$K75),0),0) -> 0 | X75: =IFERROR(IF(AND(X$54>=EOMONTH($J75,-1)+1,X$54<=EOMONTH(EOMONTH($J75,-1)+1,$K75-1)),IF(NOT(ISBLANK($N75)),$N75/$K75,$I75/$K75),0),0) -> 0 | Y75: =IFERROR(IF(AND(Y$54>=EOMONTH($J75,-1)+1,Y$54<=EOMONTH(EOMONTH($J75,-1)+1,$K75-1)),IF(NOT(ISBLANK($N75)),$N75/$K75,$I75/$K75),0),0) -> 0 | Z75: =SUM(W75:Y75) -> 0 | AA75: =IFERROR(IF(AND(AA$54>=EOMONTH($J75,-1)+1,AA$54<=EOMONTH(EOMONTH($J75,-1)+1,$K75-1)),IF(NOT(ISBLANK($N75)),$N75/$K75,$I75/$K75),0),0) -> 0 | AB75: =IFERROR(IF(AND(AB$54>=EOMONTH($J75,-1)+1,AB$54<=EOMONTH(EOMONTH($J75,-1)+1,$K75-1)),IF(NOT(ISBLANK($N75)),$N75/$K75,$I75/$K75),0),0) -> 0 | AC75: =IFERROR(IF(AND(AC$54>=EOMONTH($J75,-1)+1,AC$54<=EOMONTH(EOMONTH($J75,-1)+1,$K75-1)),IF(NOT(ISBLANK($N75)),$N75/$K75,$I75/$K75),0),0) -> 0 | AD75: =SUM(AA75:AC75) -> 0 | AE75: =IFERROR(IF(AND(AE$54>=EOMONTH($J75,-1)+1,AE$54<=EOMONTH(EOMONTH($J75,-1)+1,$K75-1)),IF(NOT(ISBLANK($N75)),$N75/$K75,$I75/$K75),0),0) -> 0 | AF75: =IFERROR(IF(AND(AF$54>=EOMONTH($J75,-1)+1,AF$54<=EOMONTH(EOMONTH($J75,-1)+1,$K75-1)),IF(NOT(ISBLANK($N75)),$N75/$K75,$I75/$K75),0),0) -> 0 | AG75: =IFERROR(IF(AND(AG$54>=EOMONTH($J75,-1)+1,AG$54<=EOMONTH(EOMONTH($J75,-1)+1,$K75-1)),IF(NOT(ISBLANK($N75)),$N75/$K75,$I75/$K75),0),0) -> 0 | AH75: =SUM(AE75:AG75) -> 0 | AI75: =SUM(V75,Z75,AD75,AH75) -> 0 | AM75: =N75*AL75 -> 0 | AN75: =C75 -> 11 - Resourcing de DSL para DD | AO75: P | AP75: {=IF(OR(AN75="",AN75=0),"",IF(SUMPRODUCT(($C$55:$C$175=AN75)*(S$54:$AG$54<EOMONTH(TODAY(),-1)+1)*(ISNUMBER(S$55:$AG$175)),S$55:$AG$175)=0,"",SUMPRODUCT(($C$55:$C$175=AN75)*(S$54:$AG$54<EOMONTH(TODAY(),-1)+1)*(ISNUMBER(S$55:$AG$175)),S$55:$AG$175)))}
Q76: Real | R76: 0 | V76: =SUM(S76:U76) -> 0 | Z76: =SUM(W76:Y76) -> 0 | AD76: =SUM(AA76:AC76) -> 0 | AH76: =SUM(AE76:AG76) -> 0 | AI76: =SUM(V76,Z76,AD76,AH76) -> 0 | AN76: =C75 -> 11 - Resourcing de DSL para DD | AO76: R | AP76: {=IF(OR(AN76="",AN76=0),"",IF(SUMPRODUCT(($C$55:$C$175=AN76)*($S$54:AG$54<=TODAY())*(ISNUMBER($S$56:AG$176)),$S$56:AG$176)=0,"",SUMPRODUCT(($C$55:$C$175=AN76)*($S$54:AG$54<=TODAY())*(ISNUMBER($S$56:AG$176)),$S$56:AG$176)))}
A77: Kaizen | B77: GGF | C77: 12 - Aproveitamento de peças Obsoletas - A9583176540 | D77: \\192.168.0.20\DEPARTAMENTOS\Engenharia\0. Kaizen Diadema\5. 2025\12 Dezembro - 5\54 - Aproveitamento_de_peças_obsoletas.xlsx | E77: Transformar o PN obsoleto no PN conrrete A9583178440, por meio de corte laser 3D | F77: R. Luz | G77: 46023 | H77: 46053 | I77: 38583 | J77: 46023 | K77: 1 | M77: OK | N77: 37746.6 | O77: ✓ Concluído | P77: 1 | Q77: Previsto | R77: 1 | S77: =IFERROR(IF(AND(S$54>=EOMONTH($J77,-1)+1,S$54<=EOMONTH(EOMONTH($J77,-1)+1,$K77-1)),IF(NOT(ISBLANK($N77)),$N77/$K77,$I77/$K77),0),0) -> 37746.6 | T77: =IFERROR(IF(AND(T$54>=EOMONTH($J77,-1)+1,T$54<=EOMONTH(EOMONTH($J77,-1)+1,$K77-1)),IF(NOT(ISBLANK($N77)),$N77/$K77,$I77/$K77),0),0) -> 0 | U77: =IFERROR(IF(AND(U$54>=EOMONTH($J77,-1)+1,U$54<=EOMONTH(EOMONTH($J77,-1)+1,$K77-1)),IF(NOT(ISBLANK($N77)),$N77/$K77,$I77/$K77),0),0) -> 0 | V77: =SUM(S77:U77) -> 37746.6 | W77: =IFERROR(IF(AND(W$54>=EOMONTH($J77,-1)+1,W$54<=EOMONTH(EOMONTH($J77,-1)+1,$K77-1)),IF(NOT(ISBLANK($N77)),$N77/$K77,$I77/$K77),0),0) -> 0 | X77: =IFERROR(IF(AND(X$54>=EOMONTH($J77,-1)+1,X$54<=EOMONTH(EOMONTH($J77,-1)+1,$K77-1)),IF(NOT(ISBLANK($N77)),$N77/$K77,$I77/$K77),0),0) -> 0 | Y77: =IFERROR(IF(AND(Y$54>=EOMONTH($J77,-1)+1,Y$54<=EOMONTH(EOMONTH($J77,-1)+1,$K77-1)),IF(NOT(ISBLANK($N77)),$N77/$K77,$I77/$K77),0),0) -> 0 | Z77: =SUM(W77:Y77) -> 0 | AA77: =IFERROR(IF(AND(AA$54>=EOMONTH($J77,-1)+1,AA$54<=EOMONTH(EOMONTH($J77,-1)+1,$K77-1)),IF(NOT(ISBLANK($N77)),$N77/$K77,$I77/$K77),0),0) -> 0 | AB77: =IFERROR(IF(AND(AB$54>=EOMONTH($J77,-1)+1,AB$54<=EOMONTH(EOMONTH($J77,-1)+1,$K77-1)),IF(NOT(ISBLANK($N77)),$N77/$K77,$I77/$K77),0),0) -> 0 | AC77: =IFERROR(IF(AND(AC$54>=EOMONTH($J77,-1)+1,AC$54<=EOMONTH(EOMONTH($J77,-1)+1,$K77-1)),IF(NOT(ISBLANK($N77)),$N77/$K77,$I77/$K77),0),0) -> 0 | AD77: =SUM(AA77:AC77) -> 0 | AE77: =IFERROR(IF(AND(AE$54>=EOMONTH($J77,-1)+1,AE$54<=EOMONTH(EOMONTH($J77,-1)+1,$K77-1)),IF(NOT(ISBLANK($N77)),$N77/$K77,$I77/$K77),0),0) -> 0 | AF77: =IFERROR(IF(AND(AF$54>=EOMONTH($J77,-1)+1,AF$54<=EOMONTH(EOMONTH($J77,-1)+1,$K77-1)),IF(NOT(ISBLANK($N77)),$N77/$K77,$I77/$K77),0),0) -> 0 | AG77: =IFERROR(IF(AND(AG$54>=EOMONTH($J77,-1)+1,AG$54<=EOMONTH(EOMONTH($J77,-1)+1,$K77-1)),IF(NOT(ISBLANK($N77)),$N77/$K77,$I77/$K77),0),0) -> 0 | AH77: =SUM(AE77:AG77) -> 0 | AI77: =SUM(V77,Z77,AD77,AH77) -> 37746.6 | AJ77: 23/01/2026: Aguardando validação da controladoria. Projeto de kaizen número 54 de 2025. | AM77: =N77*AL77 -> 0 | AN77: =C77 -> 12 - Aproveitamento de peças Obsoletas - A9583176540 | AO77: P | AP77: {=IF(OR(AN77="",AN77=0),"",IF(SUMPRODUCT(($C$55:$C$175=AN77)*(S$54:$AG$54<EOMONTH(TODAY(),-1)+1)*(ISNUMBER(S$55:$AG$175)),S$55:$AG$175)=0,"",SUMPRODUCT(($C$55:$C$175=AN77)*(S$54:$AG$54<EOMONTH(TODAY(),-1)+1)*(ISNUMBER(S$55:$AG$175)),S$55:$AG$175)))} -> 37746.6
Q78: Real | R78: 1 | S78: =N77 -> 37746.6 | T78: 0 | U78: 0 | V78: =SUM(S78:U78) -> 37746.6 | W78: 0 | Z78: =SUM(W78:Y78) -> 0 | AD78: =SUM(AA78:AC78) -> 0 | AH78: =SUM(AE78:AG78) -> 0 | AI78: =SUM(V78,Z78,AD78,AH78) -> 37746.6 | AJ78: 03/02/2026: todas as peças foram expedidas ao cliente. Todas as NF de movimentaçção foram anexadas como evidência na pasta do projeto. Fica pendente a validação da controladoria. -> Validado - o valor total foi atualizado com base no custo médio da peça no estoque em Dez/25 quando enviada ao fornecedor. | AN78: =C77 -> 12 - Aproveitamento de peças Obsoletas - A9583176540 | AO78: R | AP78: {=IF(OR(AN78="",AN78=0),"",IF(SUMPRODUCT(($C$55:$C$175=AN78)*($S$54:AG$54<=TODAY())*(ISNUMBER($S$56:AG$176)),$S$56:AG$176)=0,"",SUMPRODUCT(($C$55:$C$175=AN78)*($S$54:AG$54<=TODAY())*(ISNUMBER($S$56:AG$176)),$S$56:AG$176)))} -> 37746.6
A79: Kaizen | B79: GGF | C79: 13 - Redução de Componente - 4065 de 6 para 4 | D79: \\192.168.0.20\DEPARTAMENTOS\Engenharia\0. Kaizen Diadema\5. 2025\12 Dezembro - 5\53 - Redução de Componente - 4065 de 6 para 4.xlsx | E79: O item pedaleira da MBB atualmente contém 6 porcas, porém, o desenho solicita 4 porcas. | F79: R. Luz | G79: 46023 | H79: 46127 | I79: 1890 | J79: 46113 | K79: =IF(J79="", "", 12 - MONTH(J79) + 1) -> 9 | M79: OK | N79: 1962.46 | O79: ⏳ Em Execução | P79: 1 | Q79: Previsto | R79: 1 | S79: =IFERROR(IF(AND(S$54>=EOMONTH($J79,-1)+1,S$54<=EOMONTH(EOMONTH($J79,-1)+1,$K79-1)),IF(NOT(ISBLANK($N79)),$N79/$K79,$I79/$K79),0),0) -> 0 | T79: =IFERROR(IF(AND(T$54>=EOMONTH($J79,-1)+1,T$54<=EOMONTH(EOMONTH($J79,-1)+1,$K79-1)),IF(NOT(ISBLANK($N79)),$N79/$K79,$I79/$K79),0),0) -> 0 | U79: =IFERROR(IF(AND(U$54>=EOMONTH($J79,-1)+1,U$54<=EOMONTH(EOMONTH($J79,-1)+1,$K79-1)),IF(NOT(ISBLANK($N79)),$N79/$K79,$I79/$K79),0),0) -> 0 | V79: =SUM(S79:U79) -> 0 | W79: =IFERROR(IF(AND(W$54>=EOMONTH($J79,-1)+1,W$54<=EOMONTH(EOMONTH($J79,-1)+1,$K79-1)),IF(NOT(ISBLANK($N79)),$N79/$K79,$I79/$K79),0),0) -> 218.05111 | X79: =IFERROR(IF(AND(X$54>=EOMONTH($J79,-1)+1,X$54<=EOMONTH(EOMONTH($J79,-1)+1,$K79-1)),IF(NOT(ISBLANK($N79)),$N79/$K79,$I79/$K79),0),0) -> 218.05111 | Y79: =IFERROR(IF(AND(Y$54>=EOMONTH($J79,-1)+1,Y$54<=EOMONTH(EOMONTH($J79,-1)+1,$K79-1)),IF(NOT(ISBLANK($N79)),$N79/$K79,$I79/$K79),0),0) -> 218.05111 | Z79: =SUM(W79:Y79) -> 654.15333 | AA79: =IFERROR(IF(AND(AA$54>=EOMONTH($J79,-1)+1,AA$54<=EOMONTH(EOMONTH($J79,-1)+1,$K79-1)),IF(NOT(ISBLANK($N79)),$N79/$K79,$I79/$K79),0),0) -> 218.05111 | AB79: =IFERROR(IF(AND(AB$54>=EOMONTH($J79,-1)+1,AB$54<=EOMONTH(EOMONTH($J79,-1)+1,$K79-1)),IF(NOT(ISBLANK($N79)),$N79/$K79,$I79/$K79),0),0) -> 218.05111 | AC79: =IFERROR(IF(AND(AC$54>=EOMONTH($J79,-1)+1,AC$54<=EOMONTH(EOMONTH($J79,-1)+1,$K79-1)),IF(NOT(ISBLANK($N79)),$N79/$K79,$I79/$K79),0),0) -> 218.05111 | AD79: =SUM(AA79:AC79) -> 654.15333 | AE79: =IFERROR(IF(AND(AE$54>=EOMONTH($J79,-1)+1,AE$54<=EOMONTH(EOMONTH($J79,-1)+1,$K79-1)),IF(NOT(ISBLANK($N79)),$N79/$K79,$I79/$K79),0),0) -> 218.05111 | AF79: =IFERROR(IF(AND(AF$54>=EOMONTH($J79,-1)+1,AF$54<=EOMONTH(EOMONTH($J79,-1)+1,$K79-1)),IF(NOT(ISBLANK($N79)),$N79/$K79,$I79/$K79),0),0) -> 218.05111 | AG79: =IFERROR(IF(AND(AG$54>=EOMONTH($J79,-1)+1,AG$54<=EOMONTH(EOMONTH($J79,-1)+1,$K79-1)),IF(NOT(ISBLANK($N79)),$N79/$K79,$I79/$K79),0),0) -> 218.05111 | AH79: =SUM(AE79:AG79) -> 654.15333 | AI79: =SUM(V79,Z79,AD79,AH79) -> 1962.46 | AJ79: 23/01/2026: Aguardando validação da controladoria. Projeto de kaizen número 53 de 2025. | AM79: =N79*AL79 -> 0 | AN79: =C79 -> 13 - Redução de Componente - 4065 de 6 para 4 | AO79: P | AP79: {=IF(OR(AN79="",AN79=0),"",IF(SUMPRODUCT(($C$55:$C$175=AN79)*(S$54:$AG$54<EOMONTH(TODAY(),-1)+1)*(ISNUMBER(S$55:$AG$175)),S$55:$AG$175)=0,"",SUMPRODUCT(($C$55:$C$175=AN79)*(S$54:$AG$54<EOMONTH(TODAY(),-1)+1)*(ISNUMBER(S$55:$AG$175)),S$55:$AG$175)))} -> 436.10222
Q80: Real | R80: 0.95 | V80: =SUM(S80:U80) -> 0 | Z80: =SUM(W80:Y80) -> 0 | AD80: =SUM(AA80:AC80) -> 0 | AH80: =SUM(AE80:AG80) -> 0 | AI80: =SUM(V80,Z80,AD80,AH80) -> 0 | AN80: =C79 -> 13 - Redução de Componente - 4065 de 6 para 4 | AO80: R | AP80: {=IF(OR(AN80="",AN80=0),"",IF(SUMPRODUCT(($C$55:$C$175=AN80)*($S$54:AG$54<=TODAY())*(ISNUMBER($S$56:AG$176)),$S$56:AG$176)=0,"",SUMPRODUCT(($C$55:$C$175=AN80)*($S$54:AG$54<=TODAY())*(ISNUMBER($S$56:AG$176)),$S$56:AG$176)))}
A81: BSW | B81: VA | C81: 14 - REDUÇÃO DE MP DA000518Z (Anchieta) Código DD - VB000324Z | D81: \\192.168.0.20\DEPARTAMENTOS\\Engenharia\0. Kaizen Diadema\6. 2026\01 Janeiro\04 - DA000518Z_Thiago Cardoso_Engenharia\4 - KAIZEN DA000518Z.xlsx | E81: Aumentar a largura da bobina de 1100 para 1250, eliminando sobra (retalho). | F81: T. Cardodo | G81: 46023 | H81: 46054 | I81: 39996 | J81: 46054 | K81: =IF(J81="", "", 12 - MONTH(J81) + 1) -> 11 | M81: OK | N81: 46996.932 | O81: ✓ Concluído | P81: 1 | Q81: Previsto | R81: 1 | S81: =IFERROR(IF(AND(S$54>=EOMONTH($J81,-1)+1,S$54<=EOMONTH(EOMONTH($J81,-1)+1,$K81-1)),IF(NOT(ISBLANK($N81)),$N81/$K81,$I81/$K81),0),0) -> 0 | T81: =IFERROR(IF(AND(T$54>=EOMONTH($J81,-1)+1,T$54<=EOMONTH(EOMONTH($J81,-1)+1,$K81-1)),IF(NOT(ISBLANK($N81)),$N81/$K81,$I81/$K81),0),0) -> 4272.4484 | U81: =IFERROR(IF(AND(U$54>=EOMONTH($J81,-1)+1,U$54<=EOMONTH(EOMONTH($J81,-1)+1,$K81-1)),IF(NOT(ISBLANK($N81)),$N81/$K81,$I81/$K81),0),0) -> 4272.4484 | V81: =SUM(S81:U81) -> 8544.8967 | W81: =IFERROR(IF(AND(W$54>=EOMONTH($J81,-1)+1,W$54<=EOMONTH(EOMONTH($J81,-1)+1,$K81-1)),IF(NOT(ISBLANK($N81)),$N81/$K81,$I81/$K81),0),0) -> 4272.4484 | X81: =IFERROR(IF(AND(X$54>=EOMONTH($J81,-1)+1,X$54<=EOMONTH(EOMONTH($J81,-1)+1,$K81-1)),IF(NOT(ISBLANK($N81)),$N81/$K81,$I81/$K81),0),0) -> 4272.4484 | Y81: =IFERROR(IF(AND(Y$54>=EOMONTH($J81,-1)+1,Y$54<=EOMONTH(EOMONTH($J81,-1)+1,$K81-1)),IF(NOT(ISBLANK($N81)),$N81/$K81,$I81/$K81),0),0) -> 4272.4484 | Z81: =SUM(W81:Y81) -> 12817.345 | AA81: =IFERROR(IF(AND(AA$54>=EOMONTH($J81,-1)+1,AA$54<=EOMONTH(EOMONTH($J81,-1)+1,$K81-1)),IF(NOT(ISBLANK($N81)),$N81/$K81,$I81/$K81),0),0) -> 4272.4484 | AB81: =IFERROR(IF(AND(AB$54>=EOMONTH($J81,-1)+1,AB$54<=EOMONTH(EOMONTH($J81,-1)+1,$K81-1)),IF(NOT(ISBLANK($N81)),$N81/$K81,$I81/$K81),0),0) -> 4272.4484 | AC81: =IFERROR(IF(AND(AC$54>=EOMONTH($J81,-1)+1,AC$54<=EOMONTH(EOMONTH($J81,-1)+1,$K81-1)),IF(NOT(ISBLANK($N81)),$N81/$K81,$I81/$K81),0),0) -> 4272.4484 | AD81: =SUM(AA81:AC81) -> 12817.345 | AE81: =IFERROR(IF(AND(AE$54>=EOMONTH($J81,-1)+1,AE$54<=EOMONTH(EOMONTH($J81,-1)+1,$K81-1)),IF(NOT(ISBLANK($N81)),$N81/$K81,$I81/$K81),0),0) -> 4272.4484 | AF81: =IFERROR(IF(AND(AF$54>=EOMONTH($J81,-1)+1,AF$54<=EOMONTH(EOMONTH($J81,-1)+1,$K81-1)),IF(NOT(ISBLANK($N81)),$N81/$K81,$I81/$K81),0),0) -> 4272.4484 | AG81: =IFERROR(IF(AND(AG$54>=EOMONTH($J81,-1)+1,AG$54<=EOMONTH(EOMONTH($J81,-1)+1,$K81-1)),IF(NOT(ISBLANK($N81)),$N81/$K81,$I81/$K81),0),0) -> 4272.4484 | AH81: =SUM(AE81:AG81) -> 12817.345 | AI81: =SUM(V81,Z81,AD81,AH81) -> 46996.932 | AJ81: 23/01/2026: Aguardando validação da controladoria. Projeto de kaizen número 04 de 2026 | AM81: =N81*AL81 -> 0 | AN81: =C81 -> 14 - REDUÇÃO DE MP DA000518Z (Anchieta) Código DD - VB000324Z | AO81: P | AP81: {=IF(OR(AN81="",AN81=0),"",IF(SUMPRODUCT(($C$55:$C$175=AN81)*(S$54:$AG$54<EOMONTH(TODAY(),-1)+1)*(ISNUMBER(S$55:$AG$175)),S$55:$AG$175)=0,"",SUMPRODUCT(($C$55:$C$175=AN81)*(S$54:$AG$54<EOMONTH(TODAY(),-1)+1)*(ISNUMBER(S$55:$AG$175)),S$55:$AG$175)))} -> 17089.793
Q82: Real | R82: 1 | T82: 4586.7548 | U82: 4262.5124 | V82: =SUM(S82:U82) -> 8849.2673 | W82: 6339.1211 | X82: 4808.99 | Z82: =SUM(W82:Y82) -> 11148.111 | AD82: =SUM(AA82:AC82) -> 0 | AH82: =SUM(AE82:AG82) -> 0 | AI82: =SUM(V82,Z82,AD82,AH82) -> 19997.378 | AJ82: 03/02/2026: A bobina deu entrada na DELGA Diadema em 22/01/2026 NF 139598. Fica pendente a validação da controladoria. | AN82: =C81 -> 14 - REDUÇÃO DE MP DA000518Z (Anchieta) Código DD - VB000324Z | AO82: R | AP82: {=IF(OR(AN82="",AN82=0),"",IF(SUMPRODUCT(($C$55:$C$175=AN82)*($S$54:AG$54<=TODAY())*(ISNUMBER($S$56:AG$176)),$S$56:AG$176)=0,"",SUMPRODUCT(($C$55:$C$175=AN82)*($S$54:AG$54<=TODAY())*(ISNUMBER($S$56:AG$176)),$S$56:AG$176)))} -> 19997.378
A83: Kaizen | B83: GGF | C83: 15 - Kaizem - Botões BI - MANUAL | D83: \\192.168.0.20\DEPARTAMENTOS\\Engenharia\0. Kaizen Diadema\6. 2026\01 Janeiro\05 - Kaizem - Botões BI - MANUAL_Rafael Almeida_Ferramentaria\5 - Kaizem - Botões BI - MANUAL_Rev00.xlsx | E83: Reduzir custos de fabricação, utilizando recursos internos. | F83: S. Souza | G83: 46023 | H83: 46053 | I83: 3279.77 | J83: 46023 | K83: 1 | M83: OK | N83: 3656.94 | O83: ✓ Concluído | P83: 1 | Q83: Previsto | R83: 1 | S83: =IFERROR(IF(AND(S$54>=EOMONTH($J83,-1)+1,S$54<=EOMONTH(EOMONTH($J83,-1)+1,$K83-1)),IF(NOT(ISBLANK($N83)),$N83/$K83,$I83/$K83),0),0) -> 3656.94 | T83: =IFERROR(IF(AND(T$54>=EOMONTH($J83,-1)+1,T$54<=EOMONTH(EOMONTH($J83,-1)+1,$K83-1)),IF(NOT(ISBLANK($N83)),$N83/$K83,$I83/$K83),0),0) -> 0 | U83: =IFERROR(IF(AND(U$54>=EOMONTH($J83,-1)+1,U$54<=EOMONTH(EOMONTH($J83,-1)+1,$K83-1)),IF(NOT(ISBLANK($N83)),$N83/$K83,$I83/$K83),0),0) -> 0 | V83: =SUM(S83:U83) -> 3656.94 | W83: =IFERROR(IF(AND(W$54>=EOMONTH($J83,-1)+1,W$54<=EOMONTH(EOMONTH($J83,-1)+1,$K83-1)),IF(NOT(ISBLANK($N83)),$N83/$K83,$I83/$K83),0),0) -> 0 | X83: =IFERROR(IF(AND(X$54>=EOMONTH($J83,-1)+1,X$54<=EOMONTH(EOMONTH($J83,-1)+1,$K83-1)),IF(NOT(ISBLANK($N83)),$N83/$K83,$I83/$K83),0),0) -> 0 | Y83: =IFERROR(IF(AND(Y$54>=EOMONTH($J83,-1)+1,Y$54<=EOMONTH(EOMONTH($J83,-1)+1,$K83-1)),IF(NOT(ISBLANK($N83)),$N83/$K83,$I83/$K83),0),0) -> 0 | Z83: =SUM(W83:Y83) -> 0 | AA83: =IFERROR(IF(AND(AA$54>=EOMONTH($J83,-1)+1,AA$54<=EOMONTH(EOMONTH($J83,-1)+1,$K83-1)),IF(NOT(ISBLANK($N83)),$N83/$K83,$I83/$K83),0),0) -> 0 | AB83: =IFERROR(IF(AND(AB$54>=EOMONTH($J83,-1)+1,AB$54<=EOMONTH(EOMONTH($J83,-1)+1,$K83-1)),IF(NOT(ISBLANK($N83)),$N83/$K83,$I83/$K83),0),0) -> 0 | AC83: =IFERROR(IF(AND(AC$54>=EOMONTH($J83,-1)+1,AC$54<=EOMONTH(EOMONTH($J83,-1)+1,$K83-1)),IF(NOT(ISBLANK($N83)),$N83/$K83,$I83/$K83),0),0) -> 0 | AD83: =SUM(AA83:AC83) -> 0 | AE83: =IFERROR(IF(AND(AE$54>=EOMONTH($J83,-1)+1,AE$54<=EOMONTH(EOMONTH($J83,-1)+1,$K83-1)),IF(NOT(ISBLANK($N83)),$N83/$K83,$I83/$K83),0),0) -> 0 | AF83: =IFERROR(IF(AND(AF$54>=EOMONTH($J83,-1)+1,AF$54<=EOMONTH(EOMONTH($J83,-1)+1,$K83-1)),IF(NOT(ISBLANK($N83)),$N83/$K83,$I83/$K83),0),0) -> 0 | AG83: =IFERROR(IF(AND(AG$54>=EOMONTH($J83,-1)+1,AG$54<=EOMONTH(EOMONTH($J83,-1)+1,$K83-1)),IF(NOT(ISBLANK($N83)),$N83/$K83,$I83/$K83),0),0) -> 0 | AH83: =SUM(AE83:AG83) -> 0 | AI83: =SUM(V83,Z83,AD83,AH83) -> 3656.94 | AJ83: 23/01/2026: Aguardando validação da controladoria. Projeto de kaizen número 05 de 2026 | AM83: =N83*AL83 -> 0 | AN83: =C83 -> 15 - Kaizem - Botões BI - MANUAL | AO83: P | AP83: {=IF(OR(AN83="",AN83=0),"",IF(SUMPRODUCT(($C$55:$C$175=AN83)*(S$54:$AG$54<EOMONTH(TODAY(),-1)+1)*(ISNUMBER(S$55:$AG$175)),S$55:$AG$175)=0,"",SUMPRODUCT(($C$55:$C$175=AN83)*(S$54:$AG$54<EOMONTH(TODAY(),-1)+1)*(ISNUMBER(S$55:$AG$175)),S$55:$AG$175)))} -> 3656.94
Q84: Real | R84: 1 | S84: 3656.94 | V84: =SUM(S84:U84) -> 3656.94 | Z84: =SUM(W84:Y84) -> 0 | AD84: =SUM(AA84:AC84) -> 0 | AH84: =SUM(AE84:AG84) -> 0 | AI84: =SUM(V84,Z84,AD84,AH84) -> 3656.94 | AJ84: 03/02/2026: o trabalho já foi conclído. Fica pendente apenas a validação da controladoria. | AN84: =C83 -> 15 - Kaizem - Botões BI - MANUAL | AO84: R | AP84: {=IF(OR(AN84="",AN84=0),"",IF(SUMPRODUCT(($C$55:$C$175=AN84)*($S$54:AG$54<=TODAY())*(ISNUMBER($S$56:AG$176)),$S$56:AG$176)=0,"",SUMPRODUCT(($C$55:$C$175=AN84)*($S$54:AG$54<=TODAY())*(ISNUMBER($S$56:AG$176)),$S$56:AG$176)))} -> 3656.94
A85: Kaizen | B85: GGF | C85: 16 - Eficiência de MO na linha de Solda e Montagem | D85: \\192.168.0.20\DEPARTAMENTOS\Engenharia\0. Kaizen Diadema\6. 2026\02 Fevereiro\Kaizens 10_11_12_consolidados_ Redução de 2MOD.xlsx | E85: Foram realizados 3 kaizens na linha de solda e montagem, melhorando a eficiência de MO (redução de 2MO). Kaizens 10, 11 e 12. | F85: V. Moreira | G85: 46027 | H85: 46112 | I85: 228000 | J85: 46082 | K85: =IF(J85="", "", 12 - MONTH(J85) + 1) -> 10 | M85: OK | N85: 124710.19 | O85: ✓ Concluído | P85: 1 | Q85: Previsto | R85: 1 | S85: =IFERROR(IF(AND(S$54>=EOMONTH($J85,-1)+1,S$54<=EOMONTH(EOMONTH($J85,-1)+1,$K85-1)),IF(NOT(ISBLANK($N85)),$N85/$K85,$I85/$K85),0),0) -> 0 | T85: =IFERROR(IF(AND(T$54>=EOMONTH($J85,-1)+1,T$54<=EOMONTH(EOMONTH($J85,-1)+1,$K85-1)),IF(NOT(ISBLANK($N85)),$N85/$K85,$I85/$K85),0),0) -> 0 | U85: =IFERROR(IF(AND(U$54>=EOMONTH($J85,-1)+1,U$54<=EOMONTH(EOMONTH($J85,-1)+1,$K85-1)),IF(NOT(ISBLANK($N85)),$N85/$K85,$I85/$K85),0),0) -> 12471.019 | V85: =SUM(S85:U85) -> 12471.019 | W85: =IFERROR(IF(AND(W$54>=EOMONTH($J85,-1)+1,W$54<=EOMONTH(EOMONTH($J85,-1)+1,$K85-1)),IF(NOT(ISBLANK($N85)),$N85/$K85,$I85/$K85),0),0) -> 12471.019 | X85: =IFERROR(IF(AND(X$54>=EOMONTH($J85,-1)+1,X$54<=EOMONTH(EOMONTH($J85,-1)+1,$K85-1)),IF(NOT(ISBLANK($N85)),$N85/$K85,$I85/$K85),0),0) -> 12471.019 | Y85: =IFERROR(IF(AND(Y$54>=EOMONTH($J85,-1)+1,Y$54<=EOMONTH(EOMONTH($J85,-1)+1,$K85-1)),IF(NOT(ISBLANK($N85)),$N85/$K85,$I85/$K85),0),0) -> 12471.019 | Z85: =SUM(W85:Y85) -> 37413.057 | AA85: =IFERROR(IF(AND(AA$54>=EOMONTH($J85,-1)+1,AA$54<=EOMONTH(EOMONTH($J85,-1)+1,$K85-1)),IF(NOT(ISBLANK($N85)),$N85/$K85,$I85/$K85),0),0) -> 12471.019 | AB85: =IFERROR(IF(AND(AB$54>=EOMONTH($J85,-1)+1,AB$54<=EOMONTH(EOMONTH($J85,-1)+1,$K85-1)),IF(NOT(ISBLANK($N85)),$N85/$K85,$I85/$K85),0),0) -> 12471.019 | AC85: =IFERROR(IF(AND(AC$54>=EOMONTH($J85,-1)+1,AC$54<=EOMONTH(EOMONTH($J85,-1)+1,$K85-1)),IF(NOT(ISBLANK($N85)),$N85/$K85,$I85/$K85),0),0) -> 12471.019 | AD85: =SUM(AA85:AC85) -> 37413.057 | AE85: =IFERROR(IF(AND(AE$54>=EOMONTH($J85,-1)+1,AE$54<=EOMONTH(EOMONTH($J85,-1)+1,$K85-1)),IF(NOT(ISBLANK($N85)),$N85/$K85,$I85/$K85),0),0) -> 12471.019 | AF85: =IFERROR(IF(AND(AF$54>=EOMONTH($J85,-1)+1,AF$54<=EOMONTH(EOMONTH($J85,-1)+1,$K85-1)),IF(NOT(ISBLANK($N85)),$N85/$K85,$I85/$K85),0),0) -> 12471.019 | AG85: =IFERROR(IF(AND(AG$54>=EOMONTH($J85,-1)+1,AG$54<=EOMONTH(EOMONTH($J85,-1)+1,$K85-1)),IF(NOT(ISBLANK($N85)),$N85/$K85,$I85/$K85),0),0) -> 12471.019 | AH85: =SUM(AE85:AG85) -> 37413.057 | AI85: =SUM(V85,Z85,AD85,AH85) -> 124710.19 | AJ85: 03/02/206 - O Vitório entregou 3 kaizens que juntos reduzirão 2 MOD. Projetos de kaizen número 10, 11 e 12 de 2026 | AM85: =N85*AL85 -> 0 | AN85: =C85 -> 16 - Eficiência de MO na linha de Solda e Montagem | AO85: P | AP85: {=IF(OR(AN85="",AN85=0),"",IF(SUMPRODUCT(($C$55:$C$175=AN85)*(S$54:$AG$54<EOMONTH(TODAY(),-1)+1)*(ISNUMBER(S$55:$AG$175)),S$55:$AG$175)=0,"",SUMPRODUCT(($C$55:$C$175=AN85)*(S$54:$AG$54<EOMONTH(TODAY(),-1)+1)*(ISNUMBER(S$55:$AG$175)),S$55:$AG$175)))} -> 37413.057
Q86: Real | R86: 1 | S86: 0 | T86: 0 | U86: -19064.81 | V86: =SUM(S86:U86) -> -19064.81 | W86: 15975 | X86: 15975 | Y86: 0 | Z86: =SUM(W86:Y86) -> 31950 | AD86: =SUM(AA86:AC86) -> 0 | AH86: =SUM(AE86:AG86) -> 0 | AI86: =SUM(V86,Z86,AD86,AH86) -> 12885.19 | AJ86: 03/02/2026 - No dia 06/02/2026 foi executado a primeira redução de MOD. | AN86: =C85 -> 16 - Eficiência de MO na linha de Solda e Montagem | AO86: R | AP86: {=IF(OR(AN86="",AN86=0),"",IF(SUMPRODUCT(($C$55:$C$175=AN86)*($S$54:AG$54<=TODAY())*(ISNUMBER($S$56:AG$176)),$S$56:AG$176)=0,"",SUMPRODUCT(($C$55:$C$175=AN86)*($S$54:AG$54<=TODAY())*(ISNUMBER($S$56:AG$176)),$S$56:AG$176)))} -> 12885.19
A87: BSW | B87: VA | C87: 17 - MB003537LB_MB003538LB | D87: \\192.168.0.20\DEPARTAMENTOS\\Engenharia\0. Kaizen Diadema\6. 2026\02 Fevereiro\13 - MB003537LB_MB003538LB - Bruno Manachini_Engenharia\13 - KAIZEN - MB003537LB_MB003538LB_Rev00_Bruno Manachini.xlsx | E87: De 111 peças por chapa para 160 | F87: B. Manachini | G87: 46054 | H87: 46112 | I87: 51480 | J87: 46082 | K87: =IF(J87="", "", 12 - MONTH(J87) + 1) -> 10 | M87: OK | N87: 33838.06 | O87: ✓ Concluído | P87: 1 | Q87: Previsto | R87: 1 | S87: =IFERROR(IF(AND(S$54>=EOMONTH($J87,-1)+1,S$54<=EOMONTH(EOMONTH($J87,-1)+1,$K87-1)),IF(NOT(ISBLANK($N87)),$N87/$K87,$I87/$K87),0),0) -> 0 | T87: =IFERROR(IF(AND(T$54>=EOMONTH($J87,-1)+1,T$54<=EOMONTH(EOMONTH($J87,-1)+1,$K87-1)),IF(NOT(ISBLANK($N87)),$N87/$K87,$I87/$K87),0),0) -> 0 | U87: =IFERROR(IF(AND(U$54>=EOMONTH($J87,-1)+1,U$54<=EOMONTH(EOMONTH($J87,-1)+1,$K87-1)),IF(NOT(ISBLANK($N87)),$N87/$K87,$I87/$K87),0),0) -> 3383.806 | V87: =SUM(S87:U87) -> 3383.806 | W87: =IFERROR(IF(AND(W$54>=EOMONTH($J87,-1)+1,W$54<=EOMONTH(EOMONTH($J87,-1)+1,$K87-1)),IF(NOT(ISBLANK($N87)),$N87/$K87,$I87/$K87),0),0) -> 3383.806 | X87: =IFERROR(IF(AND(X$54>=EOMONTH($J87,-1)+1,X$54<=EOMONTH(EOMONTH($J87,-1)+1,$K87-1)),IF(NOT(ISBLANK($N87)),$N87/$K87,$I87/$K87),0),0) -> 3383.806 | Y87: =IFERROR(IF(AND(Y$54>=EOMONTH($J87,-1)+1,Y$54<=EOMONTH(EOMONTH($J87,-1)+1,$K87-1)),IF(NOT(ISBLANK($N87)),$N87/$K87,$I87/$K87),0),0) -> 3383.806 | Z87: =SUM(W87:Y87) -> 10151.418 | AA87: =IFERROR(IF(AND(AA$54>=EOMONTH($J87,-1)+1,AA$54<=EOMONTH(EOMONTH($J87,-1)+1,$K87-1)),IF(NOT(ISBLANK($N87)),$N87/$K87,$I87/$K87),0),0) -> 3383.806 | AB87: =IFERROR(IF(AND(AB$54>=EOMONTH($J87,-1)+1,AB$54<=EOMONTH(EOMONTH($J87,-1)+1,$K87-1)),IF(NOT(ISBLANK($N87)),$N87/$K87,$I87/$K87),0),0) -> 3383.806 | AC87: =IFERROR(IF(AND(AC$54>=EOMONTH($J87,-1)+1,AC$54<=EOMONTH(EOMONTH($J87,-1)+1,$K87-1)),IF(NOT(ISBLANK($N87)),$N87/$K87,$I87/$K87),0),0) -> 3383.806 | AD87: =SUM(AA87:AC87) -> 10151.418 | AE87: =IFERROR(IF(AND(AE$54>=EOMONTH($J87,-1)+1,AE$54<=EOMONTH(EOMONTH($J87,-1)+1,$K87-1)),IF(NOT(ISBLANK($N87)),$N87/$K87,$I87/$K87),0),0) -> 3383.806 | AF87: =IFERROR(IF(AND(AF$54>=EOMONTH($J87,-1)+1,AF$54<=EOMONTH(EOMONTH($J87,-1)+1,$K87-1)),IF(NOT(ISBLANK($N87)),$N87/$K87,$I87/$K87),0),0) -> 3383.806 | AG87: =IFERROR(IF(AND(AG$54>=EOMONTH($J87,-1)+1,AG$54<=EOMONTH(EOMONTH($J87,-1)+1,$K87-1)),IF(NOT(ISBLANK($N87)),$N87/$K87,$I87/$K87),0),0) -> 3383.806 | AH87: =SUM(AE87:AG87) -> 10151.418 | AI87: =SUM(V87,Z87,AD87,AH87) -> 33838.06 | AJ87: 05/02/2026 - Kaizen número 13 de 2026, em processo de implementação. Programa de corte laser e LT SAP. Projeto de kaizen número 13 de 2026 | AM87: =N87*AL87 -> 0 | AN87: =C87 -> 17 - MB003537LB_MB003538LB | AO87: P | AP87: {=IF(OR(AN87="",AN87=0),"",IF(SUMPRODUCT(($C$55:$C$175=AN87)*(S$54:$AG$54<EOMONTH(TODAY(),-1)+1)*(ISNUMBER(S$55:$AG$175)),S$55:$AG$175)=0,"",SUMPRODUCT(($C$55:$C$175=AN87)*(S$54:$AG$54<EOMONTH(TODAY(),-1)+1)*(ISNUMBER(S$55:$AG$175)),S$55:$AG$175)))} -> 10151.418
Q88: Real | R88: 1 | U88: 3976.6832 | V88: =SUM(S88:U88) -> 3976.6832 | W88: 3849.0581 | X88: 2730.8879 | Z88: =SUM(W88:Y88) -> 6579.946 | AD88: =SUM(AA88:AC88) -> 0 | AH88: =SUM(AE88:AG88) -> 0 | AI88: =SUM(V88,Z88,AD88,AH88) -> 10556.629 | AJ88: 05/02/2026 - Aguardando validçaão da controladoria; 10/02/2026: validado pela Carolina Rodrigues em 10/02/2026 15h31 - e-mail -> Calculado o ganho direto da MP, visto que os processos não mudam - baseado no volume Budget dos itens que são faturados (Março a Dezembro) | AN88: =C87 -> 17 - MB003537LB_MB003538LB | AO88: R | AP88: {=IF(OR(AN88="",AN88=0),"",IF(SUMPRODUCT(($C$55:$C$175=AN88)*($S$54:AG$54<=TODAY())*(ISNUMBER($S$56:AG$176)),$S$56:AG$176)=0,"",SUMPRODUCT(($C$55:$C$175=AN88)*($S$54:AG$54<=TODAY())*(ISNUMBER($S$56:AG$176)),$S$56:AG$176)))} -> 10556.629
A89: Redução de custo | B89: Outros | C89: 18 - Venda de Embalagens, ativos e sucatas | D89: \\192.168.0.20\DEPARTAMENTOS\\Engenharia\0. Kaizen Diadema\6. 2026\03 Março\41 - VENDA DE ATIVOS OBSOLETOS_Paulo Algodoal_Produção\41 - VENDA DE ATIVOS OBSOLETOS_REV00.xlsx | E89: Fazer levantamento de embalagens obsoletas, quantificar e pesar. | F89: P. Algodoal | G89: 46058 | H89: 46147 | I89: =20000+26052 -> 46052 | K89: =IF(J89="", "", 12 - MONTH(J89) + 1) | M89: OK | O89: ⏳ Em Execução | Q89: Previsto | R89: 0.91 | S89: =IFERROR(IF(AND(S$54>=EOMONTH($J89,-1)+1,S$54<=EOMONTH(EOMONTH($J89,-1)+1,$K89-1)),IF(NOT(ISBLANK($N89)),$N89/$K89,$I89/$K89),0),0) -> 0 | T89: =IFERROR(IF(AND(T$54>=EOMONTH($J89,-1)+1,T$54<=EOMONTH(EOMONTH($J89,-1)+1,$K89-1)),IF(NOT(ISBLANK($N89)),$N89/$K89,$I89/$K89),0),0) -> 0 | U89: =IFERROR(IF(AND(U$54>=EOMONTH($J89,-1)+1,U$54<=EOMONTH(EOMONTH($J89,-1)+1,$K89-1)),IF(NOT(ISBLANK($N89)),$N89/$K89,$I89/$K89),0),0) -> 0 | V89: =SUM(S89:U89) -> 0 | W89: =IFERROR(IF(AND(W$54>=EOMONTH($J89,-1)+1,W$54<=EOMONTH(EOMONTH($J89,-1)+1,$K89-1)),IF(NOT(ISBLANK($N89)),$N89/$K89,$I89/$K89),0),0) -> 0 | X89: =IFERROR(IF(AND(X$54>=EOMONTH($J89,-1)+1,X$54<=EOMONTH(EOMONTH($J89,-1)+1,$K89-1)),IF(NOT(ISBLANK($N89)),$N89/$K89,$I89/$K89),0),0) -> 0 | Y89: =20000+26052 -> 46052 | Z89: =SUM(W89:Y89) -> 46052 | AA89: =IFERROR(IF(AND(AA$54>=EOMONTH($J89,-1)+1,AA$54<=EOMONTH(EOMONTH($J89,-1)+1,$K89-1)),IF(NOT(ISBLANK($N89)),$N89/$K89,$I89/$K89),0),0) -> 0 | AB89: =IFERROR(IF(AND(AB$54>=EOMONTH($J89,-1)+1,AB$54<=EOMONTH(EOMONTH($J89,-1)+1,$K89-1)),IF(NOT(ISBLANK($N89)),$N89/$K89,$I89/$K89),0),0) -> 0 | AC89: =IFERROR(IF(AND(AC$54>=EOMONTH($J89,-1)+1,AC$54<=EOMONTH(EOMONTH($J89,-1)+1,$K89-1)),IF(NOT(ISBLANK($N89)),$N89/$K89,$I89/$K89),0),0) -> 0 | AD89: =SUM(AA89:AC89) -> 0 | AE89: =IFERROR(IF(AND(AE$54>=EOMONTH($J89,-1)+1,AE$54<=EOMONTH(EOMONTH($J89,-1)+1,$K89-1)),IF(NOT(ISBLANK($N89)),$N89/$K89,$I89/$K89),0),0) -> 0 | AF89: =IFERROR(IF(AND(AF$54>=EOMONTH($J89,-1)+1,AF$54<=EOMONTH(EOMONTH($J89,-1)+1,$K89-1)),IF(NOT(ISBLANK($N89)),$N89/$K89,$I89/$K89),0),0) -> 0 | AG89: =IFERROR(IF(AND(AG$54>=EOMONTH($J89,-1)+1,AG$54<=EOMONTH(EOMONTH($J89,-1)+1,$K89-1)),IF(NOT(ISBLANK($N89)),$N89/$K89,$I89/$K89),0),0) -> 0 | AH89: =SUM(AE89:AG89) -> 0 | AI89: =SUM(V89,Z89,AD89,AH89) -> 46052 | AJ89: 02/04/2026: Projeto de kaizen número 42 de 2026. | AM89: =N89*AL89 -> 0 | AN89: =C89 -> 18 - Venda de Embalagens, ativos e sucatas | AO89: P | AP89: {=IF(OR(AN89="",AN89=0),"",IF(SUMPRODUCT(($C$55:$C$175=AN89)*(S$54:$AG$54<EOMONTH(TODAY(),-1)+1)*(ISNUMBER(S$55:$AG$175)),S$55:$AG$175)=0,"",SUMPRODUCT(($C$55:$C$175=AN89)*(S$54:$AG$54<EOMONTH(TODAY(),-1)+1)*(ISNUMBER(S$55:$AG$175)),S$55:$AG$175)))}
Q90: Real | R90: 0.7 | V90: =SUM(S90:U90) -> 0 | Z90: =SUM(W90:Y90) -> 0 | AD90: =SUM(AA90:AC90) -> 0 | AH90: =SUM(AE90:AG90) -> 0 | AI90: =SUM(V90,Z90,AD90,AH90) -> 0 | AN90: =C89 -> 18 - Venda de Embalagens, ativos e sucatas | AO90: R | AP90: {=IF(OR(AN90="",AN90=0),"",IF(SUMPRODUCT(($C$55:$C$175=AN90)*($S$54:AG$54<=TODAY())*(ISNUMBER($S$56:AG$176)),$S$56:AG$176)=0,"",SUMPRODUCT(($C$55:$C$175=AN90)*($S$54:AG$54<=TODAY())*(ISNUMBER($S$56:AG$176)),$S$56:AG$176)))}
A91: Kaizen | B91: GGF | C91: 19 - Kaizen Facão. DA000481Z - PRODUTIVIDADE | D91: \\192.168.0.20\DEPARTAMENTOS\Engenharia\0. Kaizen Diadema\6. 2026\01 Janeiro\07 - Kaizen Facão_Sebastião Gomes\7 - KAIZEN FACÃO DA000418Z_JAN 2026.xlsx | E91: Reduzir a quantidade de MO de 2 para 1 MO. | F91: S. Gomes | G91: 46027 | H91: 46081 | I91: 54000 | J91: 46082 | K91: =IF(J91="", "", 12 - MONTH(J91) + 1) -> 10 | O91: ✓ Concluído | P91: 1 | Q91: Previsto | R91: 1 | S91: =IFERROR(IF(AND(S$54>=EOMONTH($J91,-1)+1,S$54<=EOMONTH(EOMONTH($J91,-1)+1,$K91-1)),IF(NOT(ISBLANK($N91)),$N91/$K91,$I91/$K91),0),0) -> 0 | T91: =IFERROR(IF(AND(T$54>=EOMONTH($J91,-1)+1,T$54<=EOMONTH(EOMONTH($J91,-1)+1,$K91-1)),IF(NOT(ISBLANK($N91)),$N91/$K91,$I91/$K91),0),0) -> 0 | U91: =IFERROR(IF(AND(U$54>=EOMONTH($J91,-1)+1,U$54<=EOMONTH(EOMONTH($J91,-1)+1,$K91-1)),IF(NOT(ISBLANK($N91)),$N91/$K91,$I91/$K91),0),0) -> 5400 | V91: =SUM(S91:U91) -> 5400 | W91: =IFERROR(IF(AND(W$54>=EOMONTH($J91,-1)+1,W$54<=EOMONTH(EOMONTH($J91,-1)+1,$K91-1)),IF(NOT(ISBLANK($N91)),$N91/$K91,$I91/$K91),0),0) -> 5400 | X91: =IFERROR(IF(AND(X$54>=EOMONTH($J91,-1)+1,X$54<=EOMONTH(EOMONTH($J91,-1)+1,$K91-1)),IF(NOT(ISBLANK($N91)),$N91/$K91,$I91/$K91),0),0) -> 5400 | Y91: =IFERROR(IF(AND(Y$54>=EOMONTH($J91,-1)+1,Y$54<=EOMONTH(EOMONTH($J91,-1)+1,$K91-1)),IF(NOT(ISBLANK($N91)),$N91/$K91,$I91/$K91),0),0) -> 5400 | Z91: =SUM(W91:Y91) -> 16200 | AA91: =IFERROR(IF(AND(AA$54>=EOMONTH($J91,-1)+1,AA$54<=EOMONTH(EOMONTH($J91,-1)+1,$K91-1)),IF(NOT(ISBLANK($N91)),$N91/$K91,$I91/$K91),0),0) -> 5400 | AB91: =IFERROR(IF(AND(AB$54>=EOMONTH($J91,-1)+1,AB$54<=EOMONTH(EOMONTH($J91,-1)+1,$K91-1)),IF(NOT(ISBLANK($N91)),$N91/$K91,$I91/$K91),0),0) -> 5400 | AC91: =IFERROR(IF(AND(AC$54>=EOMONTH($J91,-1)+1,AC$54<=EOMONTH(EOMONTH($J91,-1)+1,$K91-1)),IF(NOT(ISBLANK($N91)),$N91/$K91,$I91/$K91),0),0) -> 5400 | AD91: =SUM(AA91:AC91) -> 16200 | AE91: =IFERROR(IF(AND(AE$54>=EOMONTH($J91,-1)+1,AE$54<=EOMONTH(EOMONTH($J91,-1)+1,$K91-1)),IF(NOT(ISBLANK($N91)),$N91/$K91,$I91/$K91),0),0) -> 5400 | AF91: =IFERROR(IF(AND(AF$54>=EOMONTH($J91,-1)+1,AF$54<=EOMONTH(EOMONTH($J91,-1)+1,$K91-1)),IF(NOT(ISBLANK($N91)),$N91/$K91,$I91/$K91),0),0) -> 5400 | AG91: =IFERROR(IF(AND(AG$54>=EOMONTH($J91,-1)+1,AG$54<=EOMONTH(EOMONTH($J91,-1)+1,$K91-1)),IF(NOT(ISBLANK($N91)),$N91/$K91,$I91/$K91),0),0) -> 5400 | AH91: =SUM(AE91:AG91) -> 16200 | AI91: =SUM(V91,Z91,AD91,AH91) -> 54000 | AJ91: 05/02/2026: Falta atualizar a LT do SAP. Projeto de kaizen número 07 de 2026. | AM91: =N91*AL91 -> 0 | AN91: =C91 -> 19 - Kaizen Facão. DA000481Z - PRODUTIVIDADE | AO91: P | AP91: {=IF(OR(AN91="",AN91=0),"",IF(SUMPRODUCT(($C$55:$C$175=AN91)*(S$54:$AG$54<EOMONTH(TODAY(),-1)+1)*(ISNUMBER(S$55:$AG$175)),S$55:$AG$175)=0,"",SUMPRODUCT(($C$55:$C$175=AN91)*(S$54:$AG$54<EOMONTH(TODAY(),-1)+1)*(ISNUMBER(S$55:$AG$175)),S$55:$AG$175)))} -> 16200
Q92: Real | R92: 1 | V92: =SUM(S92:U92) -> 0 | Z92: =SUM(W92:Y92) -> 0 | AD92: =SUM(AA92:AC92) -> 0 | AH92: =SUM(AE92:AG92) -> 0 | AI92: =SUM(V92,Z92,AD92,AH92) -> 0 | AJ92: Projeto concluído, tendo redução de 1MO somando este projeto com o projeto 3 (Cavalo Marinho) e projeto 4 (Pulmão). | AN92: =C91 -> 19 - Kaizen Facão. DA000481Z - PRODUTIVIDADE | AO92: R | AP92: {=IF(OR(AN92="",AN92=0),"",IF(SUMPRODUCT(($C$55:$C$175=AN92)*($S$54:AG$54<=TODAY())*(ISNUMBER($S$56:AG$176)),$S$56:AG$176)=0,"",SUMPRODUCT(($C$55:$C$175=AN92)*($S$54:AG$54<=TODAY())*(ISNUMBER($S$56:AG$176)),$S$56:AG$176)))}
A93: Redução de custo | C93: 20 - Redução refugo em relação ao budget | D93: \\192.168.0.20\DEPARTAMENTOS\Engenharia\0. Kaizen Diadema\6. 2026\02 Fevereiro\19 - Redução de refugo em relação ao budget_Rodrigo Larrubia\19 - Redução de refugo em relação ao budget 2026.xlsx | E93: Para budget 2026 foi previsto R$442K (36,8k/mês). Objetivo 0,2% do faturamento, logo, R$360K. | F93: R. Larrubia | G93: 46027 | H93: 46387 | J93: 46023 | K93: =IF(J93="", "", 12 - MONTH(J93) + 1) -> 12 | M93: Não Ok | P93: 1 | Q93: Previsto | R93: 0.31 | S93: =IFERROR(IF(AND(S$54>=EOMONTH($J93,-1)+1,S$54<=EOMONTH(EOMONTH($J93,-1)+1,$K93-1)),IF(NOT(ISBLANK($N93)),$N93/$K93,$I93/$K93),0),0) -> 0 | T93: =IFERROR(IF(AND(T$54>=EOMONTH($J93,-1)+1,T$54<=EOMONTH(EOMONTH($J93,-1)+1,$K93-1)),IF(NOT(ISBLANK($N93)),$N93/$K93,$I93/$K93),0),0) -> 0 | U93: =IFERROR(IF(AND(U$54>=EOMONTH($J93,-1)+1,U$54<=EOMONTH(EOMONTH($J93,-1)+1,$K93-1)),IF(NOT(ISBLANK($N93)),$N93/$K93,$I93/$K93),0),0) -> 0 | V93: =SUM(S93:U93) -> 0 | W93: =IFERROR(IF(AND(W$54>=EOMONTH($J93,-1)+1,W$54<=EOMONTH(EOMONTH($J93,-1)+1,$K93-1)),IF(NOT(ISBLANK($N93)),$N93/$K93,$I93/$K93),0),0) -> 0 | X93: =IFERROR(IF(AND(X$54>=EOMONTH($J93,-1)+1,X$54<=EOMONTH(EOMONTH($J93,-1)+1,$K93-1)),IF(NOT(ISBLANK($N93)),$N93/$K93,$I93/$K93),0),0) -> 0 | Y93: =IFERROR(IF(AND(Y$54>=EOMONTH($J93,-1)+1,Y$54<=EOMONTH(EOMONTH($J93,-1)+1,$K93-1)),IF(NOT(ISBLANK($N93)),$N93/$K93,$I93/$K93),0),0) -> 0 | Z93: =SUM(W93:Y93) -> 0 | AA93: =IFERROR(IF(AND(AA$54>=EOMONTH($J93,-1)+1,AA$54<=EOMONTH(EOMONTH($J93,-1)+1,$K93-1)),IF(NOT(ISBLANK($N93)),$N93/$K93,$I93/$K93),0),0) -> 0 | AB93: =IFERROR(IF(AND(AB$54>=EOMONTH($J93,-1)+1,AB$54<=EOMONTH(EOMONTH($J93,-1)+1,$K93-1)),IF(NOT(ISBLANK($N93)),$N93/$K93,$I93/$K93),0),0) -> 0 | AC93: =IFERROR(IF(AND(AC$54>=EOMONTH($J93,-1)+1,AC$54<=EOMONTH(EOMONTH($J93,-1)+1,$K93-1)),IF(NOT(ISBLANK($N93)),$N93/$K93,$I93/$K93),0),0) -> 0 | AD93: =SUM(AA93:AC93) -> 0 | AE93: =IFERROR(IF(AND(AE$54>=EOMONTH($J93,-1)+1,AE$54<=EOMONTH(EOMONTH($J93,-1)+1,$K93-1)),IF(NOT(ISBLANK($N93)),$N93/$K93,$I93/$K93),0),0) -> 0 | AF93: =IFERROR(IF(AND(AF$54>=EOMONTH($J93,-1)+1,AF$54<=EOMONTH(EOMONTH($J93,-1)+1,$K93-1)),IF(NOT(ISBLANK($N93)),$N93/$K93,$I93/$K93),0),0) -> 0 | AG93: =IFERROR(IF(AND(AG$54>=EOMONTH($J93,-1)+1,AG$54<=EOMONTH(EOMONTH($J93,-1)+1,$K93-1)),IF(NOT(ISBLANK($N93)),$N93/$K93,$I93/$K93),0),0) -> 0 | AH93: =SUM(AE93:AG93) -> 0 | AI93: =SUM(V93,Z93,AD93,AH93) -> 0 | AJ93: 05/02/2026 - O objetivo é reduzir o custo médio mensal previsto no budget, para um custo de 0,2% em relação ao faturamento. Budget prevê R$442K. Se ficarmos anaixo de 0,2% do faturamento (R$360K), o potencial de ganho é R$82K - VALIDADO Custos >> Projeção de ganho anual de 83.506,82 ( nessa meta o interessante é praticar sempre menos do que o Budget mensal, visto que a projeção do Budget anual já considera 0,2% do faturamento. | AM93: =N93*AL93 -> 0 | AN93: =C93 -> 20 - Redução refugo em relação ao budget | AO93: P | AP93: {=IF(OR(AN93="",AN93=0),"",IF(SUMPRODUCT(($C$55:$C$175=AN93)*(S$54:$AG$54<EOMONTH(TODAY(),-1)+1)*(ISNUMBER(S$55:$AG$175)),S$55:$AG$175)=0,"",SUMPRODUCT(($C$55:$C$175=AN93)*(S$54:$AG$54<EOMONTH(TODAY(),-1)+1)*(ISNUMBER(S$55:$AG$175)),S$55:$AG$175)))}
Q94: Real | S94: 0 | T94: 0 | V94: =SUM(S94:U94) -> 0 | Z94: =SUM(W94:Y94) -> 0 | AD94: =SUM(AA94:AC94) -> 0 | AH94: =SUM(AE94:AG94) -> 0 | AI94: =SUM(V94,Z94,AD94,AH94) -> 0 | AJ94: 05/02/2026: e-mail do Paulo Ribeiro confirmando o R$ do budget, 05/02/2026 16h18, salvo na pasta, como evidência. Projeto de kaizen númrero 19 de 2026 | AN94: =C93 -> 20 - Redução refugo em relação ao budget | AO94: R | AP94: {=IF(OR(AN94="",AN94=0),"",IF(SUMPRODUCT(($C$55:$C$175=AN94)*($S$54:AG$54<=TODAY())*(ISNUMBER($S$56:AG$176)),$S$56:AG$176)=0,"",SUMPRODUCT(($C$55:$C$175=AN94)*($S$54:AG$54<=TODAY())*(ISNUMBER($S$56:AG$176)),$S$56:AG$176)))}
A95: BSW | B95: VA | C95: 21 - Kaizen_Redução de peso bruto MB003537LA_MB003538LA | D95: \\192.168.0.20\DEPARTAMENTOS\\Engenharia\0. Kaizen Diadema\6. 2026\02 Fevereiro\14 - MB003537LA_MB003538LA - Bruno Manachini_Engenharia\14 - KAIZEN - MB003537LA_MB003538LA_Rev00_Bruno Manachini.xlsx | E95: De 111 peças por chapa para 168 | F95: B. Manachini | G95: 46054 | H95: 46112 | I95: 56826 | J95: 46082 | K95: =IF(J95="", "", 12 - MONTH(J95) + 1) -> 10 | M95: OK | N95: 37365.58 | O95: ✓ Concluído | P95: 1 | Q95: Previsto | R95: 1 | S95: =IFERROR(IF(AND(S$54>=EOMONTH($J95,-1)+1,S$54<=EOMONTH(EOMONTH($J95,-1)+1,$K95-1)),IF(NOT(ISBLANK($N95)),$N95/$K95,$I95/$K95),0),0) -> 0 | T95: =IFERROR(IF(AND(T$54>=EOMONTH($J95,-1)+1,T$54<=EOMONTH(EOMONTH($J95,-1)+1,$K95-1)),IF(NOT(ISBLANK($N95)),$N95/$K95,$I95/$K95),0),0) -> 0 | U95: =IFERROR(IF(AND(U$54>=EOMONTH($J95,-1)+1,U$54<=EOMONTH(EOMONTH($J95,-1)+1,$K95-1)),IF(NOT(ISBLANK($N95)),$N95/$K95,$I95/$K95),0),0) -> 3736.558 | V95: =SUM(S95:U95) -> 3736.558 | W95: =IFERROR(IF(AND(W$54>=EOMONTH($J95,-1)+1,W$54<=EOMONTH(EOMONTH($J95,-1)+1,$K95-1)),IF(NOT(ISBLANK($N95)),$N95/$K95,$I95/$K95),0),0) -> 3736.558 | X95: =IFERROR(IF(AND(X$54>=EOMONTH($J95,-1)+1,X$54<=EOMONTH(EOMONTH($J95,-1)+1,$K95-1)),IF(NOT(ISBLANK($N95)),$N95/$K95,$I95/$K95),0),0) -> 3736.558 | Y95: =IFERROR(IF(AND(Y$54>=EOMONTH($J95,-1)+1,Y$54<=EOMONTH(EOMONTH($J95,-1)+1,$K95-1)),IF(NOT(ISBLANK($N95)),$N95/$K95,$I95/$K95),0),0) -> 3736.558 | Z95: =SUM(W95:Y95) -> 11209.674 | AA95: =IFERROR(IF(AND(AA$54>=EOMONTH($J95,-1)+1,AA$54<=EOMONTH(EOMONTH($J95,-1)+1,$K95-1)),IF(NOT(ISBLANK($N95)),$N95/$K95,$I95/$K95),0),0) -> 3736.558 | AB95: =IFERROR(IF(AND(AB$54>=EOMONTH($J95,-1)+1,AB$54<=EOMONTH(EOMONTH($J95,-1)+1,$K95-1)),IF(NOT(ISBLANK($N95)),$N95/$K95,$I95/$K95),0),0) -> 3736.558 | AC95: =IFERROR(IF(AND(AC$54>=EOMONTH($J95,-1)+1,AC$54<=EOMONTH(EOMONTH($J95,-1)+1,$K95-1)),IF(NOT(ISBLANK($N95)),$N95/$K95,$I95/$K95),0),0) -> 3736.558 | AD95: =SUM(AA95:AC95) -> 11209.674 | AE95: =IFERROR(IF(AND(AE$54>=EOMONTH($J95,-1)+1,AE$54<=EOMONTH(EOMONTH($J95,-1)+1,$K95-1)),IF(NOT(ISBLANK($N95)),$N95/$K95,$I95/$K95),0),0) -> 3736.558 | AF95: =IFERROR(IF(AND(AF$54>=EOMONTH($J95,-1)+1,AF$54<=EOMONTH(EOMONTH($J95,-1)+1,$K95-1)),IF(NOT(ISBLANK($N95)),$N95/$K95,$I95/$K95),0),0) -> 3736.558 | AG95: =IFERROR(IF(AND(AG$54>=EOMONTH($J95,-1)+1,AG$54<=EOMONTH(EOMONTH($J95,-1)+1,$K95-1)),IF(NOT(ISBLANK($N95)),$N95/$K95,$I95/$K95),0),0) -> 3736.558 | AH95: =SUM(AE95:AG95) -> 11209.674 | AI95: =SUM(V95,Z95,AD95,AH95) -> 37365.58 | AJ95: 05/02/2026 - Projeto de kaizen número 14 de 2026, em processo de implementação. Programa de corte laser e LT SAP. | AM95: =N95*AL95 -> 0 | AN95: =C95 -> 21 - Kaizen_Redução de peso bruto MB003537LA_MB003538LA | AO95: P | AP95: {=IF(OR(AN95="",AN95=0),"",IF(SUMPRODUCT(($C$55:$C$175=AN95)*(S$54:$AG$54<EOMONTH(TODAY(),-1)+1)*(ISNUMBER(S$55:$AG$175)),S$55:$AG$175)=0,"",SUMPRODUCT(($C$55:$C$175=AN95)*(S$54:$AG$54<EOMONTH(TODAY(),-1)+1)*(ISNUMBER(S$55:$AG$175)),S$55:$AG$175)))} -> 11209.674
Q96: Real | R96: 1 | U96: 4391.241 | V96: =SUM(S96:U96) -> 4391.241 | W96: 4250.3113 | X96: 3015.575 | Z96: =SUM(W96:Y96) -> 7265.8863 | AD96: =SUM(AA96:AC96) -> 0 | AH96: =SUM(AE96:AG96) -> 0 | AI96: =SUM(V96,Z96,AD96,AH96) -> 11657.127 | AJ96: 05/02/2026 - Aguardando validação dae Custos -> Calculado o ganho direto da MP, visto que os processos não mudam - baseado no volume Budget dos itens que são faturados (Março a Dezembro) | AN96: =C95 -> 21 - Kaizen_Redução de peso bruto MB003537LA_MB003538LA | AO96: R | AP96: {=IF(OR(AN96="",AN96=0),"",IF(SUMPRODUCT(($C$55:$C$175=AN96)*($S$54:AG$54<=TODAY())*(ISNUMBER($S$56:AG$176)),$S$56:AG$176)=0,"",SUMPRODUCT(($C$55:$C$175=AN96)*($S$54:AG$54<=TODAY())*(ISNUMBER($S$56:AG$176)),$S$56:AG$176)))} -> 11657.127
A97: BSW | B97: VA | C97: 22 - Aproveitamento de Retalho do corte laser - MB002316LA_MB003533LA_MB003673LC | D97: \\192.168.0.20\DEPARTAMENTOS\Engenharia\0. Kaizen Diadema\6. 2026\02 Fevereiro\15 - MB002316LA_MB003533LA_MB003673LC - Bruno Manachini_Engenharia\15 - KAIZEN - MB002316LA_MB003533LA_MB003673LC_Rev00_Bruno Manachini.xlsx | E97: Corta as peças MB003673LC e MB003533LA/LB no retalho da peça MB002316LA | F97: B. Manachini | G97: 46054 | H97: 46082 | I97: 36000 | J97: 46113 | K97: =IF(J97="", "", 12 - MONTH(J97) + 1) -> 9 | M97: Não Ok | O97: ✓ Concluído | P97: 1 | Q97: Previsto | R97: 1 | S97: =IFERROR(IF(AND(S$54>=EOMONTH($J97,-1)+1,S$54<=EOMONTH(EOMONTH($J97,-1)+1,$K97-1)),IF(NOT(ISBLANK($N97)),$N97/$K97,$I97/$K97),0),0) -> 0 | T97: =IFERROR(IF(AND(T$54>=EOMONTH($J97,-1)+1,T$54<=EOMONTH(EOMONTH($J97,-1)+1,$K97-1)),IF(NOT(ISBLANK($N97)),$N97/$K97,$I97/$K97),0),0) -> 0 | U97: =IFERROR(IF(AND(U$54>=EOMONTH($J97,-1)+1,U$54<=EOMONTH(EOMONTH($J97,-1)+1,$K97-1)),IF(NOT(ISBLANK($N97)),$N97/$K97,$I97/$K97),0),0) -> 0 | V97: =SUM(S97:U97) -> 0 | W97: =IFERROR(IF(AND(W$54>=EOMONTH($J97,-1)+1,W$54<=EOMONTH(EOMONTH($J97,-1)+1,$K97-1)),IF(NOT(ISBLANK($N97)),$N97/$K97,$I97/$K97),0),0) -> 4000 | X97: =IFERROR(IF(AND(X$54>=EOMONTH($J97,-1)+1,X$54<=EOMONTH(EOMONTH($J97,-1)+1,$K97-1)),IF(NOT(ISBLANK($N97)),$N97/$K97,$I97/$K97),0),0) -> 4000 | Y97: =IFERROR(IF(AND(Y$54>=EOMONTH($J97,-1)+1,Y$54<=EOMONTH(EOMONTH($J97,-1)+1,$K97-1)),IF(NOT(ISBLANK($N97)),$N97/$K97,$I97/$K97),0),0) -> 4000 | Z97: =SUM(W97:Y97) -> 12000 | AA97: =IFERROR(IF(AND(AA$54>=EOMONTH($J97,-1)+1,AA$54<=EOMONTH(EOMONTH($J97,-1)+1,$K97-1)),IF(NOT(ISBLANK($N97)),$N97/$K97,$I97/$K97),0),0) -> 4000 | AB97: =IFERROR(IF(AND(AB$54>=EOMONTH($J97,-1)+1,AB$54<=EOMONTH(EOMONTH($J97,-1)+1,$K97-1)),IF(NOT(ISBLANK($N97)),$N97/$K97,$I97/$K97),0),0) -> 4000 | AC97: =IFERROR(IF(AND(AC$54>=EOMONTH($J97,-1)+1,AC$54<=EOMONTH(EOMONTH($J97,-1)+1,$K97-1)),IF(NOT(ISBLANK($N97)),$N97/$K97,$I97/$K97),0),0) -> 4000 | AD97: =SUM(AA97:AC97) -> 12000 | AE97: =IFERROR(IF(AND(AE$54>=EOMONTH($J97,-1)+1,AE$54<=EOMONTH(EOMONTH($J97,-1)+1,$K97-1)),IF(NOT(ISBLANK($N97)),$N97/$K97,$I97/$K97),0),0) -> 4000 | AF97: =IFERROR(IF(AND(AF$54>=EOMONTH($J97,-1)+1,AF$54<=EOMONTH(EOMONTH($J97,-1)+1,$K97-1)),IF(NOT(ISBLANK($N97)),$N97/$K97,$I97/$K97),0),0) -> 4000 | AG97: =IFERROR(IF(AND(AG$54>=EOMONTH($J97,-1)+1,AG$54<=EOMONTH(EOMONTH($J97,-1)+1,$K97-1)),IF(NOT(ISBLANK($N97)),$N97/$K97,$I97/$K97),0),0) -> 4000 | AH97: =SUM(AE97:AG97) -> 12000 | AI97: =SUM(V97,Z97,AD97,AH97) -> 36000 | AJ97: 13/02/2026: Projeto de kaizen número 15 de 2026. | AM97: =N97*AL97 -> 0 | AN97: =C97 -> 22 - Aproveitamento de Retalho do corte laser - MB002316LA_MB003533LA_MB003673LC | AO97: P | AP97: {=IF(OR(AN97="",AN97=0),"",IF(SUMPRODUCT(($C$55:$C$175=AN97)*(S$54:$AG$54<EOMONTH(TODAY(),-1)+1)*(ISNUMBER(S$55:$AG$175)),S$55:$AG$175)=0,"",SUMPRODUCT(($C$55:$C$175=AN97)*(S$54:$AG$54<EOMONTH(TODAY(),-1)+1)*(ISNUMBER(S$55:$AG$175)),S$55:$AG$175)))} -> 8000
Q98: Real | R98: 1 | V98: =SUM(S98:U98) -> 0 | Z98: =SUM(W98:Y98) -> 0 | AD98: =SUM(AA98:AC98) -> 0 | AH98: =SUM(AE98:AG98) -> 0 | AI98: =SUM(V98,Z98,AD98,AH98) -> 0 | AN98: =C97 -> 22 - Aproveitamento de Retalho do corte laser - MB002316LA_MB003533LA_MB003673LC | AO98: R | AP98: {=IF(OR(AN98="",AN98=0),"",IF(SUMPRODUCT(($C$55:$C$175=AN98)*($S$54:AG$54<=TODAY())*(ISNUMBER($S$56:AG$176)),$S$56:AG$176)=0,"",SUMPRODUCT(($C$55:$C$175=AN98)*($S$54:AG$54<=TODAY())*(ISNUMBER($S$56:AG$176)),$S$56:AG$176)))}
A99: BSW | B99: VA | C99: 23 - Redução do peso bruto VW000581Z / VW000582Z | D99: \\192.168.0.20\DEPARTAMENTOS\\Engenharia\0. Kaizen Diadema\6. 2026\02 Fevereiro\16 - VW000581Z_VW000582Z - Bruno Manachini\16 - KAIZEN - Redução do peso bruto VW000581Z VW000582Z_Rev00_B. Manachini.xlsx | E99: Reduzir o blank de 840mm para 820mm (passo). | F99: B. Manachini | G99: 46069 | H99: 46111 | I99: 270000 | J99: 46174 | K99: =IF(J99="", "", 12 - MONTH(J99) + 1) -> 7 | M99: OK | N99: 128107.04 | O99: ⏳ Em Execução | P99: 0.8 | Q99: Previsto | R99: 0.2 | S99: =IFERROR(IF(AND(S$54>=EOMONTH($J99,-1)+1,S$54<=EOMONTH(EOMONTH($J99,-1)+1,$K99-1)),IF(NOT(ISBLANK($N99)),$N99/$K99,$I99/$K99),0),0) -> 0 | T99: =IFERROR(IF(AND(T$54>=EOMONTH($J99,-1)+1,T$54<=EOMONTH(EOMONTH($J99,-1)+1,$K99-1)),IF(NOT(ISBLANK($N99)),$N99/$K99,$I99/$K99),0),0) -> 0 | U99: =IFERROR(IF(AND(U$54>=EOMONTH($J99,-1)+1,U$54<=EOMONTH(EOMONTH($J99,-1)+1,$K99-1)),IF(NOT(ISBLANK($N99)),$N99/$K99,$I99/$K99),0),0) -> 0 | V99: =SUM(S99:U99) -> 0 | W99: =IFERROR(IF(AND(W$54>=EOMONTH($J99,-1)+1,W$54<=EOMONTH(EOMONTH($J99,-1)+1,$K99-1)),IF(NOT(ISBLANK($N99)),$N99/$K99,$I99/$K99),0),0) -> 0 | X99: =IFERROR(IF(AND(X$54>=EOMONTH($J99,-1)+1,X$54<=EOMONTH(EOMONTH($J99,-1)+1,$K99-1)),IF(NOT(ISBLANK($N99)),$N99/$K99,$I99/$K99),0),0) -> 0 | Y99: =IFERROR(IF(AND(Y$54>=EOMONTH($J99,-1)+1,Y$54<=EOMONTH(EOMONTH($J99,-1)+1,$K99-1)),IF(NOT(ISBLANK($N99)),$N99/$K99,$I99/$K99),0),0) -> 18301.006 | Z99: =SUM(W99:Y99) -> 18301.006 | AA99: =IFERROR(IF(AND(AA$54>=EOMONTH($J99,-1)+1,AA$54<=EOMONTH(EOMONTH($J99,-1)+1,$K99-1)),IF(NOT(ISBLANK($N99)),$N99/$K99,$I99/$K99),0),0) -> 18301.006 | AB99: =IFERROR(IF(AND(AB$54>=EOMONTH($J99,-1)+1,AB$54<=EOMONTH(EOMONTH($J99,-1)+1,$K99-1)),IF(NOT(ISBLANK($N99)),$N99/$K99,$I99/$K99),0),0) -> 18301.006 | AC99: =IFERROR(IF(AND(AC$54>=EOMONTH($J99,-1)+1,AC$54<=EOMONTH(EOMONTH($J99,-1)+1,$K99-1)),IF(NOT(ISBLANK($N99)),$N99/$K99,$I99/$K99),0),0) -> 18301.006 | AD99: =SUM(AA99:AC99) -> 54903.017 | AE99: =IFERROR(IF(AND(AE$54>=EOMONTH($J99,-1)+1,AE$54<=EOMONTH(EOMONTH($J99,-1)+1,$K99-1)),IF(NOT(ISBLANK($N99)),$N99/$K99,$I99/$K99),0),0) -> 18301.006 | AF99: =IFERROR(IF(AND(AF$54>=EOMONTH($J99,-1)+1,AF$54<=EOMONTH(EOMONTH($J99,-1)+1,$K99-1)),IF(NOT(ISBLANK($N99)),$N99/$K99,$I99/$K99),0),0) -> 18301.006 | AG99: =IFERROR(IF(AND(AG$54>=EOMONTH($J99,-1)+1,AG$54<=EOMONTH(EOMONTH($J99,-1)+1,$K99-1)),IF(NOT(ISBLANK($N99)),$N99/$K99,$I99/$K99),0),0) -> 18301.006 | AH99: =SUM(AE99:AG99) -> 54903.017 | AI99: =SUM(V99,Z99,AD99,AH99) -> 128107.04 | AJ99: 17/02/2026: Projeto de kaizen número 16 de 2026. Enviado 16/02/2026 para validação da Controladoria. | AM99: =N99*AL99 -> 0 | AN99: =C99 -> 23 - Redução do peso bruto VW000581Z / VW000582Z | AO99: P | AP99: {=IF(OR(AN99="",AN99=0),"",IF(SUMPRODUCT(($C$55:$C$175=AN99)*(S$54:$AG$54<EOMONTH(TODAY(),-1)+1)*(ISNUMBER(S$55:$AG$175)),S$55:$AG$175)=0,"",SUMPRODUCT(($C$55:$C$175=AN99)*(S$54:$AG$54<EOMONTH(TODAY(),-1)+1)*(ISNUMBER(S$55:$AG$175)),S$55:$AG$175)))}
Q100: Real | R100: 0.25 | V100: =SUM(S100:U100) -> 0 | Z100: =SUM(W100:Y100) -> 0 | AD100: =SUM(AA100:AC100) -> 0 | AH100: =SUM(AE100:AG100) -> 0 | AI100: =SUM(V100,Z100,AD100,AH100) -> 0 | AJ100: >> Custos - validado, considerando volume de Março a Dezembro. | AN100: =C99 -> 23 - Redução do peso bruto VW000581Z / VW000582Z | AO100: R | AP100: {=IF(OR(AN100="",AN100=0),"",IF(SUMPRODUCT(($C$55:$C$175=AN100)*($S$54:AG$54<=TODAY())*(ISNUMBER($S$56:AG$176)),$S$56:AG$176)=0,"",SUMPRODUCT(($C$55:$C$175=AN100)*($S$54:AG$54<=TODAY())*(ISNUMBER($S$56:AG$176)),$S$56:AG$176)))}
A101: BSW | B101: VA | C101: 24 - KAIZEN - Redução de peso bruto_MB002289LA_MB002290LA_Rev00_Bruno Manachini | D101: \\192.168.0.20\DEPARTAMENTOS\Engenharia\0. Kaizen Diadema\6. 2026\02 Fevereiro\20 - MB002289LA_MB002290LA - Bruno Manachini_Engenharia\20 - KAIZEN - Redução de peso bruto_MB002289LA_MB002290LA_Rev00_Bruno Manachini.xlsx | E101: Redução de 146g do peso bruto por peça (comprimento de 1540 para 2690) | F101: B. Manachini | G101: 46076 | H101: 46122 | I101: 33600 | J101: 46143 | K101: =IF(J101="", "", 12 - MONTH(J101) + 1) -> 8 | M101: OK | N101: 29532.29 | O101: ✓ Concluído | P101: 0.8 | Q101: Previsto | R101: 1 | S101: =IFERROR(IF(AND(S$54>=EOMONTH($J101,-1)+1,S$54<=EOMONTH(EOMONTH($J101,-1)+1,$K101-1)),IF(NOT(ISBLANK($N101)),$N101/$K101,$I101/$K101),0),0) -> 0 | T101: =IFERROR(IF(AND(T$54>=EOMONTH($J101,-1)+1,T$54<=EOMONTH(EOMONTH($J101,-1)+1,$K101-1)),IF(NOT(ISBLANK($N101)),$N101/$K101,$I101/$K101),0),0) -> 0 | U101: =IFERROR(IF(AND(U$54>=EOMONTH($J101,-1)+1,U$54<=EOMONTH(EOMONTH($J101,-1)+1,$K101-1)),IF(NOT(ISBLANK($N101)),$N101/$K101,$I101/$K101),0),0) -> 0 | V101: =SUM(S101:U101) -> 0 | W101: =IFERROR(IF(AND(W$54>=EOMONTH($J101,-1)+1,W$54<=EOMONTH(EOMONTH($J101,-1)+1,$K101-1)),IF(NOT(ISBLANK($N101)),$N101/$K101,$I101/$K101),0),0) -> 0 | X101: =IFERROR(IF(AND(X$54>=EOMONTH($J101,-1)+1,X$54<=EOMONTH(EOMONTH($J101,-1)+1,$K101-1)),IF(NOT(ISBLANK($N101)),$N101/$K101,$I101/$K101),0),0) -> 3691.5363 | Y101: =IFERROR(IF(AND(Y$54>=EOMONTH($J101,-1)+1,Y$54<=EOMONTH(EOMONTH($J101,-1)+1,$K101-1)),IF(NOT(ISBLANK($N101)),$N101/$K101,$I101/$K101),0),0) -> 3691.5363 | Z101: =SUM(W101:Y101) -> 7383.0725 | AA101: =IFERROR(IF(AND(AA$54>=EOMONTH($J101,-1)+1,AA$54<=EOMONTH(EOMONTH($J101,-1)+1,$K101-1)),IF(NOT(ISBLANK($N101)),$N101/$K101,$I101/$K101),0),0) -> 3691.5363 | AB101: =IFERROR(IF(AND(AB$54>=EOMONTH($J101,-1)+1,AB$54<=EOMONTH(EOMONTH($J101,-1)+1,$K101-1)),IF(NOT(ISBLANK($N101)),$N101/$K101,$I101/$K101),0),0) -> 3691.5363 | AC101: =IFERROR(IF(AND(AC$54>=EOMONTH($J101,-1)+1,AC$54<=EOMONTH(EOMONTH($J101,-1)+1,$K101-1)),IF(NOT(ISBLANK($N101)),$N101/$K101,$I101/$K101),0),0) -> 3691.5363 | AD101: =SUM(AA101:AC101) -> 11074.609 | AE101: =IFERROR(IF(AND(AE$54>=EOMONTH($J101,-1)+1,AE$54<=EOMONTH(EOMONTH($J101,-1)+1,$K101-1)),IF(NOT(ISBLANK($N101)),$N101/$K101,$I101/$K101),0),0) -> 3691.5363 | AF101: =IFERROR(IF(AND(AF$54>=EOMONTH($J101,-1)+1,AF$54<=EOMONTH(EOMONTH($J101,-1)+1,$K101-1)),IF(NOT(ISBLANK($N101)),$N101/$K101,$I101/$K101),0),0) -> 3691.5363 | AG101: =IFERROR(IF(AND(AG$54>=EOMONTH($J101,-1)+1,AG$54<=EOMONTH(EOMONTH($J101,-1)+1,$K101-1)),IF(NOT(ISBLANK($N101)),$N101/$K101,$I101/$K101),0),0) -> 3691.5363 | AH101: =SUM(AE101:AG101) -> 11074.609 | AI101: =SUM(V101,Z101,AD101,AH101) -> 29532.29 | AJ101: 24/02/2026: Projeto de kaizen número 20 de 2026. Enviado 23/02/2026 para validação da Controladoria. --> Aguardando confirmação de algumas informações (email enviado 11/03) | AM101: =N101*AL101 -> 0 | AN101: =C101 -> 24 - KAIZEN - Redução de peso bruto_MB002289LA_MB002290LA_Rev00_Bruno Manachini | AO101: P | AP101: {=IF(OR(AN101="",AN101=0),"",IF(SUMPRODUCT(($C$55:$C$175=AN101)*(S$54:$AG$54<EOMONTH(TODAY(),-1)+1)*(ISNUMBER(S$55:$AG$175)),S$55:$AG$175)=0,"",SUMPRODUCT(($C$55:$C$175=AN101)*(S$54:$AG$54<EOMONTH(TODAY(),-1)+1)*(ISNUMBER(S$55:$AG$175)),S$55:$AG$175)))} -> 3691.5363
Q102: Real | R102: 1 | V102: =SUM(S102:U102) -> 0 | X102: 3320.2091 | Z102: =SUM(W102:Y102) -> 3320.2091 | AD102: =SUM(AA102:AC102) -> 0 | AH102: =SUM(AE102:AG102) -> 0 | AI102: =SUM(V102,Z102,AD102,AH102) -> 3320.2091 | AJ102: -> Aguardando confirmação de algumas informações - email enviado em 11/03. | AN102: =C101 -> 24 - KAIZEN - Redução de peso bruto_MB002289LA_MB002290LA_Rev00_Bruno Manachini | AO102: R | AP102: {=IF(OR(AN102="",AN102=0),"",IF(SUMPRODUCT(($C$55:$C$175=AN102)*($S$54:AG$54<=TODAY())*(ISNUMBER($S$56:AG$176)),$S$56:AG$176)=0,"",SUMPRODUCT(($C$55:$C$175=AN102)*($S$54:AG$54<=TODAY())*(ISNUMBER($S$56:AG$176)),$S$56:AG$176)))} -> 3320.2091
...

Sheet Jarinu
A1: DASHBOARD EXECUTIVO - UNIDADE JARINU
A2: Gestão Estratégica de Projetos e Redução de Custos | Grupo Delga | 2026
A4: META DA UNIDADE | B4: RETORNO PREVISTO (Total) | C4: PREVISTO 2026 | E4: 💰 RETORNO VALIDADO | G4: 💰 RETORNO REAL | J4: % ATINGIMENTO DA META | L4: INICIATIVAS | O4: TOP 20 Raking de Projetos Valorizados
A5: =Parâmetros!E8 -> 5356000 | B5: =SUM(I55:I128) -> 3919443 | C5: =SUMIF(Q55:Q128,"Previsto",AI55:AI128) -> 2392012.2 | E5: =SUM(N55:N128) -> 2819031.8 | G5: =SUMIF(Q55:Q128,"Real",AI55:AI128) -> 393297.17 | J5: =G5/A5 -> 0.073431137 | L5: =SUM(I9:I11) -> 34 | O5: POS | P5: Tipo | Q5: Valor Previsto | R5: Valor Previsto Custos | S5: Retorno Previsto | T5: Retorno Real até hoje | U5: Projetos | Z5: Peso | AA5: Pareto | AB5: % Previsto | AC5: % Real | AD5: Planejado | AE5: % Responsabilidade Delga
O6: {=_xlfn.SEQUENCE(20)} -> 1 | P6: =_xlfn.XLOOKUP(U6,$C$55:$C$128,$A$55:$A$128) -> BSW | Q6: =MAX(I55:I128) -> 1063359 | R6: =_xlfn.XLOOKUP(Q6,$I$55:$I$128,$N$55:$N$128) -> 1145830.2 | S6: =_xlfn.XLOOKUP(U6,$B$55:$B$144,$I$55:$I$144) -> #N/A | T6: {=SUMPRODUCT(($B$55:$B$143=U6)*(S$54:$AG$54<=TODAY())*(ISNUMBER(R$56:$AF$144)),R$56:$AF$144)} -> #REF! | U6: =IFERROR(HYPERLINK(INDEX($D$55:$D$128,MATCH(Q6,$I$55:$I$128,0)),INDEX($C$55:$C$128,MATCH(Q6,$I$55:$I$128,0)) ), "" ) -> 06 - Redução consumo MTP aplicando tolerância mínima | Z6: =Q6/$C$5 -> 0.44454581 | AA6: =Pareto!E70 -> 0.2713036 | AB6: {=IFERROR(INDEX($R$55:$R$128,MATCH(1,($AN$55:$AN$128=U6)*($Q$55:$Q$128="Previsto"), 0) ), "")} -> 0.32939189 | AC6: 0.29 | AD6: =IF(OR(AB6="",AC6=""),"",IF(AC6=100%,"CONCLUÍDO",IF(AC6=0,IF(AB6=0,"PROJETO NÃO INICIADO","FALTA DE ACOMPANHAMENTO"),IF(AC6>AB6,"ADIANTADO",IF(AC6=AB6,"CONFORME PLANEJADO","ATRASO"))))) -> ATRASO | AE6: {=_xlfn.XLOOKUP($U$6:$U$24,$C$55:$C$128,$P$55:$P$128)} -> 0.1
A7: 📊 SAVING PREVISTO POR PILAR | H7: 📋 STATUS DAS INICIATIVAS | K7: 🏭 INDICADORES OPERACIONAIS | O7: 2 | P7: =_xlfn.XLOOKUP(U7,$C$55:$C$128,$A$55:$A$128) -> BSW | Q7: =IFERROR(LARGE($I$55:$I$128,O7)," ") -> 513721 | R7: =_xlfn.XLOOKUP(Q7,$I$55:$I$128,$N$55:$N$128) -> 0 | S7: =_xlfn.XLOOKUP(U7,$B$55:$B$144,$I$55:$I$144) -> #N/A | T7: {=SUMPRODUCT(($B$55:$B$143=U7)*(S$54:$AG$54<=TODAY())*(ISNUMBER(R$56:$AF$144)),R$56:$AF$144)} -> #REF! | U7: =IFERROR(HYPERLINK(INDEX($D$55:$D$128,MATCH(Q7,$I$55:$I$128,0)),INDEX($C$55:$C$128,MATCH(Q7,$I$55:$I$128,0)) ), "" ) -> 03 - Redução de consumo de MP dos blanks com a técnica de corte Wave | Z7: =Q7/$C$5 -> 0.21476521 | AA7: =Pareto!E71 -> 0.4023735 | AB7: {=IFERROR(INDEX($R$55:$R$128,MATCH(1,($AN$55:$AN$128=U7)*($Q$55:$Q$128="Previsto"), 0) ), "")} | AC7: {=IFERROR( INDEX($R$55:$R$128,MATCH(1,($AN$55:$AN$128=U7)*($Q$55:$Q$128="Real"),0)),"")} | AD7: =IF(OR(AB7="",AC7=""),"",IF(AC7=100%,"CONCLUÍDO",IF(AC7=0,IF(AB7=0,"PROJETO NÃO INICIADO","FALTA DE ACOMPANHAMENTO"),IF(AC7>AB7,"ADIANTADO",IF(AC7=AB7,"CONFORME PLANEJADO","ATRASO"))))) | AE7: 0.9
A8: Pilar | B8: Qtd. | C8: Saving (R$) | D8: Saving Validado 2026 | E8: % Total | F8: Barra | H8: Status | I8: Qtd. | J8: R$ Previsto | K8: Aderência SPD: Unidade | L8: Aderência SPD: Auditado | M8: Análise de Margem (Form 206) | O8: 3 | P8: =_xlfn.XLOOKUP(U8,$C$55:$C$128,$A$55:$A$128) -> BSW | Q8: =IFERROR(LARGE($I$55:$I$128,O8)," ") -> 435138 | R8: =_xlfn.XLOOKUP(Q8,$I$55:$I$128,$N$55:$N$128) -> 442663.07 | S8: =_xlfn.XLOOKUP(U8,$B$55:$B$144,$I$55:$I$144) -> #N/A | T8: {=SUMPRODUCT(($B$55:$B$143=U8)*(S$54:$AG$54<=TODAY())*(ISNUMBER(R$56:$AF$144)),R$56:$AF$144)} -> #REF! | U8: =IFERROR(HYPERLINK(INDEX($D$55:$D$128,MATCH(Q8,$I$55:$I$128,0)),INDEX($C$55:$C$128,MATCH(Q8,$I$55:$I$128,0)) ), "" ) -> 27 - Redução consumo MTP aplicando tolerância mínima curva B | Z8: =Q8/$C$5 -> 0.18191295 | AA8: =Pareto!E72 -> 0.51339387 | AB8: {=IFERROR(INDEX($R$55:$R$128,MATCH(1,($AN$55:$AN$128=U8)*($Q$55:$Q$128="Previsto"), 0) ), "")} -> 0.2 | AC8: {=IFERROR( INDEX($R$55:$R$128,MATCH(1,($AN$55:$AN$128=U8)*($Q$55:$Q$128="Real"),0)),"")} -> 0 | AD8: =IF(OR(AB8="",AC8=""),"",IF(AC8=100%,"CONCLUÍDO",IF(AC8=0,IF(AB8=0,"PROJETO NÃO INICIADO","FALTA DE ACOMPANHAMENTO"),IF(AC8>AB8,"ADIANTADO",IF(AC8=AB8,"CONFORME PLANEJADO","ATRASO"))))) -> FALTA DE ACOMPANHAMENTO | AE8: 0
A9: Kaizen | B9: =COUNTIF($A$55:$A$128,A9) -> 4 | C9: =SUMIF($A$55:$A$128,A9,$I$55:$I$128) -> 731000 | D9: =SUMIF($A$55:$A$128,A9,$N$55:$N$128) -> 390000 | E9: =IF($D$13=0,"",D9/$D$13) -> 0.13834537 | F9: =E9 -> 0.13834537 | H9: ✓ Concluído | I9: =COUNTIF($O$55:$O$128,H9) -> 7 | J9: =SUMIF($O$55:$O$128,H9,$I$55:$I$128) -> 414120 | O9: 4 | P9: =_xlfn.XLOOKUP(U9,$C$55:$C$128,$A$55:$A$128) -> Kaizen | Q9: =IFERROR(LARGE($I$55:$I$128,O9)," ") -> 390000 | R9: =_xlfn.XLOOKUP(Q9,$I$55:$I$128,$N$55:$N$128) -> 390000 | S9: =_xlfn.XLOOKUP(U9,$B$55:$B$144,$I$55:$I$144) -> #N/A | T9: {=SUMPRODUCT(($B$55:$B$143=U9)*(S$54:$AG$54<=TODAY())*(ISNUMBER(R$56:$AF$144)),R$56:$AF$144)} -> #REF! | U9: =IFERROR(HYPERLINK(INDEX($D$55:$D$128,MATCH(Q9,$I$55:$I$128,0)),INDEX($C$55:$C$128,MATCH(Q9,$I$55:$I$128,0)) ), "" ) -> 36 - Venda Robos | Z9: =Q9/$C$5 -> 0.16304265 | AA9: =Pareto!E73 -> 0.6128978 | AB9: {=IFERROR(INDEX($R$55:$R$128,MATCH(1,($AN$55:$AN$128=U9)*($Q$55:$Q$128="Previsto"), 0) ), "")} -> 1 | AC9: {=IFERROR( INDEX($R$55:$R$128,MATCH(1,($AN$55:$AN$128=U9)*($Q$55:$Q$128="Real"),0)),"")} -> 1 | AD9: =IF(OR(AB9="",AC9=""),"",IF(AC9=100%,"CONCLUÍDO",IF(AC9=0,IF(AB9=0,"PROJETO NÃO INICIADO","FALTA DE ACOMPANHAMENTO"),IF(AC9>AB9,"ADIANTADO",IF(AC9=AB9,"CONFORME PLANEJADO","ATRASO"))))) -> CONCLUÍDO | AE9: 0
A10: Redução de Custo | B10: =COUNTIF($A$55:$A$128,A10) -> 19 | C10: =SUMIF($A$55:$A$128,A10,$I$55:$I$128) -> 466969 | D10: =SUMIF($A$55:$A$128,A10,$N$55:$N$128) -> 549981.18 | E10: =IF($D$13=0,"",D10/$D$13) -> 0.19509577 | F10: =E10 -> 0.19509577 | H10: ⏳ Em Execução | I10: =COUNTIF($O$55:$O$128,H10) -> 23 | J10: =SUMIF($O$55:$O$128,H10,$I$55:$I$128) -> 3403113 | K10: =E159 -> 0.71428571 | L10: =F159 -> 0.42857143 | M10: =L154 -> 0.43333333 | O10: 5 | P10: =_xlfn.XLOOKUP(U10,$C$55:$C$128,$A$55:$A$128) -> BSW | Q10: =IFERROR(LARGE($I$55:$I$128,O10)," ") -> 308498 | R10: =_xlfn.XLOOKUP(Q10,$I$55:$I$128,$N$55:$N$128) -> 209476.06 | S10: =_xlfn.XLOOKUP(U10,$B$55:$B$144,$I$55:$I$144) -> #N/A | T10: {=SUMPRODUCT(($B$55:$B$143=U10)*(S$54:$AG$54<=TODAY())*(ISNUMBER(R$56:$AF$144)),R$56:$AF$144)} -> #REF! | U10: =IFERROR(HYPERLINK(INDEX($D$55:$D$128,MATCH(Q10,$I$55:$I$128,0)),INDEX($C$55:$C$128,MATCH(Q10,$I$55:$I$128,0)) ), "" ) -> 28 - Redução consumo MTP aplicando tolerância mínima curva C | Z10: =Q10/$C$5 -> 0.12897008 | AA10: =Pareto!E74 -> 0.69160746 | AB10: {=IFERROR(INDEX($R$55:$R$128,MATCH(1,($AN$55:$AN$128=U10)*($Q$55:$Q$128="Previsto"), 0) ), "")} -> 0.2 | AC10: {=IFERROR( INDEX($R$55:$R$128,MATCH(1,($AN$55:$AN$128=U10)*($Q$55:$Q$128="Real"),0)),"")} -> 0.21052632 | AD10: =IF(OR(AB10="",AC10=""),"",IF(AC10=100%,"CONCLUÍDO",IF(AC10=0,IF(AB10=0,"PROJETO NÃO INICIADO","FALTA DE ACOMPANHAMENTO"),IF(AC10>AB10,"ADIANTADO",IF(AC10=AB10,"CONFORME PLANEJADO","ATRASO"))))) -> ADIANTADO | AE10: 0
A11: Você Resolve | B11: =COUNTIF($A$55:$A$128,A11) -> 1 | C11: =SUMIF($A$55:$A$128,A11,$I$55:$I$128) -> 0 | D11: =SUMIF($A$55:$A$128,A11,$N$55:$N$128) -> 0 | E11: =IF($D$13=0,"",D11/$D$13) -> 0 | F11: =E11 -> 0 | H11: 📝 Não iniciado | I11: =COUNTIF($O$55:$O$128,H11) -> 4 | J11: =SUMIF($O$55:$O$128,H11,$I$55:$I$128) -> 0 | O11: 6 | P11: =_xlfn.XLOOKUP(U11,$C$55:$C$128,$A$55:$A$128) -> Redução de custo | Q11: =IFERROR(LARGE($I$55:$I$128,O11)," ") -> 306000 | R11: =_xlfn.XLOOKUP(Q11,$I$55:$I$128,$N$55:$N$128) -> 306000 | S11: =_xlfn.XLOOKUP(U11,$B$55:$B$144,$I$55:$I$144) -> #N/A | T11: {=SUMPRODUCT(($B$55:$B$143=U11)*(S$54:$AG$54<=TODAY())*(ISNUMBER(R$56:$AF$144)),R$56:$AF$144)} -> #REF! | U11: =IFERROR(HYPERLINK(INDEX($D$55:$D$128,MATCH(Q11,$I$55:$I$128,0)),INDEX($C$55:$C$128,MATCH(Q11,$I$55:$I$128,0)) ), "" ) -> 30 - Redução de Refugo | Z11: =Q11/$C$5 -> 0.12792577 | AA11: =Pareto!E75 -> 0.76967977 | AB11: {=IFERROR(INDEX($R$55:$R$128,MATCH(1,($AN$55:$AN$128=U11)*($Q$55:$Q$128="Previsto"), 0) ), "")} -> 0.8 | AC11: {=IFERROR( INDEX($R$55:$R$128,MATCH(1,($AN$55:$AN$128=U11)*($Q$55:$Q$128="Real"),0)),"")} -> 0.8 | AD11: =IF(OR(AB11="",AC11=""),"",IF(AC11=100%,"CONCLUÍDO",IF(AC11=0,IF(AB11=0,"PROJETO NÃO INICIADO","FALTA DE ACOMPANHAMENTO"),IF(AC11>AB11,"ADIANTADO",IF(AC11=AB11,"CONFORME PLANEJADO","ATRASO"))))) -> CONFORME PLANEJADO | AE11: 0
A12: BSW | B12: =COUNTIF($A$55:$A$128,A12) -> 13 | C12: =SUMIF($A$55:$A$128,A12,$I$55:$I$128) -> 2721474 | D12: =SUMIF($A$55:$A$128,A12,$N$55:$N$128) -> 1879050.6 | E12: =IF($D$13=0,"",D12/$D$13) -> 0.66655886 | F12: =E12 -> 0.66655886 | O12: 7 | P12: =_xlfn.XLOOKUP(U12,$C$55:$C$128,$A$55:$A$128) -> Kaizen | Q12: =IFERROR(LARGE($I$55:$I$128,O12)," ") -> 301000 | R12: =_xlfn.XLOOKUP(Q12,$I$55:$I$128,$N$55:$N$128) -> 0 | S12: =_xlfn.XLOOKUP(U12,$B$55:$B$144,$I$55:$I$144) -> #N/A | T12: {=SUMPRODUCT(($B$55:$B$143=U12)*(S$54:$AG$54<=TODAY())*(ISNUMBER(R$56:$AF$144)),R$56:$AF$144)} -> #REF! | U12: =IFERROR(HYPERLINK(INDEX($D$55:$D$128,MATCH(Q12,$I$55:$I$128,0)),INDEX($C$55:$C$128,MATCH(Q12,$I$55:$I$128,0)) ), "" ) -> 32 - Empilhadeiras Elétricas | Z12: =Q12/$C$5 -> 0.12583548 | AA12: =Pareto!E76 -> 0.8464764 | AB12: {=IFERROR(INDEX($R$55:$R$128,MATCH(1,($AN$55:$AN$128=U12)*($Q$55:$Q$128="Previsto"), 0) ), "")} -> 0.92307692 | AC12: {=IFERROR( INDEX($R$55:$R$128,MATCH(1,($AN$55:$AN$128=U12)*($Q$55:$Q$128="Real"),0)),"")} -> 0 | AD12: =IF(OR(AB12="",AC12=""),"",IF(AC12=100%,"CONCLUÍDO",IF(AC12=0,IF(AB12=0,"PROJETO NÃO INICIADO","FALTA DE ACOMPANHAMENTO"),IF(AC12>AB12,"ADIANTADO",IF(AC12=AB12,"CONFORME PLANEJADO","ATRASO"))))) -> FALTA DE ACOMPANHAMENTO | AE12: 0
A13: TOTAL | B13: =SUM(B9:B12) -> 37 | C13: =SUM(C9:C12) -> 3919443 | D13: =SUM(D9:D12) -> 2819031.8 | E13: =SUM(E9:E12) -> 1 | O13: 8 | P13: =_xlfn.XLOOKUP(U13,$C$55:$C$128,$A$55:$A$128) -> BSW | Q13: =IFERROR(LARGE($I$55:$I$128,O13)," ") -> 102967 | R13: =_xlfn.XLOOKUP(Q13,$I$55:$I$128,$N$55:$N$128) -> 0 | S13: =_xlfn.XLOOKUP(U13,$B$55:$B$144,$I$55:$I$144) -> #N/A | T13: {=SUMPRODUCT(($B$55:$B$143=U13)*(S$54:$AG$54<=TODAY())*(ISNUMBER(R$56:$AF$144)),R$56:$AF$144)} -> #REF! | U13: =IFERROR(HYPERLINK(INDEX($D$55:$D$128,MATCH(Q13,$I$55:$I$128,0)),INDEX($C$55:$C$128,MATCH(Q13,$I$55:$I$128,0)) ), "" ) -> 19 - Redução da largura da bobina mãe do Curvão | Z13: =Q13/$C$5 -> 0.043046185 | AA13: =Pareto!E77 -> 0.87274722 | AB13: {=IFERROR(INDEX($R$55:$R$128,MATCH(1,($AN$55:$AN$128=U13)*($Q$55:$Q$128="Previsto"), 0) ), "")} -> 0 | AC13: {=IFERROR( INDEX($R$55:$R$128,MATCH(1,($AN$55:$AN$128=U13)*($Q$55:$Q$128="Real"),0)),"")} -> 0 | AD13: =IF(OR(AB13="",AC13=""),"",IF(AC13=100%,"CONCLUÍDO",IF(AC13=0,IF(AB13=0,"PROJETO NÃO INICIADO","FALTA DE ACOMPANHAMENTO"),IF(AC13>AB13,"ADIANTADO",IF(AC13=AB13,"CONFORME PLANEJADO","ATRASO"))))) -> PROJETO NÃO INICIADO | AE13: 0.5
H14: ; | O14: 9 | P14: =_xlfn.XLOOKUP(U14,$C$55:$C$128,$A$55:$A$128) -> BSW | Q14: =IFERROR(LARGE($I$55:$I$128,O14)," ") -> 91444 | R14: =_xlfn.XLOOKUP(Q14,$I$55:$I$128,$N$55:$N$128) -> 0 | S14: =_xlfn.XLOOKUP(U14,$B$55:$B$144,$I$55:$I$144) -> #N/A | T14: {=SUMPRODUCT(($B$55:$B$143=U14)*(S$54:$AG$54<=TODAY())*(ISNUMBER(R$56:$AF$144)),R$56:$AF$144)} -> #REF! | U14: =IFERROR(HYPERLINK(INDEX($D$55:$D$128,MATCH(Q14,$I$55:$I$128,0)),INDEX($C$55:$C$128,MATCH(Q14,$I$55:$I$128,0)) ), "" ) -> 05 - Aplicar borda aparadas nas bobinas | Z14: =Q14/$C$5 -> 0.038228902 | AA14: =Pareto!E78 -> 0.89607809 | AB14: {=IFERROR(INDEX($R$55:$R$128,MATCH(1,($AN$55:$AN$128=U14)*($Q$55:$Q$128="Previsto"), 0) ), "")} -> 0.41666667 | AC14: {=IFERROR( INDEX($R$55:$R$128,MATCH(1,($AN$55:$AN$128=U14)*($Q$55:$Q$128="Real"),0)),"")} -> 0.33333333 | AD14: =IF(OR(AB14="",AC14=""),"",IF(AC14=100%,"CONCLUÍDO",IF(AC14=0,IF(AB14=0,"PROJETO NÃO INICIADO","FALTA DE ACOMPANHAMENTO"),IF(AC14>AB14,"ADIANTADO",IF(AC14=AB14,"CONFORME PLANEJADO","ATRASO"))))) -> ATRASO | AE14: 0.8
F15: VA | G15: =SUMIF($B$55:$B$176,F15,$N$55:$N$176) -> 1879050.6 | O15: 10 | P15: =_xlfn.XLOOKUP(U15,$C$55:$C$128,$A$55:$A$128) -> Redução de custo | Q15: =IFERROR(LARGE($I$55:$I$128,O15)," ") -> 90850 | R15: =_xlfn.XLOOKUP(Q15,$I$55:$I$128,$N$55:$N$128) -> 165883.52 | S15: =_xlfn.XLOOKUP(U15,$B$55:$B$144,$I$55:$I$144) -> #N/A | T15: {=SUMPRODUCT(($B$55:$B$143=U15)*(S$54:$AG$54<=TODAY())*(ISNUMBER(R$56:$AF$144)),R$56:$AF$144)} -> #REF! | U15: =IFERROR(HYPERLINK(INDEX($D$55:$D$128,MATCH(Q15,$I$55:$I$128,0)),INDEX($C$55:$C$128,MATCH(Q15,$I$55:$I$128,0)) ), "" ) -> 24 - Redução de consumo de MTP China 1 porca (-10 mm) | Z15: =Q15/$C$5 -> 0.037980576 | AA15: =Pareto!E79 -> 0.9192574 | AB15: {=IFERROR(INDEX($R$55:$R$128,MATCH(1,($AN$55:$AN$128=U15)*($Q$55:$Q$128="Previsto"), 0) ), "")} -> 0.875 | AC15: {=IFERROR( INDEX($R$55:$R$128,MATCH(1,($AN$55:$AN$128=U15)*($Q$55:$Q$128="Real"),0)),"")} -> 0 | AD15: =IF(OR(AB15="",AC15=""),"",IF(AC15=100%,"CONCLUÍDO",IF(AC15=0,IF(AB15=0,"PROJETO NÃO INICIADO","FALTA DE ACOMPANHAMENTO"),IF(AC15>AB15,"ADIANTADO",IF(AC15=AB15,"CONFORME PLANEJADO","ATRASO"))))) -> FALTA DE ACOMPANHAMENTO | AE15: 0
F16: GGF | G16: =SUMIF($B$55:$B$176,F16,$N$55:$N$176) -> 549981.18 | O16: 11 | P16: =_xlfn.XLOOKUP(U16,$C$55:$C$128,$A$55:$A$128) -> BSW | Q16: =IFERROR(LARGE($I$55:$I$128,O16)," ") -> 75733 | R16: =_xlfn.XLOOKUP(Q16,$I$55:$I$128,$N$55:$N$128) -> 0 | S16: =_xlfn.XLOOKUP(U16,$B$55:$B$144,$I$55:$I$144) -> #N/A | T16: {=SUMPRODUCT(($B$55:$B$143=U16)*(S$54:$AG$54<=TODAY())*(ISNUMBER(R$56:$AF$144)),R$56:$AF$144)} -> #REF! | U16: =IFERROR(HYPERLINK(INDEX($D$55:$D$128,MATCH(Q16,$I$55:$I$128,0)),INDEX($C$55:$C$128,MATCH(Q16,$I$55:$I$128,0)) ), "" ) -> 04 - Redução da largura dos slitters | Z16: =Q16/$C$5 -> 0.031660792 | AA16: =Pareto!E80 -> 0.93857979 | AB16: {=IFERROR(INDEX($R$55:$R$128,MATCH(1,($AN$55:$AN$128=U16)*($Q$55:$Q$128="Previsto"), 0) ), "")} -> 0.4 | AC16: {=IFERROR( INDEX($R$55:$R$128,MATCH(1,($AN$55:$AN$128=U16)*($Q$55:$Q$128="Real"),0)),"")} -> 0.4 | AD16: =IF(OR(AB16="",AC16=""),"",IF(AC16=100%,"CONCLUÍDO",IF(AC16=0,IF(AB16=0,"PROJETO NÃO INICIADO","FALTA DE ACOMPANHAMENTO"),IF(AC16>AB16,"ADIANTADO",IF(AC16=AB16,"CONFORME PLANEJADO","ATRASO"))))) -> CONFORME PLANEJADO | AE16: 0.5
F17: MA | G17: =SUMIF($B$55:$B$176,F17,$N$55:$N$176) -> 0 | O17: 12 | P17: =_xlfn.XLOOKUP(U17,$C$55:$C$128,$A$55:$A$128) -> BSW | Q17: =IFERROR(LARGE($I$55:$I$128,O17)," ") -> 62210 | R17: =_xlfn.XLOOKUP(Q17,$I$55:$I$128,$N$55:$N$128) -> 0 | S17: =_xlfn.XLOOKUP(U17,$B$55:$B$144,$I$55:$I$144) -> #N/A | T17: {=SUMPRODUCT(($B$55:$B$143=U17)*(S$54:$AG$54<=TODAY())*(ISNUMBER(R$56:$AF$144)),R$56:$AF$144)} -> #REF! | U17: =IFERROR(HYPERLINK(INDEX($D$55:$D$128,MATCH(Q17,$I$55:$I$128,0)),INDEX($C$55:$C$128,MATCH(Q17,$I$55:$I$128,0)) ), "" ) -> 40 - Redução de disperdicio bobina. | Z17: =Q17/$C$5 -> 0.026007393 | AA17: =Pareto!E81 -> 0.95445195 | AB17: {=IFERROR(INDEX($R$55:$R$128,MATCH(1,($AN$55:$AN$128=U17)*($Q$55:$Q$128="Previsto"), 0) ), "")} -> 0 | AC17: 0.9 | AD17: =IF(OR(AB17="",AC17=""),"",IF(AC17=100%,"CONCLUÍDO",IF(AC17=0,IF(AB17=0,"PROJETO NÃO INICIADO","FALTA DE ACOMPANHAMENTO"),IF(AC17>AB17,"ADIANTADO",IF(AC17=AB17,"CONFORME PLANEJADO","ATRASO"))))) -> ADIANTADO | AE17: 0
F18: Outros | G18: =SUMIF($B$55:$B$176,F18,$N$55:$N$176) -> 390000 | O18: 13 | P18: =_xlfn.XLOOKUP(U18,$C$55:$C$128,$A$55:$A$128) -> Redução de custo | Q18: =IFERROR(LARGE($I$55:$I$128,O18)," ") -> 47086 | R18: =_xlfn.XLOOKUP(Q18,$I$55:$I$128,$N$55:$N$128) -> 60984.11 | S18: =_xlfn.XLOOKUP(U18,$B$55:$B$144,$I$55:$I$144) -> #N/A | T18: {=SUMPRODUCT(($B$55:$B$143=U18)*(S$54:$AG$54<=TODAY())*(ISNUMBER(R$56:$AF$144)),R$56:$AF$144)} -> #REF! | U18: =IFERROR(HYPERLINK(INDEX($D$55:$D$128,MATCH(Q18,$I$55:$I$128,0)),INDEX($C$55:$C$128,MATCH(Q18,$I$55:$I$128,0)) ), "" ) -> 25 - Redução de consumo de MTP China 2 porca (-10 mm) | Z18: =Q18/$C$5 -> 0.019684682 | AA18: =Pareto!E82 -> 0.96646539 | AB18: {=IFERROR(INDEX($R$55:$R$128,MATCH(1,($AN$55:$AN$128=U18)*($Q$55:$Q$128="Previsto"), 0) ), "")} -> 0.66666667 | AC18: {=IFERROR( INDEX($R$55:$R$128,MATCH(1,($AN$55:$AN$128=U18)*($Q$55:$Q$128="Real"),0)),"")} -> 0 | AD18: =IF(OR(AB18="",AC18=""),"",IF(AC18=100%,"CONCLUÍDO",IF(AC18=0,IF(AB18=0,"PROJETO NÃO INICIADO","FALTA DE ACOMPANHAMENTO"),IF(AC18>AB18,"ADIANTADO",IF(AC18=AB18,"CONFORME PLANEJADO","ATRASO"))))) -> FALTA DE ACOMPANHAMENTO | AE18: 0
O19: 14 | P19: =_xlfn.XLOOKUP(U19,$C$55:$C$128,$A$55:$A$128) -> Kaizen | Q19: =IFERROR(LARGE($I$55:$I$128,O19)," ") -> 40000.001 | R19: =_xlfn.XLOOKUP(Q19,$I$55:$I$128,$N$55:$N$128) -> 0 | S19: =_xlfn.XLOOKUP(U19,$B$55:$B$144,$I$55:$I$144) -> #N/A | T19: {=SUMPRODUCT(($B$55:$B$143=U19)*(S$54:$AG$54<=TODAY())*(ISNUMBER(R$56:$AF$144)),R$56:$AF$144)} -> #REF! | U19: =IFERROR(HYPERLINK(INDEX($D$55:$D$128,MATCH(Q19,$I$55:$I$128,0)),INDEX($C$55:$C$128,MATCH(Q19,$I$55:$I$128,0)) ), "" ) -> 39 - Venda de sucata de cobre | Z19: =Q19/$C$5 -> 0.016722323 | AA19: =Pareto!E83 -> 0.97667092 | AB19: {=IFERROR(INDEX($R$55:$R$128,MATCH(1,($AN$55:$AN$128=U19)*($Q$55:$Q$128="Previsto"), 0) ), "")} -> 0 | AC19: {=IFERROR( INDEX($R$55:$R$128,MATCH(1,($AN$55:$AN$128=U19)*($Q$55:$Q$128="Real"),0)),"")} -> 0 | AD19: =IF(OR(AB19="",AC19=""),"",IF(AC19=100%,"CONCLUÍDO",IF(AC19=0,IF(AB19=0,"PROJETO NÃO INICIADO","FALTA DE ACOMPANHAMENTO"),IF(AC19>AB19,"ADIANTADO",IF(AC19=AB19,"CONFORME PLANEJADO","ATRASO"))))) -> PROJETO NÃO INICIADO | AE19: 0
O20: 15 | P20: =_xlfn.XLOOKUP(U20,$C$55:$C$128,$A$55:$A$128) -> BSW | Q20: =IFERROR(LARGE($I$55:$I$128,O20)," ") -> 34645 | R20: =_xlfn.XLOOKUP(Q20,$I$55:$I$128,$N$55:$N$128) -> 47248.27 | S20: =_xlfn.XLOOKUP(U20,$B$55:$B$144,$I$55:$I$144) -> #N/A | T20: {=SUMPRODUCT(($B$55:$B$143=U20)*(S$54:$AG$54<=TODAY())*(ISNUMBER(R$56:$AF$144)),R$56:$AF$144)} -> #REF! | U20: =IFERROR(HYPERLINK(INDEX($D$55:$D$128,MATCH(Q20,$I$55:$I$128,0)),INDEX($C$55:$C$128,MATCH(Q20,$I$55:$I$128,0)) ), "" ) -> 15 - Redução de consumo no slitter dos itens VW000950AA/951AA | Z20: =Q20/$C$5 -> 0.014483622 | AA20: =Pareto!E84 -> 0.98551019 | AB20: {=IFERROR(INDEX($R$55:$R$128,MATCH(1,($AN$55:$AN$128=U20)*($Q$55:$Q$128="Previsto"), 0) ), "")} -> 0.90909091 | AC20: {=IFERROR( INDEX($R$55:$R$128,MATCH(1,($AN$55:$AN$128=U20)*($Q$55:$Q$128="Real"),0)),"")} -> 0.36363636 | AD20: =IF(OR(AB20="",AC20=""),"",IF(AC20=100%,"CONCLUÍDO",IF(AC20=0,IF(AB20=0,"PROJETO NÃO INICIADO","FALTA DE ACOMPANHAMENTO"),IF(AC20>AB20,"ADIANTADO",IF(AC20=AB20,"CONFORME PLANEJADO","ATRASO"))))) -> ATRASO | AE20: 0.5
O21: 16 | P21: =_xlfn.XLOOKUP(U21,$C$55:$C$128,$A$55:$A$128) -> BSW | Q21: =IFERROR(LARGE($I$55:$I$128,O21)," ") -> 24120 | R21: =_xlfn.XLOOKUP(Q21,$I$55:$I$128,$N$55:$N$128) -> 11228.26 | S21: =_xlfn.XLOOKUP(U21,$B$55:$B$144,$I$55:$I$144) -> #N/A | T21: {=SUMPRODUCT(($B$55:$B$143=U21)*(S$54:$AG$54<=TODAY())*(ISNUMBER(R$56:$AF$144)),R$56:$AF$144)} -> #REF! | U21: =IFERROR(HYPERLINK(INDEX($D$55:$D$128,MATCH(Q21,$I$55:$I$128,0)),INDEX($C$55:$C$128,MATCH(Q21,$I$55:$I$128,0)) ), "" ) -> 14 - Redução de consumo no passo do blank dos itens VW000950AA/951AA | Z21: =Q21/$C$5 -> 0.010083561 | AA21: =Pareto!E85 -> 0.99166412 | AB21: {=IFERROR(INDEX($R$55:$R$128,MATCH(1,($AN$55:$AN$128=U21)*($Q$55:$Q$128="Previsto"), 0) ), "")} -> 1 | AC21: {=IFERROR( INDEX($R$55:$R$128,MATCH(1,($AN$55:$AN$128=U21)*($Q$55:$Q$128="Real"),0)),"")} -> 1 | AD21: =IF(OR(AB21="",AC21=""),"",IF(AC21=100%,"CONCLUÍDO",IF(AC21=0,IF(AB21=0,"PROJETO NÃO INICIADO","FALTA DE ACOMPANHAMENTO"),IF(AC21>AB21,"ADIANTADO",IF(AC21=AB21,"CONFORME PLANEJADO","ATRASO"))))) -> CONCLUÍDO | AE21: 0.9
O22: 17 | P22: =_xlfn.XLOOKUP(U22,$C$55:$C$128,$A$55:$A$128) -> Redução de custo | Q22: =IFERROR(LARGE($I$55:$I$128,O22)," ") -> 19309 | R22: =_xlfn.XLOOKUP(Q22,$I$55:$I$128,$N$55:$N$128) -> 15889.551 | S22: =_xlfn.XLOOKUP(U22,$B$55:$B$144,$I$55:$I$144) -> #N/A | T22: {=SUMPRODUCT(($B$55:$B$143=U22)*(S$54:$AG$54<=TODAY())*(ISNUMBER(R$56:$AF$144)),R$56:$AF$144)} -> #REF! | U22: =IFERROR(HYPERLINK(INDEX($D$55:$D$128,MATCH(Q22,$I$55:$I$128,0)),INDEX($C$55:$C$128,MATCH(Q22,$I$55:$I$128,0)) ), "" ) -> 23 - Redução do consumo de MTP VW000938AB (- 3 mm no passo) | Z22: =Q22/$C$5 -> 0.0080722833 | AA22: =Pareto!E86 -> 0.99659059 | AB22: {=IFERROR(INDEX($R$55:$R$128,MATCH(1,($AN$55:$AN$128=U22)*($Q$55:$Q$128="Previsto"), 0) ), "")} -> 1 | AC22: {=IFERROR( INDEX($R$55:$R$128,MATCH(1,($AN$55:$AN$128=U22)*($Q$55:$Q$128="Real"),0)),"")} -> 1 | AD22: =IF(OR(AB22="",AC22=""),"",IF(AC22=100%,"CONCLUÍDO",IF(AC22=0,IF(AB22=0,"PROJETO NÃO INICIADO","FALTA DE ACOMPANHAMENTO"),IF(AC22>AB22,"ADIANTADO",IF(AC22=AB22,"CONFORME PLANEJADO","ATRASO"))))) -> CONCLUÍDO | AE22: 0
O23: 18 | P23: =_xlfn.XLOOKUP(U23,$C$55:$C$128,$A$55:$A$128) -> BSW | Q23: =IFERROR(LARGE($I$55:$I$128,O23)," ") -> 9639 | R23: =_xlfn.XLOOKUP(Q23,$I$55:$I$128,$N$55:$N$128) -> 22604.71 | S23: =_xlfn.XLOOKUP(U23,$B$55:$B$144,$I$55:$I$144) -> #N/A | T23: {=SUMPRODUCT(($B$55:$B$143=U23)*(S$54:$AG$54<=TODAY())*(ISNUMBER(R$56:$AF$144)),R$56:$AF$144)} -> #REF! | U23: =IFERROR(HYPERLINK(INDEX($D$55:$D$128,MATCH(Q23,$I$55:$I$128,0)),INDEX($C$55:$C$128,MATCH(Q23,$I$55:$I$128,0)) ), "" ) -> 29 - Redução do consumo MTP no passo do Blank VW000942AB / 943AB -5MM | Z23: =Q23/$C$5 -> 0.0040296617 | AA23: =Pareto!E87 -> 0.99904986 | AB23: {=IFERROR(INDEX($R$55:$R$128,MATCH(1,($AN$55:$AN$128=U23)*($Q$55:$Q$128="Previsto"), 0) ), "")} -> 0.88888889 | AC23: {=IFERROR( INDEX($R$55:$R$128,MATCH(1,($AN$55:$AN$128=U23)*($Q$55:$Q$128="Real"),0)),"")} -> 0.33333333 | AD23: =IF(OR(AB23="",AC23=""),"",IF(AC23=100%,"CONCLUÍDO",IF(AC23=0,IF(AB23=0,"PROJETO NÃO INICIADO","FALTA DE ACOMPANHAMENTO"),IF(AC23>AB23,"ADIANTADO",IF(AC23=AB23,"CONFORME PLANEJADO","ATRASO"))))) -> ATRASO | AE23: 0
O24: 19 | P24: =_xlfn.XLOOKUP(U24,$C$55:$C$128,$A$55:$A$128) -> Redução de custo | Q24: =IFERROR(LARGE($I$55:$I$128,O24)," ") -> 2500 | R24: =_xlfn.XLOOKUP(Q24,$I$55:$I$128,$N$55:$N$128) -> 0 | S24: =_xlfn.XLOOKUP(U24,$B$55:$B$144,$I$55:$I$144) -> #N/A | T24: {=SUMPRODUCT(($B$55:$B$143=U24)*(S$54:$AG$54<=TODAY())*(ISNUMBER(R$56:$AF$144)),R$56:$AF$144)} -> #REF! | U24: =IFERROR(HYPERLINK(INDEX($D$55:$D$128,MATCH(Q24,$I$55:$I$128,0)),INDEX($C$55:$C$128,MATCH(Q24,$I$55:$I$128,0)) ), "" ) -> 33- Rollout impressora Administrativo | Z24: =Q24/$C$5 -> 0.0010451452 | AA24: =Pareto!E88 -> 0.99968771 | AB24: {=IFERROR(INDEX($R$55:$R$128,MATCH(1,($AN$55:$AN$128=U24)*($Q$55:$Q$128="Previsto"), 0) ), "")} -> 1 | AC24: {=IFERROR( INDEX($R$55:$R$128,MATCH(1,($AN$55:$AN$128=U24)*($Q$55:$Q$128="Real"),0)),"")} -> 0.44 | AD24: =IF(OR(AB24="",AC24=""),"",IF(AC24=100%,"CONCLUÍDO",IF(AC24=0,IF(AB24=0,"PROJETO NÃO INICIADO","FALTA DE ACOMPANHAMENTO"),IF(AC24>AB24,"ADIANTADO",IF(AC24=AB24,"CONFORME PLANEJADO","ATRASO"))))) -> ATRASO | AE24: 0
O25: 20 | P25: =_xlfn.XLOOKUP(U24,$C$55:$C$128,$A$55:$A$128) -> Redução de custo | Q25: =IFERROR(LARGE($I$55:$I$128,O25)," ") -> 1224 | R25: =_xlfn.XLOOKUP(Q25,$I$55:$I$128,$N$55:$N$128) -> 1224 | S25: =_xlfn.XLOOKUP(U24,$B$55:$B$144,$I$55:$I$144) -> #N/A | T25: {=SUMPRODUCT(($B$55:$B$143=U24)*(S$54:$AG$54<=TODAY())*(ISNUMBER(R$56:$AF$144)),R$56:$AF$144)} -> #REF! | U25: =IFERROR(HYPERLINK(INDEX($D$55:$D$128,MATCH(Q25,$I$55:$I$128,0)),INDEX($C$55:$C$128,MATCH(Q25,$I$55:$I$128,0)) ), "" ) -> 31 - Redução impressora Backup | Z25: =Q25/$C$5 -> 0.00051170308 | AA25: =Pareto!E89 -> 1 | AB25: {=IFERROR(INDEX($R$55:$R$128,MATCH(1,($AN$55:$AN$128=U24)*($Q$55:$Q$128="Previsto"), 0) ), "")} -> 1 | AC25: {=IFERROR( INDEX($R$55:$R$128,MATCH(1,($AN$55:$AN$128=U24)*($Q$55:$Q$128="Real"),0)),"")} -> 0.44 | AD25: =IF(OR(AB25="",AC25=""),"",IF(AC25=100%,"CONCLUÍDO",IF(AC25=0,IF(AB25=0,"PROJETO NÃO INICIADO","FALTA DE ACOMPANHAMENTO"),IF(AC25>AB25,"ADIANTADO",IF(AC25=AB25,"CONFORME PLANEJADO","ATRASO"))))) -> ATRASO
O26: Total | Q26: =SUM(Q6:Q25) -> 3919443 | R26: =SUM(R6:R25) -> 2819031.8
A27: 1. KPIs ESTRATÉGICOS
A28: CATEGORIA | B28: KPI | C28: UN | D28: Frequência | E28: TIPO | F28: BASELINE 2025 | G28: META 2026 | H28: Jan | I28: P. Ofensor1 | J28: Fev | K28: P. Ofensor2 | L28: Mar | M28: P. Ofensor3 | N28: Abr | O28: P. Ofensor4 | P28: Mai | Q28: P. Ofensor5 | R28: Jun | S28: P. Ofensor6 | T28: Jul | U28: P. Ofensor7 | V28: Ago | W28: P. Ofensor8 | X28: Set | Y28: P. Ofensor9 | Z28: Out | AA28: P. Ofensor10 | AB28: Nov | AC28: P. Ofensor11 | AD28: Dez | AE28: P. Ofensor12
A29: Financeiro | B29: Margem VA | C29: % | D29: Mensal | E29: Maior Melhor | F29: 0.366 | G29: 0.367 | H29: 0.372 | I29: Matéria Prima | J29: 0.327 | K29: Matéria Prima | L29: 0.358 | M29: Matéria Prima | N29: 0.38 | O29: Matéria Prima | P29: 0.411 | Q29: Matéria Prima
A30: Financeiro | B30: Custo de Scrap (Refugo) | C30: % | D30: Semanal | E30: Menor Melhor | F30: 0.0037 | G30: 0.002 | H30: 0.0028 | I30: Try Out | J30: 23595.82 | K30: Try Out | L30: 66468.61 | M30: Try Out | N30: 42764.61 | O30: Try Out | P30: 42189.13 | Q30: Try Out
A31: Operacional | B31: OEE | C31: % | D31: Semanal | E31: Maior Melhor | F31: 0.537 | G31: 75%% | H31: 0.418 | I31: Manutenção Mecanica | J31: 0.724 | K31: Manutenção Mecanica | L31: 0.541 | M31: Manutenção Mecanica | N31: 0.582 | O31: Manutenção Mecanica | P31: 0.631 | Q31: Manutenção Mecanica
A32: Operacional | B32: Eficiência de MO | C32: % | D32: Semanal | E32: Maior Melhor | F32: 0.7408 | G32: 0.77 | H32: 0.712 | I32: Turn Over | J32: 76.9 | K32: Turn Over | L32: 0.77 | M32: Turn Over | N32: 0.74 | O32: Turn Over | P32: 75,0%% | Q32: Turn Over
A33: Operacional | B33: Performance | C33: % | D33: Semanal | E33: Maior Melhor | F33: 0.8807 | G33: 0.866 | H33: 0.8237 | I33: Turn Over | J33: 0.8477 | K33: Turn Over | L33: 0.8477 | M33: Turn Over | N33: 0.7533 | O33: Turn Over | P33: 0.8954 | Q33: Turn Over
A34: Operacional | B34: Qualidade | C34: % | D34: Semanal | E34: Maior Melhor | F34: NA | G34: NA | H34: NA | I34: NA | J34: NA | K34: NA | L34: NA | M34: NA | N34: NA | O34: NA | P34: NA | Q34: NA
A35: Operacional | B35: Disponibilidade | C35: % | D35: Semanal | E35: Maior Melhor | F35: 0.6379 | G35: 86.6 | H35: 0.8319 | I35: Manutenção Mecanica | J35: 0.854 | K35: Manutenção Mecanica | L35: 0.8043 | M35: Manutenção Mecanica | N35: 0.7847 | O35: Manutenção Mecanica | P35: 0.7047 | Q35: Manutenção Mecanica
A36: Operacional | B36: MTBF (Manutenção) | C36: h | D36: Semanal | E36: Maior Melhor | F36: 8.4993056 | G36: 8.3333333 | H36: 6.0243056 | I36: CSR54009 | J36: 6.3715278 | K36: NA | L36: 10.325694 | M36: NA | N36: 11.924306 | O36: NA | P36: 10.704167 | Q36: NA
A37: Operacional | B37: MTTR (Manutenção) | C37: h | D37: Semanal | E37: Menor Melhor | F37: 0.020833333 | G37: 0.034722222 | H37: 0.020833333 | I37: NA | J37: 0.020138889 | K37: NA | L37: 0.017361111 | M37: NA | N37: 0.018055556 | O37: NA | P37: 0.022222222 | Q37: NA
A38: Operacional | B38: Horas Extras | C38: Valor | D38: Semanal | E38: Menor Melhor | F38: 785490 | G38: 421705 | H38: 100336.44 | I38: Turn Over | J38: 32904 | K38: Turn Over | L38: 40106 | M38: Turn Over | N38: 83345.63 | O38: Turn Over | P38: 102906.25 | Q38: Turn Over
A39: Operacional | B39: Acuracidade Estoque | C39: Valor | D39: Semanal | E39: Menor Melhor | F39: 11267 | G39: -129647 | H39: 12008 | J39: 12431 | L39: 11056 | N39: 10502 | P39: 10724
A40: Qualidade | B40: PPM Interno | C40: ppm | D40: Semanal | E40: Menor Melhor | F40: 21979 | G40: 21000 | H40: 1837 | I40: Try Out | J40: 1926 | K40: Try Out | L40: 2902 | M40: Try Out | N40: 2870 | O40: Try Out | P40: 2522 | Q40: Try Out
A41: Qualidade | B41: PPM Externo | C41: ppm | D41: Semanal | E41: Menor Melhor | F41: 34297 | G41: 30000 | H41: 2474 | I41: NA | J41: 2249 | L41: 0 | N41: 0 | P41: 0
A42: Qualidade | B42: CONC | C42: % | D42: Mensal | E42: Menor Melhor | F42: 0.0087 | G42: 0.80% | H42: 0.0111 | I42: Hora Extra | J42: 0.0085 | K42: Hora Extra | L42: 0.0107 | M42: Hora Extra | N42: 0.0144 | O42: Hora Extra | P42: 1,44%% | Q42: Hora Extra
A43: Qualidade | B43: Reclamações de Clientes | C43: qtd | D43: Diário | E43: Menor Melhor | F43: 19 | G43: 14 | H43: 3 | I43: Falha na porca da ciser | J43: 0 | K43: NA | L43: 1 | M43: NA | N43: 2 | P43: 4 | Q43: NA
A44: Segurança | B44: Taxa de Frequência de Acidente | C44: taxa | D44: 24 | E44: Menor Melhor | F44: 10 | G44: 20 | H44: 24 | I44: Corte na mão | J44: 26 | K44: NA | L44: 0 | M44: NA | N44: 0 | O44: NA | P44: 13 | Q44: NA
A45: Validação Processo | B45: % Conformidade vs POC | C45: % | D45: P/ Prioridade | E45: Maior Melhor | F45: 0.5 | H45: 1 | J45: 1 | L45: 1 | N45: 1 | P45: 1 | AJ45: Departamento Suporte
A46: Sistema de Produção Delga (SPD) | B46: % Aderência às Ferramentas SPD | C46: % | D46: Semanal | E46: Maior Melhor | F46: 0.53 | G46: 1 | H46: 0.72 | I46: Utilização de form irregular | J46: 0.87 | K46: Utilização de form irregular | L46: 55.3% | M46: Utilização de form irregular | N46: 0.61 | O46: Utilização de form irregular | P46: 1 | Q46: Utilização de form irregular | AJ46: Departamentos | AK46: Valor de Impacto
A47: Operacional | B47: MTBF (Ferramentaria) | C47: h | D47: Semanal | E47: Maior Melhor | F47: 18.708333 | G47: 14.583333 | H47: 0.36893519 | J47: 19.333333 | L47: 9.09697 | N47: 19.458333 | P47: 18.583333 | AJ47: Compras | AK47: =SUMIF($AK$55:$AK$128,AJ47,$AM$55:$AM$128) -> 0
A48: Operacional | B48: MTTR (Ferramentaria) | C48: h | D48: Semanal | E48: Menor Melhor | F48: 0.022916667 | G48: 0.020833333 | H48: 0.024814815 | J48: 0.027083333 | L48: 0.010416667 | N48: 0.0090277778 | P48: 0.00625 | AJ48: Vendas | AK48: =SUMIF($AK$55:$AK$128,AJ48,$AM$55:$AM$128) -> 0
A49: Gerente de Planta | B49: Performance de GESTÂO | C49: R$ | D49: Mensal | E49: Maior Melhor ↑ | F49: ?? | G49: ?? | H49: ?? | I49: ?? | J49: ?? | K49: ?? | L49: ?? | M49: ?? | N49: ?? | AJ49: Orçamento | AK49: =SUMIF($AK$55:$AK$128,AJ49,$AM$55:$AM$128) -> 0
AJ50: Simulação | AK50: =SUMIF($AK$55:$AK$128,AJ50,$AM$55:$AM$128) -> 0
AJ51: Eng. Corporativa | AK51: =SUMIF($AK$55:$AK$128,AJ51,$AM$55:$AM$128) -> 0
A53: 2. IDEIAS DE KAIZENS E PROJETOS DE REDUÇÃO DE CUSTOS | S53: 1° Tri | W53: 2° Tri | AA53: 3° Tri | AE53: 4° Tri
A54: TIPO Redução de custos / Kaizen / Você resolve | B54: VA / GGF / Material Auxiliar | C54: Nome do Projeto | D54: Caminho da Evidência | E54: DESCRIÇÃO | F54: RESPONSÁVEL | G54: Inicio Mês/Ano | H54: Termino Mês/Ano | I54: PREVISTO (R$) | J54: Mês do 1º RETORNO | K54: Quantidade de meses com retorno | L54: Processo de entrega do projeto a custos | M54: VALIDADOR OK / NOK | N54: SAVING VALIDADO (R$ Valor) | O54: Status | P54: % Responsabilidade Delga | R54: Avanço | S54: 46023 | T54: 46054 | U54: 46082 | V54: Total 1° Tri | W54: 46113 | X54: 46143 | Y54: 46174 | Z54: Total 2° Tri | AA54: 46204 | AB54: 46235 | AC54: 46266 | AD54: Total 3° Tri | AE54: 46296 | AF54: 46327 | AG54: 46357 | AH54: Total 4° Tri | AI54: Total Ano | AJ54: OBS | AK54: Departamento Suporte | AL54: % de Impacto | AM54: Impacto Financeiro | AN54: proj ref. | AP54: Retorno até hoje
A55: Redução de custo | B55: GGF | C55: 01 - Desenvolver célula de solda para soldar porcas | D55: \\192.168.5.20\Departamentos\TI\Projetos\Master 2026\01 - Desenvolver célula de solda para soldar porcas\01 - Desenvolver célula de solda para soldar porcas.xlsx | E55: Confeccionar uma célula de solda para manufaturar conjuntos e sub conjuntos de elementos roscados substituindo as estacionarias | F55: Jonathan | G55: 46023 | H55: 46296 | K55: =IF(J55="", "", 12 - MONTH(J55) + 1) | O55: ⏳ Em Execução | P55: 0.8 | Q55: Previsto | R55: =AVERAGE([3]Estrutura!$I$5:$I$9) -> 0.79032258 | S55: =IFERROR(IF(AND(S$54>=EOMONTH($J55,-1)+1,S$54<=EOMONTH(EOMONTH($J55,-1)+1,$K55-1)),IF(NOT(ISBLANK($N55)),$N55/$K55,$I55/$K55),0),0) -> 0 | T55: =IFERROR(IF(AND(T$54>=EOMONTH($J55,-1)+1,T$54<=EOMONTH(EOMONTH($J55,-1)+1,$K55-1)),IF(NOT(ISBLANK($N55)),$N55/$K55,$I55/$K55),0),0) -> 0 | U55: =IFERROR(IF(AND(U$54>=EOMONTH($J55,-1)+1,U$54<=EOMONTH(EOMONTH($J55,-1)+1,$K55-1)),IF(NOT(ISBLANK($N55)),$N55/$K55,$I55/$K55),0),0) -> 0 | V55: =SUM(S55:U55) -> 0 | W55: =IFERROR(IF(AND(W$54>=EOMONTH($J55,-1)+1,W$54<=EOMONTH(EOMONTH($J55,-1)+1,$K55-1)),IF(NOT(ISBLANK($N55)),$N55/$K55,$I55/$K55),0),0) -> 0 | X55: =IFERROR(IF(AND(X$54>=EOMONTH($J55,-1)+1,X$54<=EOMONTH(EOMONTH($J55,-1)+1,$K55-1)),IF(NOT(ISBLANK($N55)),$N55/$K55,$I55/$K55),0),0) -> 0 | Y55: =IFERROR(IF(AND(Y$54>=EOMONTH($J55,-1)+1,Y$54<=EOMONTH(EOMONTH($J55,-1)+1,$K55-1)),IF(NOT(ISBLANK($N55)),$N55/$K55,$I55/$K55),0),0) -> 0 | Z55: =SUM(W55:Y55) -> 0 | AA55: =IFERROR(IF(AND(AA$54>=EOMONTH($J55,-1)+1,AA$54<=EOMONTH(EOMONTH($J55,-1)+1,$K55-1)),IF(NOT(ISBLANK($N55)),$N55/$K55,$I55/$K55),0),0) -> 0 | AB55: =IFERROR(IF(AND(AB$54>=EOMONTH($J55,-1)+1,AB$54<=EOMONTH(EOMONTH($J55,-1)+1,$K55-1)),IF(NOT(ISBLANK($N55)),$N55/$K55,$I55/$K55),0),0) -> 0 | AC55: =IFERROR(IF(AND(AC$54>=EOMONTH($J55,-1)+1,AC$54<=EOMONTH(EOMONTH($J55,-1)+1,$K55-1)),IF(NOT(ISBLANK($N55)),$N55/$K55,$I55/$K55),0),0) -> 0 | AD55: =SUM(AA55:AC55) -> 0 | AE55: =IFERROR(IF(AND(AE$54>=EOMONTH($J55,-1)+1,AE$54<=EOMONTH(EOMONTH($J55,-1)+1,$K55-1)),IF(NOT(ISBLANK($N55)),$N55/$K55,$I55/$K55),0),0) -> 0 | AF55: =IFERROR(IF(AND(AF$54>=EOMONTH($J55,-1)+1,AF$54<=EOMONTH(EOMONTH($J55,-1)+1,$K55-1)),IF(NOT(ISBLANK($N55)),$N55/$K55,$I55/$K55),0),0) -> 0 | AG55: =IFERROR(IF(AND(AG$54>=EOMONTH($J55,-1)+1,AG$54<=EOMONTH(EOMONTH($J55,-1)+1,$K55-1)),IF(NOT(ISBLANK($N55)),$N55/$K55,$I55/$K55),0),0) -> 0 | AH55: =SUM(AE55:AG55) -> 0 | AI55: =SUM(V55,Z55,AD55,AH55) -> 0 | AM55: =N55*AL55 -> 0 | AN55: =C55 -> 01 - Desenvolver célula de solda para soldar porcas | AO55: P | AP55: {=IF(OR(AN55="",AN55=0),"",IF(SUMPRODUCT(($C$55:$C$128=AN55)*(S$54:$AG$54<EOMONTH(TODAY(),-1)+1)*(ISNUMBER(S$55:$AG$128)),S$55:$AG$128)=0,"",SUMPRODUCT(($C$55:$C$128=AN55)*(S$54:$AG$54<EOMONTH(TODAY(),-1)+1)*(ISNUMBER(S$55:$AG$128)),S$55:$AG$128)))}
Q56: Real | R56: =AVERAGE([3]Estrutura!$J$5:$J$9) -> 0.79 | V56: =SUM(S56:U56) -> 0 | Z56: =SUM(W56:Y56) -> 0 | AD56: =SUM(AA56:AC56) -> 0 | AH56: =SUM(AE56:AG56) -> 0 | AI56: =SUM(V56,Z56,AD56,AH56) -> 0 | AN56: =C55 -> 01 - Desenvolver célula de solda para soldar porcas | AO56: R | AP56: {=IF(OR(AN56="",AN56=0),"",IF(SUMPRODUCT(($C$55:$C$143=AN56)*($S$54:AG$54<=TODAY())*(ISNUMBER($S$56:AG$144)),$S$56:AG$144)=0,"",SUMPRODUCT(($C$55:$C$143=AN56)*($S$54:AG$54<=TODAY())*(ISNUMBER($S$56:AG$144)),$S$56:AG$144)))}
A57: Redução de custo | B57: GGF | C57: 02 - Aumentar a produtividade da estamparia atraves da implementação lote econômico e multiplos de MTP | D57: \\192.168.5.20\Departamentos\TI\Projetos\Master 2026\02 - Aumentar a produtividade da estamparia atraves da implementação lote econômico e multiplos de MTP\A3 Aumento de Produtividade por Implementação de Lote Econômico e Padronização de Embalagens.xlsx | E57: Padronização do processo de fabricação. Matéria Prima e Embalagens para possibilitar o controle de estoque/recebimento e produção de acordo com a POC diminuindo a quantidade de set up | F57: Willian | G57: 46024 | H57: 46266 | J57: 46266 | K57: =IF(J57="", "", 12 - MONTH(J57) + 1) -> 4 | O57: ⏳ Em Execução | P57: 0.9 | Q57: Previsto | R57: =AVERAGE([4]Estrutura!$I$5:$I$15) -> 0.87262156 | S57: =IFERROR(IF(S$54>=EOMONTH($J57,-1)+1,IF(NOT(ISBLANK($N57)),$N57/12,$I57/12),0),0) -> 0 | T57: =IFERROR(IF(T$54>=EOMONTH($J57,-1)+1,IF(NOT(ISBLANK($N57)),$N57/12,$I57/12),0),0) -> 0 | U57: =IFERROR(IF(U$54>=EOMONTH($J57,-1)+1,IF(NOT(ISBLANK($N57)),$N57/12,$I57/12),0),0) -> 0 | V57: =SUM(S57:U57) -> 0 | W57: =IFERROR(IF(W$54>=EOMONTH($J57,-1)+1,IF(NOT(ISBLANK($N57)),$N57/12,$I57/12),0),0) -> 0 | X57: =IFERROR(IF(X$54>=EOMONTH($J57,-1)+1,IF(NOT(ISBLANK($N57)),$N57/12,$I57/12),0),0) -> 0 | Y57: =IFERROR(IF(Y$54>=EOMONTH($J57,-1)+1,IF(NOT(ISBLANK($N57)),$N57/12,$I57/12),0),0) -> 0 | Z57: =SUM(W57:Y57) -> 0 | AA57: =IFERROR(IF(AA$54>=EOMONTH($J57,-1)+1,IF(NOT(ISBLANK($N57)),$N57/12,$I57/12),0),0) -> 0 | AB57: =IFERROR(IF(AB$54>=EOMONTH($J57,-1)+1,IF(NOT(ISBLANK($N57)),$N57/12,$I57/12),0),0) -> 0 | AC57: =IFERROR(IF(AC$54>=EOMONTH($J57,-1)+1,IF(NOT(ISBLANK($N57)),$N57/12,$I57/12),0),0) -> 0 | AD57: =SUM(AA57:AC57) -> 0 | AE57: =IFERROR(IF(AE$54>=EOMONTH($J57,-1)+1,IF(NOT(ISBLANK($N57)),$N57/12,$I57/12),0),0) -> 0 | AF57: =IFERROR(IF(AF$54>=EOMONTH($J57,-1)+1,IF(NOT(ISBLANK($N57)),$N57/12,$I57/12),0),0) -> 0 | AG57: =IFERROR(IF(AG$54>=EOMONTH($J57,-1)+1,IF(NOT(ISBLANK($N57)),$N57/12,$I57/12),0),0) -> 0 | AH57: =SUM(AE57:AG57) -> 0 | AI57: =SUM(V57,Z57,AD57,AH57) -> 0 | AM57: =N57*AL57 -> 0 | AN57: =C57 -> 02 - Aumentar a produtividade da estamparia atraves da implementação lote econômico e multiplos de MTP | AO57: P | AP57: {=IF(OR(AN57="",AN57=0),"",IF(SUMPRODUCT(($C$55:$C$128=AN57)*(S$54:$AG$54<EOMONTH(TODAY(),-1)+1)*(ISNUMBER(S$55:$AG$128)),S$55:$AG$128)=0,"",SUMPRODUCT(($C$55:$C$128=AN57)*(S$54:$AG$54<EOMONTH(TODAY(),-1)+1)*(ISNUMBER(S$55:$AG$128)),S$55:$AG$128)))}
Q58: Real | R58: =AVERAGE([4]Estrutura!$J$5:$J$15) -> 0.72727273 | V58: =SUM(S58:U58) -> 0 | Z58: =SUM(W58:Y58) -> 0 | AD58: =SUM(AA58:AC58) -> 0 | AH58: =SUM(AE58:AG58) -> 0 | AI58: =SUM(V58,Z58,AD58,AH58) -> 0 | AN58: =C57 -> 02 - Aumentar a produtividade da estamparia atraves da implementação lote econômico e multiplos de MTP | AO58: R | AP58: {=IF(OR(AN58="",AN58=0),"",IF(SUMPRODUCT(($C$55:$C$143=AN58)*($S$54:AG$54<=TODAY())*(ISNUMBER($S$56:AG$144)),$S$56:AG$144)=0,"",SUMPRODUCT(($C$55:$C$143=AN58)*($S$54:AG$54<=TODAY())*(ISNUMBER($S$56:AG$144)),$S$56:AG$144)))}
A59: BSW | B59: VA | C59: 03 - Redução de consumo de MP dos blanks com a técnica de corte Wave | D59: \\192.168.5.20\Departamentos\TI\Projetos\Master 2026\03 - Redução de consumo de MP dos blanks com a técnica de corte Wave\Planta Melhoria Blank Wave - Gestão de Projetos.xlsx | E59: Inserir cortes wave nos blanks retangulares que são utilizados na prensa Isgec | F59: Felipe | G59: 46023 | H59: 46174 | I59: 513721 | J59: 46174 | K59: =IF(J59="", "", 12 - MONTH(J59) + 1) -> 7 | O59: ⏳ Em Execução | P59: 0.9 | Q59: Previsto | R59: =AVERAGE(#REF!) -> #REF! | S59: =IFERROR(IF(S$54>=EOMONTH($J59,-1)+1,IF(NOT(ISBLANK($N59)),$N59/12,$I59/12),0),0) -> 0 | T59: =IFERROR(IF(T$54>=EOMONTH($J59,-1)+1,IF(NOT(ISBLANK($N59)),$N59/12,$I59/12),0),0) -> 0 | U59: =IFERROR(IF(U$54>=EOMONTH($J59,-1)+1,IF(NOT(ISBLANK($N59)),$N59/12,$I59/12),0),0) -> 0 | V59: =SUM(S59:U59) -> 0 | W59: =IFERROR(IF(W$54>=EOMONTH($J59,-1)+1,IF(NOT(ISBLANK($N59)),$N59/12,$I59/12),0),0) -> 0 | X59: =IFERROR(IF(X$54>=EOMONTH($J59,-1)+1,IF(NOT(ISBLANK($N59)),$N59/12,$I59/12),0),0) -> 0 | Y59: =IFERROR(IF(Y$54>=EOMONTH($J59,-1)+1,IF(NOT(ISBLANK($N59)),$N59/12,$I59/12),0),0) -> 42810.083 | Z59: =SUM(W59:Y59) -> 42810.083 | AA59: =IFERROR(IF(AA$54>=EOMONTH($J59,-1)+1,IF(NOT(ISBLANK($N59)),$N59/12,$I59/12),0),0) -> 42810.083 | AB59: =IFERROR(IF(AB$54>=EOMONTH($J59,-1)+1,IF(NOT(ISBLANK($N59)),$N59/12,$I59/12),0),0) -> 42810.083 | AC59: =IFERROR(IF(AC$54>=EOMONTH($J59,-1)+1,IF(NOT(ISBLANK($N59)),$N59/12,$I59/12),0),0) -> 42810.083 | AD59: =SUM(AA59:AC59) -> 128430.25 | AE59: =IFERROR(IF(AE$54>=EOMONTH($J59,-1)+1,IF(NOT(ISBLANK($N59)),$N59/12,$I59/12),0),0) -> 42810.083 | AF59: =IFERROR(IF(AF$54>=EOMONTH($J59,-1)+1,IF(NOT(ISBLANK($N59)),$N59/12,$I59/12),0),0) -> 42810.083 | AG59: =IFERROR(IF(AG$54>=EOMONTH($J59,-1)+1,IF(NOT(ISBLANK($N59)),$N59/12,$I59/12),0),0) -> 42810.083 | AH59: =SUM(AE59:AG59) -> 128430.25 | AI59: =SUM(V59,Z59,AD59,AH59) -> 299670.58 | AM59: =N59*AL59 -> 0 | AN59: =C59 -> 03 - Redução de consumo de MP dos blanks com a técnica de corte Wave | AO59: P | AP59: {=IF(OR(AN59="",AN59=0),"",IF(SUMPRODUCT(($C$55:$C$128=AN59)*(S$54:$AG$54<EOMONTH(TODAY(),-1)+1)*(ISNUMBER(S$55:$AG$128)),S$55:$AG$128)=0,"",SUMPRODUCT(($C$55:$C$128=AN59)*(S$54:$AG$54<EOMONTH(TODAY(),-1)+1)*(ISNUMBER(S$55:$AG$128)),S$55:$AG$128)))}
Q60: Real | R60: =AVERAGE(#REF!) -> #REF! | V60: =SUM(S60:U60) -> 0 | Z60: =SUM(W60:Y60) -> 0 | AD60: =SUM(AA60:AC60) -> 0 | AH60: =SUM(AE60:AG60) -> 0 | AI60: =SUM(V60,Z60,AD60,AH60) -> 0 | AN60: =C59 -> 03 - Redução de consumo de MP dos blanks com a técnica de corte Wave | AO60: R | AP60: {=IF(OR(AN60="",AN60=0),"",IF(SUMPRODUCT(($C$55:$C$143=AN60)*($S$54:AG$54<=TODAY())*(ISNUMBER($S$56:AG$144)),$S$56:AG$144)=0,"",SUMPRODUCT(($C$55:$C$143=AN60)*($S$54:AG$54<=TODAY())*(ISNUMBER($S$56:AG$144)),$S$56:AG$144)))}
A61: BSW | B61: VA | C61: 04 - Redução da largura dos slitters | D61: \\192.168.5.20\Departamentos\TI\Projetos\Master 2026\04 - Redução da largura dos slitters\04 - Redução da largura dos slitters.xlsx | E61: Redução das larguras dos slitters (137/138 e 567/568 MQB) | F61: Tersio | G61: 46054 | H61: 46174 | I61: 75733 | J61: 46174 | K61: =IF(J61="", "", 12 - MONTH(J61) + 1) -> 7 | O61: ⏳ Em Execução | P61: 0.5 | Q61: Previsto | R61: 0.4 | S61: =IFERROR(IF(S$54>=EOMONTH($J61,-1)+1,IF(NOT(ISBLANK($N61)),$N61/12,$I61/12),0),0) -> 0 | T61: =IFERROR(IF(T$54>=EOMONTH($J61,-1)+1,IF(NOT(ISBLANK($N61)),$N61/12,$I61/12),0),0) -> 0 | U61: =IFERROR(IF(U$54>=EOMONTH($J61,-1)+1,IF(NOT(ISBLANK($N61)),$N61/12,$I61/12),0),0) -> 0 | V61: =SUM(S61:U61) -> 0 | W61: =IFERROR(IF(W$54>=EOMONTH($J61,-1)+1,IF(NOT(ISBLANK($N61)),$N61/12,$I61/12),0),0) -> 0 | X61: =IFERROR(IF(X$54>=EOMONTH($J61,-1)+1,IF(NOT(ISBLANK($N61)),$N61/12,$I61/12),0),0) -> 0 | Y61: =IFERROR(IF(Y$54>=EOMONTH($J61,-1)+1,IF(NOT(ISBLANK($N61)),$N61/12,$I61/12),0),0) -> 6311.0833 | Z61: =SUM(W61:Y61) -> 6311.0833 | AA61: =IFERROR(IF(AA$54>=EOMONTH($J61,-1)+1,IF(NOT(ISBLANK($N61)),$N61/12,$I61/12),0),0) -> 6311.0833 | AB61: =IFERROR(IF(AB$54>=EOMONTH($J61,-1)+1,IF(NOT(ISBLANK($N61)),$N61/12,$I61/12),0),0) -> 6311.0833 | AC61: =IFERROR(IF(AC$54>=EOMONTH($J61,-1)+1,IF(NOT(ISBLANK($N61)),$N61/12,$I61/12),0),0) -> 6311.0833 | AD61: =SUM(AA61:AC61) -> 18933.25 | AE61: =IFERROR(IF(AE$54>=EOMONTH($J61,-1)+1,IF(NOT(ISBLANK($N61)),$N61/12,$I61/12),0),0) -> 6311.0833 | AF61: =IFERROR(IF(AF$54>=EOMONTH($J61,-1)+1,IF(NOT(ISBLANK($N61)),$N61/12,$I61/12),0),0) -> 6311.0833 | AG61: =IFERROR(IF(AG$54>=EOMONTH($J61,-1)+1,IF(NOT(ISBLANK($N61)),$N61/12,$I61/12),0),0) -> 6311.0833 | AH61: =SUM(AE61:AG61) -> 18933.25 | AI61: =SUM(V61,Z61,AD61,AH61) -> 44177.583 | AM61: =N61*AL61 -> 0 | AN61: =C61 -> 04 - Redução da largura dos slitters | AO61: P | AP61: {=IF(OR(AN61="",AN61=0),"",IF(SUMPRODUCT(($C$55:$C$128=AN61)*(S$54:$AG$54<EOMONTH(TODAY(),-1)+1)*(ISNUMBER(S$55:$AG$128)),S$55:$AG$128)=0,"",SUMPRODUCT(($C$55:$C$128=AN61)*(S$54:$AG$54<EOMONTH(TODAY(),-1)+1)*(ISNUMBER(S$55:$AG$128)),S$55:$AG$128)))}
Q62: Real | R62: 0.4 | V62: =SUM(S62:U62) -> 0 | Z62: =SUM(W62:Y62) -> 0 | AD62: =SUM(AA62:AC62) -> 0 | AH62: =SUM(AE62:AG62) -> 0 | AI62: =SUM(V62,Z62,AD62,AH62) -> 0 | AJ62: Formalizado ou não ? Quais são os itens corretos? | AN62: =C61 -> 04 - Redução da largura dos slitters | AO62: R | AP62: {=IF(OR(AN62="",AN62=0),"",IF(SUMPRODUCT(($C$55:$C$143=AN62)*($S$54:AG$54<=TODAY())*(ISNUMBER($S$56:AG$144)),$S$56:AG$144)=0,"",SUMPRODUCT(($C$55:$C$143=AN62)*($S$54:AG$54<=TODAY())*(ISNUMBER($S$56:AG$144)),$S$56:AG$144)))}
A63: BSW | B63: VA | C63: 05 - Aplicar borda aparadas nas bobinas | D63: \\192.168.5.20\Departamentos\TI\Projetos\Master 2026\05- Aplicar borda aparada nas bobinas\05 - Aplicação de bordas aparadas.xlsx | E63: Implementar processo de bordas aparadas nas bobinas mãe para 7 itens. (2 itens inviabilizado) Restam 5 Itens | F63: Felipe | G63: 46054 | H63: 46235 | I63: 91444 | J63: 46235 | K63: =IF(J63="", "", 12 - MONTH(J63) + 1) -> 5 | M63: Não Ok | O63: ⏳ Em Execução | P63: 0.8 | Q63: Previsto | R63: =AVERAGE([5]Estrutura!$I$5:$I$16) -> 0.41666667 | S63: =IFERROR(IF(S$54>=EOMONTH($J63,-1)+1,IF(NOT(ISBLANK($N63)),$N63/12,$I63/12),0),0) -> 0 | T63: =IFERROR(IF(T$54>=EOMONTH($J63,-1)+1,IF(NOT(ISBLANK($N63)),$N63/12,$I63/12),0),0) -> 0 | U63: =IFERROR(IF(U$54>=EOMONTH($J63,-1)+1,IF(NOT(ISBLANK($N63)),$N63/12,$I63/12),0),0) -> 0 | V63: =SUM(S63:U63) -> 0 | W63: =IFERROR(IF(W$54>=EOMONTH($J63,-1)+1,IF(NOT(ISBLANK($N63)),$N63/12,$I63/12),0),0) -> 0 | X63: =IFERROR(IF(X$54>=EOMONTH($J63,-1)+1,IF(NOT(ISBLANK($N63)),$N63/12,$I63/12),0),0) -> 0 | Y63: =IFERROR(IF(Y$54>=EOMONTH($J63,-1)+1,IF(NOT(ISBLANK($N63)),$N63/12,$I63/12),0),0) -> 0 | Z63: =SUM(W63:Y63) -> 0 | AA63: =IFERROR(IF(AA$54>=EOMONTH($J63,-1)+1,IF(NOT(ISBLANK($N63)),$N63/12,$I63/12),0),0) -> 0 | AB63: =IFERROR(IF(AB$54>=EOMONTH($J63,-1)+1,IF(NOT(ISBLANK($N63)),$N63/12,$I63/12),0),0) -> 7620.3333 | AC63: =IFERROR(IF(AC$54>=EOMONTH($J63,-1)+1,IF(NOT(ISBLANK($N63)),$N63/12,$I63/12),0),0) -> 7620.3333 | AD63: =SUM(AA63:AC63) -> 15240.667 | AE63: =IFERROR(IF(AE$54>=EOMONTH($J63,-1)+1,IF(NOT(ISBLANK($N63)),$N63/12,$I63/12),0),0) -> 7620.3333 | AF63: =IFERROR(IF(AF$54>=EOMONTH($J63,-1)+1,IF(NOT(ISBLANK($N63)),$N63/12,$I63/12),0),0) -> 7620.3333 | AG63: =IFERROR(IF(AG$54>=EOMONTH($J63,-1)+1,IF(NOT(ISBLANK($N63)),$N63/12,$I63/12),0),0) -> 7620.3333 | AH63: =SUM(AE63:AG63) -> 22861 | AI63: =SUM(V63,Z63,AD63,AH63) -> 38101.667 | AM63: =N63*AL63 -> 0 | AN63: =C63 -> 05 - Aplicar borda aparadas nas bobinas | AO63: P | AP63: {=IF(OR(AN63="",AN63=0),"",IF(SUMPRODUCT(($C$55:$C$128=AN63)*(S$54:$AG$54<EOMONTH(TODAY(),-1)+1)*(ISNUMBER(S$55:$AG$128)),S$55:$AG$128)=0,"",SUMPRODUCT(($C$55:$C$128=AN63)*(S$54:$AG$54<EOMONTH(TODAY(),-1)+1)*(ISNUMBER(S$55:$AG$128)),S$55:$AG$128)))}
Q64: Real | R64: =AVERAGE([5]Estrutura!$J$5:$J$16) -> 0.33333333 | V64: =SUM(S64:U64) -> 0 | Z64: =SUM(W64:Y64) -> 0 | AD64: =SUM(AA64:AC64) -> 0 | AH64: =SUM(AE64:AG64) -> 0 | AI64: =SUM(V64,Z64,AD64,AH64) -> 0 | AN64: =C63 -> 05 - Aplicar borda aparadas nas bobinas | AO64: R | AP64: {=IF(OR(AN64="",AN64=0),"",IF(SUMPRODUCT(($C$55:$C$143=AN64)*($S$54:AG$54<=TODAY())*(ISNUMBER($S$56:AG$144)),$S$56:AG$144)=0,"",SUMPRODUCT(($C$55:$C$143=AN64)*($S$54:AG$54<=TODAY())*(ISNUMBER($S$56:AG$144)),$S$56:AG$144)))}
A65: BSW | B65: VA | C65: 06 - Redução consumo MTP aplicando tolerância mínima | D65: \\192.168.5.20\Departamentos\TI\Projetos\Master 2026\06 - Redução consumo MTP aplicando tolerância mínima\06 - Projeto Jarinu.xlsx | E65: Implementar mean to-low em 14 itens (Curva A) | F65: Felipe | G65: 46054 | H65: 46174 | I65: 1063359 | J65: 46174 | K65: 12 | M65: OK | N65: 1145830.2 | O65: ⏳ Em Execução | P65: 0.1 | Q65: Previsto | R65: =AVERAGE([6]Estrutura!$I$5:$I$24) -> 0.32939189 | S65: =IFERROR(IF(S$54>=EOMONTH($J65,-1)+1,IF(NOT(ISBLANK($N65)),$N65/12,$I65/12),0),0) -> 0 | T65: =IFERROR(IF(T$54>=EOMONTH($J65,-1)+1,IF(NOT(ISBLANK($N65)),$N65/12,$I65/12),0),0) -> 0 | U65: =IFERROR(IF(U$54>=EOMONTH($J65,-1)+1,IF(NOT(ISBLANK($N65)),$N65/12,$I65/12),0),0) -> 0 | V65: =SUM(S65:U65) -> 0 | W65: =IFERROR(IF(W$54>=EOMONTH($J65,-1)+1,IF(NOT(ISBLANK($N65)),$N65/12,$I65/12),0),0) -> 0 | X65: =IFERROR(IF(X$54>=EOMONTH($J65,-1)+1,IF(NOT(ISBLANK($N65)),$N65/12,$I65/12),0),0) -> 0 | Y65: =IFERROR(IF(Y$54>=EOMONTH($J65,-1)+1,IF(NOT(ISBLANK($N65)),$N65/12,$I65/12),0),0) -> 95485.853 | Z65: =SUM(W65:Y65) -> 95485.853 | AA65: =IFERROR(IF(AA$54>=EOMONTH($J65,-1)+1,IF(NOT(ISBLANK($N65)),$N65/12,$I65/12),0),0) -> 95485.853 | AB65: =IFERROR(IF(AB$54>=EOMONTH($J65,-1)+1,IF(NOT(ISBLANK($N65)),$N65/12,$I65/12),0),0) -> 95485.853 | AC65: =IFERROR(IF(AC$54>=EOMONTH($J65,-1)+1,IF(NOT(ISBLANK($N65)),$N65/12,$I65/12),0),0) -> 95485.853 | AD65: =SUM(AA65:AC65) -> 286457.56 | AE65: =IFERROR(IF(AE$54>=EOMONTH($J65,-1)+1,IF(NOT(ISBLANK($N65)),$N65/12,$I65/12),0),0) -> 95485.853 | AF65: =IFERROR(IF(AF$54>=EOMONTH($J65,-1)+1,IF(NOT(ISBLANK($N65)),$N65/12,$I65/12),0),0) -> 95485.853 | AG65: =IFERROR(IF(AG$54>=EOMONTH($J65,-1)+1,IF(NOT(ISBLANK($N65)),$N65/12,$I65/12),0),0) -> 95485.853 | AH65: =SUM(AE65:AG65) -> 286457.56 | AI65: =SUM(V65,Z65,AD65,AH65) -> 668400.97 | AJ65: Validação para 12 meses - porém a planilha considera os meses correntes de 2026 no saldo. | AM65: =N65*AL65 -> 0 | AN65: =C65 -> 06 - Redução consumo MTP aplicando tolerância mínima | AO65: P | AP65: {=IF(OR(AN65="",AN65=0),"",IF(SUMPRODUCT(($C$55:$C$128=AN65)*(S$54:$AG$54<EOMONTH(TODAY(),-1)+1)*(ISNUMBER(S$55:$AG$128)),S$55:$AG$128)=0,"",SUMPRODUCT(($C$55:$C$128=AN65)*(S$54:$AG$54<EOMONTH(TODAY(),-1)+1)*(ISNUMBER(S$55:$AG$128)),S$55:$AG$128)))}
Q66: Real | R66: =AVERAGE([6]Estrutura!$J$5:$J$24) -> 0.291 | V66: =SUM(S66:U66) -> 0 | Z66: =SUM(W66:Y66) -> 0 | AD66: =SUM(AA66:AC66) -> 0 | AH66: =SUM(AE66:AG66) -> 0 | AI66: =SUM(V66,Z66,AD66,AH66) -> 0 | AJ66: Alguns itens foram desconsiderados, pois o peso cadastrado não confere com o sinalizado no estudo, o que gera um penalti e não um ganho no Kaizen apresentado. Por isso valor validado - menor (Lembrando que o volume ainda será revisado, pois temos que trabalhar com o Budget 2026 - solicitado códigos finais ao Felipe) | AN66: =C65 -> 06 - Redução consumo MTP aplicando tolerância mínima | AO66: R | AP66: {=IF(OR(AN66="",AN66=0),"",IF(SUMPRODUCT(($C$55:$C$143=AN66)*($S$54:AG$54<=TODAY())*(ISNUMBER($S$56:AG$144)),$S$56:AG$144)=0,"",SUMPRODUCT(($C$55:$C$143=AN66)*($S$54:AG$54<=TODAY())*(ISNUMBER($S$56:AG$144)),$S$56:AG$144)))}
A67: Redução de custo | B67: GGF | C67: 07 - Balanceamento de carga máquina entre a prensa Gutmnan / Minster | D67: \\192.168.5.20\Departamentos\TI\Projetos\Master 2026\07 - Balanceamento de carga máquina entre a prensa Gutmnan e Minster\07 - Balanceamento de carga máquina entre a prensa Gutmnan e Minster.xlsx | E67: Adaptação do ferramental para transferi-lo para a prensa mister que possui maior cadência (5 ferramentas) | F67: Tersio | J67: 46113 | K67: =IF(J67="", "", 12 - MONTH(J67) + 1) -> 9 | O67: ✓ Concluído | P67: 0.85 | Q67: Previsto | S67: =IFERROR(IF(S$54>=EOMONTH($J67,-1)+1,IF(NOT(ISBLANK($N67)),$N67/12,$I67/12),0),0) -> 0 | T67: =IFERROR(IF(T$54>=EOMONTH($J67,-1)+1,IF(NOT(ISBLANK($N67)),$N67/12,$I67/12),0),0) -> 0 | U67: =IFERROR(IF(U$54>=EOMONTH($J67,-1)+1,IF(NOT(ISBLANK($N67)),$N67/12,$I67/12),0),0) -> 0 | V67: =SUM(S67:U67) -> 0 | W67: =IFERROR(IF(W$54>=EOMONTH($J67,-1)+1,IF(NOT(ISBLANK($N67)),$N67/12,$I67/12),0),0) -> 0 | X67: =IFERROR(IF(X$54>=EOMONTH($J67,-1)+1,IF(NOT(ISBLANK($N67)),$N67/12,$I67/12),0),0) -> 0 | Y67: =IFERROR(IF(Y$54>=EOMONTH($J67,-1)+1,IF(NOT(ISBLANK($N67)),$N67/12,$I67/12),0),0) -> 0 | Z67: =SUM(W67:Y67) -> 0 | AA67: =IFERROR(IF(AA$54>=EOMONTH($J67,-1)+1,IF(NOT(ISBLANK($N67)),$N67/12,$I67/12),0),0) -> 0 | AB67: =IFERROR(IF(AB$54>=EOMONTH($J67,-1)+1,IF(NOT(ISBLANK($N67)),$N67/12,$I67/12),0),0) -> 0 | AC67: =IFERROR(IF(AC$54>=EOMONTH($J67,-1)+1,IF(NOT(ISBLANK($N67)),$N67/12,$I67/12),0),0) -> 0 | AD67: =SUM(AA67:AC67) -> 0 | AE67: =IFERROR(IF(AE$54>=EOMONTH($J67,-1)+1,IF(NOT(ISBLANK($N67)),$N67/12,$I67/12),0),0) -> 0 | AF67: =IFERROR(IF(AF$54>=EOMONTH($J67,-1)+1,IF(NOT(ISBLANK($N67)),$N67/12,$I67/12),0),0) -> 0 | AG67: =IFERROR(IF(AG$54>=EOMONTH($J67,-1)+1,IF(NOT(ISBLANK($N67)),$N67/12,$I67/12),0),0) -> 0 | AH67: =SUM(AE67:AG67) -> 0 | AI67: =SUM(V67,Z67,AD67,AH67) -> 0 | AM67: =N67*AL67 -> 0 | AN67: =C67 -> 07 - Balanceamento de carga máquina entre a prensa Gutmnan / Minster | AO67: P | AP67: {=IF(OR(AN67="",AN67=0),"",IF(SUMPRODUCT(($C$55:$C$128=AN67)*(S$54:$AG$54<EOMONTH(TODAY(),-1)+1)*(ISNUMBER(S$55:$AG$128)),S$55:$AG$128)=0,"",SUMPRODUCT(($C$55:$C$128=AN67)*(S$54:$AG$54<EOMONTH(TODAY(),-1)+1)*(ISNUMBER(S$55:$AG$128)),S$55:$AG$128)))}
Q68: Real | V68: =SUM(S68:U68) -> 0 | Z68: =SUM(W68:Y68) -> 0 | AD68: =SUM(AA68:AC68) -> 0 | AH68: =SUM(AE68:AG68) -> 0 | AI68: =SUM(V68,Z68,AD68,AH68) -> 0 | AN68: =C67 -> 07 - Balanceamento de carga máquina entre a prensa Gutmnan / Minster | AO68: R | AP68: {=IF(OR(AN68="",AN68=0),"",IF(SUMPRODUCT(($C$55:$C$143=AN68)*($S$54:AG$54<=TODAY())*(ISNUMBER($S$56:AG$144)),$S$56:AG$144)=0,"",SUMPRODUCT(($C$55:$C$143=AN68)*($S$54:AG$54<=TODAY())*(ISNUMBER($S$56:AG$144)),$S$56:AG$144)))}
A69: Redução de custo | B69: GGF | C69: 08 - Individualização de zonas de segurança da máquina Baltec | D69: \\192.168.5.20\Departamentos\TI\Projetos\Master 2026\08 - Individualização de zonas de segurança da máquina Baltec\Planta Jarinu- Gestão de Projetos - Individualização de zonas de segurança.xlsx | E69: Indivisualizar zona de segurança da baltec para permitir a produção dos 2 processos simultaneamente. Cravar / Rebitar | F69: Jonathan | K69: =IF(J69="", "", 12 - MONTH(J69) + 1) | O69: ✓ Concluído | P69: 0.7 | Q69: Previsto | S69: =IFERROR(IF(S$54>=EOMONTH($J69,-1)+1,IF(NOT(ISBLANK($N69)),$N69/12,$I69/12),0),0) -> 0 | T69: =IFERROR(IF(T$54>=EOMONTH($J69,-1)+1,IF(NOT(ISBLANK($N69)),$N69/12,$I69/12),0),0) -> 0 | U69: =IFERROR(IF(U$54>=EOMONTH($J69,-1)+1,IF(NOT(ISBLANK($N69)),$N69/12,$I69/12),0),0) -> 0 | V69: =SUM(S69:U69) -> 0 | W69: =IFERROR(IF(W$54>=EOMONTH($J69,-1)+1,IF(NOT(ISBLANK($N69)),$N69/12,$I69/12),0),0) -> 0 | X69: =IFERROR(IF(X$54>=EOMONTH($J69,-1)+1,IF(NOT(ISBLANK($N69)),$N69/12,$I69/12),0),0) -> 0 | Y69: =IFERROR(IF(Y$54>=EOMONTH($J69,-1)+1,IF(NOT(ISBLANK($N69)),$N69/12,$I69/12),0),0) -> 0 | Z69: =SUM(W69:Y69) -> 0 | AA69: =IFERROR(IF(AA$54>=EOMONTH($J69,-1)+1,IF(NOT(ISBLANK($N69)),$N69/12,$I69/12),0),0) -> 0 | AB69: =IFERROR(IF(AB$54>=EOMONTH($J69,-1)+1,IF(NOT(ISBLANK($N69)),$N69/12,$I69/12),0),0) -> 0 | AC69: =IFERROR(IF(AC$54>=EOMONTH($J69,-1)+1,IF(NOT(ISBLANK($N69)),$N69/12,$I69/12),0),0) -> 0 | AD69: =SUM(AA69:AC69) -> 0 | AE69: =IFERROR(IF(AE$54>=EOMONTH($J69,-1)+1,IF(NOT(ISBLANK($N69)),$N69/12,$I69/12),0),0) -> 0 | AF69: =IFERROR(IF(AF$54>=EOMONTH($J69,-1)+1,IF(NOT(ISBLANK($N69)),$N69/12,$I69/12),0),0) -> 0 | AG69: =IFERROR(IF(AG$54>=EOMONTH($J69,-1)+1,IF(NOT(ISBLANK($N69)),$N69/12,$I69/12),0),0) -> 0 | AH69: =SUM(AE69:AG69) -> 0 | AI69: =SUM(V69,Z69,AD69,AH69) -> 0 | AM69: =N69*AL69 -> 0 | AN69: =C69 -> 08 - Individualização de zonas de segurança da máquina Baltec | AO69: P | AP69: {=IF(OR(AN69="",AN69=0),"",IF(SUMPRODUCT(($C$55:$C$128=AN69)*(S$54:$AG$54<EOMONTH(TODAY(),-1)+1)*(ISNUMBER(S$55:$AG$128)),S$55:$AG$128)=0,"",SUMPRODUCT(($C$55:$C$128=AN69)*(S$54:$AG$54<EOMONTH(TODAY(),-1)+1)*(ISNUMBER(S$55:$AG$128)),S$55:$AG$128)))}
Q70: Real | V70: =SUM(S70:U70) -> 0 | Z70: =SUM(W70:Y70) -> 0 | AD70: =SUM(AA70:AC70) -> 0 | AH70: =SUM(AE70:AG70) -> 0 | AI70: =SUM(V70,Z70,AD70,AH70) -> 0 | AN70: =C69 -> 08 - Individualização de zonas de segurança da máquina Baltec | AO70: R | AP70: {=IF(OR(AN70="",AN70=0),"",IF(SUMPRODUCT(($C$55:$C$143=AN70)*($S$54:AG$54<=TODAY())*(ISNUMBER($S$56:AG$144)),$S$56:AG$144)=0,"",SUMPRODUCT(($C$55:$C$143=AN70)*($S$54:AG$54<=TODAY())*(ISNUMBER($S$56:AG$144)),$S$56:AG$144)))}
A71: Redução de custo | B71: GGF | C71: 09 - Aumento de performance dos itens estampados na prensa Minster | E71: Aumentar a cadencia dos itens estampados na prensa Minster | F71: Felipe | K71: =IF(J71="", "", 12 - MONTH(J71) + 1) | O71: 📝 Não iniciado | P71: 0.85 | Q71: Previsto | S71: =IFERROR(IF(S$54>=EOMONTH($J71,-1)+1,IF(NOT(ISBLANK($N71)),$N71/12,$I71/12),0),0) -> 0 | T71: =IFERROR(IF(T$54>=EOMONTH($J71,-1)+1,IF(NOT(ISBLANK($N71)),$N71/12,$I71/12),0),0) -> 0 | U71: =IFERROR(IF(U$54>=EOMONTH($J71,-1)+1,IF(NOT(ISBLANK($N71)),$N71/12,$I71/12),0),0) -> 0 | V71: =SUM(S71:U71) -> 0 | W71: =IFERROR(IF(W$54>=EOMONTH($J71,-1)+1,IF(NOT(ISBLANK($N71)),$N71/12,$I71/12),0),0) -> 0 | X71: =IFERROR(IF(X$54>=EOMONTH($J71,-1)+1,IF(NOT(ISBLANK($N71)),$N71/12,$I71/12),0),0) -> 0 | Y71: =IFERROR(IF(Y$54>=EOMONTH($J71,-1)+1,IF(NOT(ISBLANK($N71)),$N71/12,$I71/12),0),0) -> 0 | Z71: =SUM(W71:Y71) -> 0 | AA71: =IFERROR(IF(AA$54>=EOMONTH($J71,-1)+1,IF(NOT(ISBLANK($N71)),$N71/12,$I71/12),0),0) -> 0 | AB71: =IFERROR(IF(AB$54>=EOMONTH($J71,-1)+1,IF(NOT(ISBLANK($N71)),$N71/12,$I71/12),0),0) -> 0 | AC71: =IFERROR(IF(AC$54>=EOMONTH($J71,-1)+1,IF(NOT(ISBLANK($N71)),$N71/12,$I71/12),0),0) -> 0 | AD71: =SUM(AA71:AC71) -> 0 | AE71: =IFERROR(IF(AE$54>=EOMONTH($J71,-1)+1,IF(NOT(ISBLANK($N71)),$N71/12,$I71/12),0),0) -> 0 | AF71: =IFERROR(IF(AF$54>=EOMONTH($J71,-1)+1,IF(NOT(ISBLANK($N71)),$N71/12,$I71/12),0),0) -> 0 | AG71: =IFERROR(IF(AG$54>=EOMONTH($J71,-1)+1,IF(NOT(ISBLANK($N71)),$N71/12,$I71/12),0),0) -> 0 | AH71: =SUM(AE71:AG71) -> 0 | AI71: =SUM(V71,Z71,AD71,AH71) -> 0 | AM71: =N71*AL71 -> 0 | AN71: =C71 -> 09 - Aumento de performance dos itens estampados na prensa Minster | AO71: P | AP71: {=IF(OR(AN71="",AN71=0),"",IF(SUMPRODUCT(($C$55:$C$128=AN71)*(S$54:$AG$54<EOMONTH(TODAY(),-1)+1)*(ISNUMBER(S$55:$AG$128)),S$55:$AG$128)=0,"",SUMPRODUCT(($C$55:$C$128=AN71)*(S$54:$AG$54<EOMONTH(TODAY(),-1)+1)*(ISNUMBER(S$55:$AG$128)),S$55:$AG$128)))}
Q72: Real | V72: =SUM(S72:U72) -> 0 | Z72: =SUM(W72:Y72) -> 0 | AD72: =SUM(AA72:AC72) -> 0 | AH72: =SUM(AE72:AG72) -> 0 | AI72: =SUM(V72,Z72,AD72,AH72) -> 0 | AN72: =C71 -> 09 - Aumento de performance dos itens estampados na prensa Minster | AO72: R | AP72: {=IF(OR(AN72="",AN72=0),"",IF(SUMPRODUCT(($C$55:$C$143=AN72)*($S$54:AG$54<=TODAY())*(ISNUMBER($S$56:AG$144)),$S$56:AG$144)=0,"",SUMPRODUCT(($C$55:$C$143=AN72)*($S$54:AG$54<=TODAY())*(ISNUMBER($S$56:AG$144)),$S$56:AG$144)))}
A73: Redução de custo | B73: GGF | C73: 10 - Aumento de performance dos itens estampados na prensa Isgec | E73: Aumentar a cadencia dos itens estampados na prensa Isgec 2500tn | F73: Felipe | K73: =IF(J73="", "", 12 - MONTH(J73) + 1) | O73: 📝 Não iniciado | P73: 0.85 | Q73: Previsto | S73: =IFERROR(IF(S$54>=EOMONTH($J73,-1)+1,IF(NOT(ISBLANK($N73)),$N73/12,$I73/12),0),0) -> 0 | T73: =IFERROR(IF(T$54>=EOMONTH($J73,-1)+1,IF(NOT(ISBLANK($N73)),$N73/12,$I73/12),0),0) -> 0 | U73: =IFERROR(IF(U$54>=EOMONTH($J73,-1)+1,IF(NOT(ISBLANK($N73)),$N73/12,$I73/12),0),0) -> 0 | V73: =SUM(S73:U73) -> 0 | W73: =IFERROR(IF(W$54>=EOMONTH($J73,-1)+1,IF(NOT(ISBLANK($N73)),$N73/12,$I73/12),0),0) -> 0 | X73: =IFERROR(IF(X$54>=EOMONTH($J73,-1)+1,IF(NOT(ISBLANK($N73)),$N73/12,$I73/12),0),0) -> 0 | Y73: =IFERROR(IF(Y$54>=EOMONTH($J73,-1)+1,IF(NOT(ISBLANK($N73)),$N73/12,$I73/12),0),0) -> 0 | Z73: =SUM(W73:Y73) -> 0 | AA73: =IFERROR(IF(AA$54>=EOMONTH($J73,-1)+1,IF(NOT(ISBLANK($N73)),$N73/12,$I73/12),0),0) -> 0 | AB73: =IFERROR(IF(AB$54>=EOMONTH($J73,-1)+1,IF(NOT(ISBLANK($N73)),$N73/12,$I73/12),0),0) -> 0 | AC73: =IFERROR(IF(AC$54>=EOMONTH($J73,-1)+1,IF(NOT(ISBLANK($N73)),$N73/12,$I73/12),0),0) -> 0 | AD73: =SUM(AA73:AC73) -> 0 | AE73: =IFERROR(IF(AE$54>=EOMONTH($J73,-1)+1,IF(NOT(ISBLANK($N73)),$N73/12,$I73/12),0),0) -> 0 | AF73: =IFERROR(IF(AF$54>=EOMONTH($J73,-1)+1,IF(NOT(ISBLANK($N73)),$N73/12,$I73/12),0),0) -> 0 | AG73: =IFERROR(IF(AG$54>=EOMONTH($J73,-1)+1,IF(NOT(ISBLANK($N73)),$N73/12,$I73/12),0),0) -> 0 | AH73: =SUM(AE73:AG73) -> 0 | AI73: =SUM(V73,Z73,AD73,AH73) -> 0 | AM73: =N73*AL73 -> 0 | AN73: =C73 -> 10 - Aumento de performance dos itens estampados na prensa Isgec | AO73: P | AP73: {=IF(OR(AN73="",AN73=0),"",IF(SUMPRODUCT(($C$55:$C$128=AN73)*(S$54:$AG$54<EOMONTH(TODAY(),-1)+1)*(ISNUMBER(S$55:$AG$128)),S$55:$AG$128)=0,"",SUMPRODUCT(($C$55:$C$128=AN73)*(S$54:$AG$54<EOMONTH(TODAY(),-1)+1)*(ISNUMBER(S$55:$AG$128)),S$55:$AG$128)))}
Q74: Real | V74: =SUM(S74:U74) -> 0 | Z74: =SUM(W74:Y74) -> 0 | AD74: =SUM(AA74:AC74) -> 0 | AH74: =SUM(AE74:AG74) -> 0 | AI74: =SUM(V74,Z74,AD74,AH74) -> 0 | AN74: =C73 -> 10 - Aumento de performance dos itens estampados na prensa Isgec | AO74: R | AP74: {=IF(OR(AN74="",AN74=0),"",IF(SUMPRODUCT(($C$55:$C$143=AN74)*($S$54:AG$54<=TODAY())*(ISNUMBER($S$56:AG$144)),$S$56:AG$144)=0,"",SUMPRODUCT(($C$55:$C$143=AN74)*($S$54:AG$54<=TODAY())*(ISNUMBER($S$56:AG$144)),$S$56:AG$144)))}
